Workbook

Sheet Dashboard
A1: MtG Deck Master — Dashboard
A2: Live formulas over Master rows 5-601. Refreshes on recalculation. Built 2026-09-03.
Q3: Charts refresh with the tables (Excel recalculates on open).
A4: Deck | B4: Commander | C4: Target | D4: In box (target cards) | E4: Placeholders in box | F4: Box total | G4: Ordered (in transit) | H4: To Buy | I4: Complete % (in hand) | J4: Complete % (incl. ordered) | K4: $ To Buy (Base/Tuned target) | L4: $ Ordered value | M4: Box market value | N4: Target build value | O4: Tuned/B3 adds still To Buy
A5: D1 | B5: Quintorius Kand | C5: =SUM(Master!$M$5:$M$601) | D5: =SUMPRODUCT((Master!$M$5:$M$601<Master!$T$5:$T$601)*Master!$M$5:$M$601+(Master!$M$5:$M$601>=Master!$T$5:$T$601)*Master!$T$5:$T$601) | E5: =SUMPRODUCT((Master!$T$5:$T$601>Master!$M$5:$M$601)*(Master!$T$5:$T$601-Master!$M$5:$M$601)) | F5: =SUM(Master!$T$5:$T$601) | G5: =SUMPRODUCT((Master!$M$5:$M$601>Master!$T$5:$T$601)*(Master!$J$5:$J$601>=(Master!$M$5:$M$601-Master!$T$5:$T$601))*(Master!$M$5:$M$601-Master!$T$5:$T$601)) | H5: =SUMPRODUCT((Master!$M$5:$M$601>Master!$T$5:$T$601)*(Master!$J$5:$J$601<(Master!$M$5:$M$601-Master!$T$5:$T$601))*(Master!$M$5:$M$601-Master!$T$5:$T$601-Master!$J$5:$J$601)) | I5: =IFERROR(D5/C5,0) | J5: =IFERROR((D5+G5)/C5,0) | K5: =SUMPRODUCT((Master!$M$5:$M$601>Master!$T$5:$T$601)*(Master!$J$5:$J$601<(Master!$M$5:$M$601-Master!$T$5:$T$601))*(Master!$M$5:$M$601-Master!$T$5:$T$601-Master!$J$5:$J$601)*Master!$K$5:$K$601) | L5: =SUMPRODUCT((Master!$M$5:$M$601>Master!$T$5:$T$601)*(Master!$J$5:$J$601>=(Master!$M$5:$M$601-Master!$T$5:$T$601))*(Master!$M$5:$M$601-Master!$T$5:$T$601)*Master!$K$5:$K$601) | M5: =SUMPRODUCT(Master!$T$5:$T$601*Master!$K$5:$K$601) | N5: =SUMPRODUCT(Master!$M$5:$M$601*Master!$K$5:$K$601) | O5: =SUMPRODUCT((Master!$M$5:$M$601>0)*(Master!$D$5:$D$601="B3")*(Master!$B$5:$B$601="To Buy"))
A6: D2 | B6: Chulane | C6: =SUM(Master!$N$5:$N$601) | D6: =SUMPRODUCT((Master!$N$5:$N$601<Master!$U$5:$U$601)*Master!$N$5:$N$601+(Master!$N$5:$N$601>=Master!$U$5:$U$601)*Master!$U$5:$U$601) | E6: =SUMPRODUCT((Master!$U$5:$U$601>Master!$N$5:$N$601)*(Master!$U$5:$U$601-Master!$N$5:$N$601)) | F6: =SUM(Master!$U$5:$U$601) | G6: =SUMPRODUCT((Master!$N$5:$N$601>Master!$U$5:$U$601)*(Master!$J$5:$J$601>=(Master!$N$5:$N$601-Master!$U$5:$U$601))*(Master!$N$5:$N$601-Master!$U$5:$U$601)) | H6: =SUMPRODUCT((Master!$N$5:$N$601>Master!$U$5:$U$601)*(Master!$J$5:$J$601<(Master!$N$5:$N$601-Master!$U$5:$U$601))*(Master!$N$5:$N$601-Master!$U$5:$U$601-Master!$J$5:$J$601)) | I6: =IFERROR(D6/C6,0) | J6: =IFERROR((D6+G6)/C6,0) | K6: =SUMPRODUCT((Master!$N$5:$N$601>Master!$U$5:$U$601)*(Master!$J$5:$J$601<(Master!$N$5:$N$601-Master!$U$5:$U$601))*(Master!$N$5:$N$601-Master!$U$5:$U$601-Master!$J$5:$J$601)*Master!$K$5:$K$601) | L6: =SUMPRODUCT((Master!$N$5:$N$601>Master!$U$5:$U$601)*(Master!$J$5:$J$601>=(Master!$N$5:$N$601-Master!$U$5:$U$601))*(Master!$N$5:$N$601-Master!$U$5:$U$601)*Master!$K$5:$K$601) | M6: =SUMPRODUCT(Master!$U$5:$U$601*Master!$K$5:$K$601) | N6: =SUMPRODUCT(Master!$N$5:$N$601*Master!$K$5:$K$601) | O6: =SUMPRODUCT((Master!$N$5:$N$601>0)*(Master!$D$5:$D$601="B3")*(Master!$B$5:$B$601="To Buy"))
A7: D3 | B7: Atraxa | C7: =SUM(Master!$O$5:$O$601) | D7: =SUMPRODUCT((Master!$O$5:$O$601<Master!$V$5:$V$601)*Master!$O$5:$O$601+(Master!$O$5:$O$601>=Master!$V$5:$V$601)*Master!$V$5:$V$601) | E7: =SUMPRODUCT((Master!$V$5:$V$601>Master!$O$5:$O$601)*(Master!$V$5:$V$601-Master!$O$5:$O$601)) | F7: =SUM(Master!$V$5:$V$601) | G7: =SUMPRODUCT((Master!$O$5:$O$601>Master!$V$5:$V$601)*(Master!$J$5:$J$601>=(Master!$O$5:$O$601-Master!$V$5:$V$601))*(Master!$O$5:$O$601-Master!$V$5:$V$601)) | H7: =SUMPRODUCT((Master!$O$5:$O$601>Master!$V$5:$V$601)*(Master!$J$5:$J$601<(Master!$O$5:$O$601-Master!$V$5:$V$601))*(Master!$O$5:$O$601-Master!$V$5:$V$601-Master!$J$5:$J$601)) | I7: =IFERROR(D7/C7,0) | J7: =IFERROR((D7+G7)/C7,0) | K7: =SUMPRODUCT((Master!$O$5:$O$601>Master!$V$5:$V$601)*(Master!$J$5:$J$601<(Master!$O$5:$O$601-Master!$V$5:$V$601))*(Master!$O$5:$O$601-Master!$V$5:$V$601-Master!$J$5:$J$601)*Master!$K$5:$K$601) | L7: =SUMPRODUCT((Master!$O$5:$O$601>Master!$V$5:$V$601)*(Master!$J$5:$J$601>=(Master!$O$5:$O$601-Master!$V$5:$V$601))*(Master!$O$5:$O$601-Master!$V$5:$V$601)*Master!$K$5:$K$601) | M7: =SUMPRODUCT(Master!$V$5:$V$601*Master!$K$5:$K$601) | N7: =SUMPRODUCT(Master!$O$5:$O$601*Master!$K$5:$K$601) | O7: =SUMPRODUCT((Master!$O$5:$O$601>0)*(Master!$D$5:$D$601="B3")*(Master!$B$5:$B$601="To Buy"))
A8: D4 | B8: Betor | C8: =SUM(Master!$P$5:$P$601) | D8: =SUMPRODUCT((Master!$P$5:$P$601<Master!$W$5:$W$601)*Master!$P$5:$P$601+(Master!$P$5:$P$601>=Master!$W$5:$W$601)*Master!$W$5:$W$601) | E8: =SUMPRODUCT((Master!$W$5:$W$601>Master!$P$5:$P$601)*(Master!$W$5:$W$601-Master!$P$5:$P$601)) | F8: =SUM(Master!$W$5:$W$601) | G8: =SUMPRODUCT((Master!$P$5:$P$601>Master!$W$5:$W$601)*(Master!$J$5:$J$601>=(Master!$P$5:$P$601-Master!$W$5:$W$601))*(Master!$P$5:$P$601-Master!$W$5:$W$601)) | H8: =SUMPRODUCT((Master!$P$5:$P$601>Master!$W$5:$W$601)*(Master!$J$5:$J$601<(Master!$P$5:$P$601-Master!$W$5:$W$601))*(Master!$P$5:$P$601-Master!$W$5:$W$601-Master!$J$5:$J$601)) | I8: =IFERROR(D8/C8,0) | J8: =IFERROR((D8+G8)/C8,0) | K8: =SUMPRODUCT((Master!$P$5:$P$601>Master!$W$5:$W$601)*(Master!$J$5:$J$601<(Master!$P$5:$P$601-Master!$W$5:$W$601))*(Master!$P$5:$P$601-Master!$W$5:$W$601-Master!$J$5:$J$601)*Master!$K$5:$K$601) | L8: =SUMPRODUCT((Master!$P$5:$P$601>Master!$W$5:$W$601)*(Master!$J$5:$J$601>=(Master!$P$5:$P$601-Master!$W$5:$W$601))*(Master!$P$5:$P$601-Master!$W$5:$W$601)*Master!$K$5:$K$601) | M8: =SUMPRODUCT(Master!$W$5:$W$601*Master!$K$5:$K$601) | N8: =SUMPRODUCT(Master!$P$5:$P$601*Master!$K$5:$K$601) | O8: =SUMPRODUCT((Master!$P$5:$P$601>0)*(Master!$D$5:$D$601="B3")*(Master!$B$5:$B$601="To Buy"))
A9: D5 | B9: Shadrix | C9: =SUM(Master!$Q$5:$Q$601) | D9: =SUMPRODUCT((Master!$Q$5:$Q$601<Master!$X$5:$X$601)*Master!$Q$5:$Q$601+(Master!$Q$5:$Q$601>=Master!$X$5:$X$601)*Master!$X$5:$X$601) | E9: =SUMPRODUCT((Master!$X$5:$X$601>Master!$Q$5:$Q$601)*(Master!$X$5:$X$601-Master!$Q$5:$Q$601)) | F9: =SUM(Master!$X$5:$X$601) | G9: =SUMPRODUCT((Master!$Q$5:$Q$601>Master!$X$5:$X$601)*(Master!$J$5:$J$601>=(Master!$Q$5:$Q$601-Master!$X$5:$X$601))*(Master!$Q$5:$Q$601-Master!$X$5:$X$601)) | H9: =SUMPRODUCT((Master!$Q$5:$Q$601>Master!$X$5:$X$601)*(Master!$J$5:$J$601<(Master!$Q$5:$Q$601-Master!$X$5:$X$601))*(Master!$Q$5:$Q$601-Master!$X$5:$X$601-Master!$J$5:$J$601)) | I9: =IFERROR(D9/C9,0) | J9: =IFERROR((D9+G9)/C9,0) | K9: =SUMPRODUCT((Master!$Q$5:$Q$601>Master!$X$5:$X$601)*(Master!$J$5:$J$601<(Master!$Q$5:$Q$601-Master!$X$5:$X$601))*(Master!$Q$5:$Q$601-Master!$X$5:$X$601-Master!$J$5:$J$601)*Master!$K$5:$K$601) | L9: =SUMPRODUCT((Master!$Q$5:$Q$601>Master!$X$5:$X$601)*(Master!$J$5:$J$601>=(Master!$Q$5:$Q$601-Master!$X$5:$X$601))*(Master!$Q$5:$Q$601-Master!$X$5:$X$601)*Master!$K$5:$K$601) | M9: =SUMPRODUCT(Master!$X$5:$X$601*Master!$K$5:$K$601) | N9: =SUMPRODUCT(Master!$Q$5:$Q$601*Master!$K$5:$K$601) | O9: =SUMPRODUCT((Master!$Q$5:$Q$601>0)*(Master!$D$5:$D$601="B3")*(Master!$B$5:$B$601="To Buy"))
A10: D6 | B10: Purphoros | C10: =SUM(Master!$R$5:$R$601) | D10: =SUMPRODUCT((Master!$R$5:$R$601<Master!$Y$5:$Y$601)*Master!$R$5:$R$601+(Master!$R$5:$R$601>=Master!$Y$5:$Y$601)*Master!$Y$5:$Y$601) | E10: =SUMPRODUCT((Master!$Y$5:$Y$601>Master!$R$5:$R$601)*(Master!$Y$5:$Y$601-Master!$R$5:$R$601)) | F10: =SUM(Master!$Y$5:$Y$601) | G10: =SUMPRODUCT((Master!$R$5:$R$601>Master!$Y$5:$Y$601)*(Master!$J$5:$J$601>=(Master!$R$5:$R$601-Master!$Y$5:$Y$601))*(Master!$R$5:$R$601-Master!$Y$5:$Y$601)) | H10: =SUMPRODUCT((Master!$R$5:$R$601>Master!$Y$5:$Y$601)*(Master!$J$5:$J$601<(Master!$R$5:$R$601-Master!$Y$5:$Y$601))*(Master!$R$5:$R$601-Master!$Y$5:$Y$601-Master!$J$5:$J$601)) | I10: =IFERROR(D10/C10,0) | J10: =IFERROR((D10+G10)/C10,0) | K10: =SUMPRODUCT((Master!$R$5:$R$601>Master!$Y$5:$Y$601)*(Master!$J$5:$J$601<(Master!$R$5:$R$601-Master!$Y$5:$Y$601))*(Master!$R$5:$R$601-Master!$Y$5:$Y$601-Master!$J$5:$J$601)*Master!$K$5:$K$601) | L10: =SUMPRODUCT((Master!$R$5:$R$601>Master!$Y$5:$Y$601)*(Master!$J$5:$J$601>=(Master!$R$5:$R$601-Master!$Y$5:$Y$601))*(Master!$R$5:$R$601-Master!$Y$5:$Y$601)*Master!$K$5:$K$601) | M10: =SUMPRODUCT(Master!$Y$5:$Y$601*Master!$K$5:$K$601) | N10: =SUMPRODUCT(Master!$R$5:$R$601*Master!$K$5:$K$601) | O10: =SUMPRODUCT((Master!$R$5:$R$601>0)*(Master!$D$5:$D$601="B3")*(Master!$B$5:$B$601="To Buy"))
A11: Total | C11: =SUM(C5:C10) | D11: =SUM(D5:D10) | E11: =SUM(E5:E10) | F11: =SUM(F5:F10) | G11: =SUM(G5:G10) | H11: =SUM(H5:H10) | I11: =IFERROR(D11/C11,0) | J11: =IFERROR((D11+G11)/C11,0) | K11: =SUM(K5:K10) | L11: =SUM(L5:L10) | M11: =SUM(M5:M10) | N11: =SUM(N5:N10) | O11: =SUM(O5:O10)
A13: Role coverage — copies in each deck box that carry a target (Primary Purpose, column AE). "Min" is a sane Commander baseline; red = below min.
A14: Role | B14: Min | C14: D1 Quintorius Kand | D14: D2 Chulane | E14: D3 Atraxa | F14: D4 Betor | G14: D5 Shadrix | H14: D6 Purphoros | I14: Purposes counted
A15: Lands | B15: 36 | C15: =SUMPRODUCT((((Master!$AF$5:$AF$601="Land")+(Master!$AF$5:$AF$601="Flexible Fixing"))>0)*((Master!$M$5:$M$601<Master!$T$5:$T$601)*Master!$M$5:$M$601+(Master!$M$5:$M$601>=Master!$T$5:$T$601)*Master!$T$5:$T$601)) | D15: =SUMPRODUCT((((Master!$AF$5:$AF$601="Land")+(Master!$AF$5:$AF$601="Flexible Fixing"))>0)*((Master!$N$5:$N$601<Master!$U$5:$U$601)*Master!$N$5:$N$601+(Master!$N$5:$N$601>=Master!$U$5:$U$601)*Master!$U$5:$U$601)) | E15: =SUMPRODUCT((((Master!$AF$5:$AF$601="Land")+(Master!$AF$5:$AF$601="Flexible Fixing"))>0)*((Master!$O$5:$O$601<Master!$V$5:$V$601)*Master!$O$5:$O$601+(Master!$O$5:$O$601>=Master!$V$5:$V$601)*Master!$V$5:$V$601)) | F15: =SUMPRODUCT((((Master!$AF$5:$AF$601="Land")+(Master!$AF$5:$AF$601="Flexible Fixing"))>0)*((Master!$P$5:$P$601<Master!$W$5:$W$601)*Master!$P$5:$P$601+(Master!$P$5:$P$601>=Master!$W$5:$W$601)*Master!$W$5:$W$601)) | G15: =SUMPRODUCT((((Master!$AF$5:$AF$601="Land")+(Master!$AF$5:$AF$601="Flexible Fixing"))>0)*((Master!$Q$5:$Q$601<Master!$X$5:$X$601)*Master!$Q$5:$Q$601+(Master!$Q$5:$Q$601>=Master!$X$5:$X$601)*Master!$X$5:$X$601)) | H15: =SUMPRODUCT((((Master!$AF$5:$AF$601="Land")+(Master!$AF$5:$AF$601="Flexible Fixing"))>0)*((Master!$R$5:$R$601<Master!$Y$5:$Y$601)*Master!$R$5:$R$601+(Master!$R$5:$R$601>=Master!$Y$5:$Y$601)*Master!$Y$5:$Y$601)) | I15: Land, Flexible Fixing
A16: Ramp | B16: 10 | C16: =SUMPRODUCT((((Master!$AF$5:$AF$601="Ramp")+(Master!$AF$5:$AF$601="Mana Rock")+(Master!$AF$5:$AF$601="Defender Ramp")+(Master!$AF$5:$AF$601="Cost Reducer"))>0)*((Master!$M$5:$M$601<Master!$T$5:$T$601)*Master!$M$5:$M$601+(Master!$M$5:$M$601>=Master!$T$5:$T$601)*Master!$T$5:$T$601)) | D16: =SUMPRODUCT((((Master!$AF$5:$AF$601="Ramp")+(Master!$AF$5:$AF$601="Mana Rock")+(Master!$AF$5:$AF$601="Defender Ramp")+(Master!$AF$5:$AF$601="Cost Reducer"))>0)*((Master!$N$5:$N$601<Master!$U$5:$U$601)*Master!$N$5:$N$601+(Master!$N$5:$N$601>=Master!$U$5:$U$601)*Master!$U$5:$U$601)) | E16: =SUMPRODUCT((((Master!$AF$5:$AF$601="Ramp")+(Master!$AF$5:$AF$601="Mana Rock")+(Master!$AF$5:$AF$601="Defender Ramp")+(Master!$AF$5:$AF$601="Cost Reducer"))>0)*((Master!$O$5:$O$601<Master!$V$5:$V$601)*Master!$O$5:$O$601+(Master!$O$5:$O$601>=Master!$V$5:$V$601)*Master!$V$5:$V$601)) | F16: =SUMPRODUCT((((Master!$AF$5:$AF$601="Ramp")+(Master!$AF$5:$AF$601="Mana Rock")+(Master!$AF$5:$AF$601="Defender Ramp")+(Master!$AF$5:$AF$601="Cost Reducer"))>0)*((Master!$P$5:$P$601<Master!$W$5:$W$601)*Master!$P$5:$P$601+(Master!$P$5:$P$601>=Master!$W$5:$W$601)*Master!$W$5:$W$601)) | G16: =SUMPRODUCT((((Master!$AF$5:$AF$601="Ramp")+(Master!$AF$5:$AF$601="Mana Rock")+(Master!$AF$5:$AF$601="Defender Ramp")+(Master!$AF$5:$AF$601="Cost Reducer"))>0)*((Master!$Q$5:$Q$601<Master!$X$5:$X$601)*Master!$Q$5:$Q$601+(Master!$Q$5:$Q$601>=Master!$X$5:$X$601)*Master!$X$5:$X$601)) | H16: =SUMPRODUCT((((Master!$AF$5:$AF$601="Ramp")+(Master!$AF$5:$AF$601="Mana Rock")+(Master!$AF$5:$AF$601="Defender Ramp")+(Master!$AF$5:$AF$601="Cost Reducer"))>0)*((Master!$R$5:$R$601<Master!$Y$5:$Y$601)*Master!$R$5:$R$601+(Master!$R$5:$R$601>=Master!$Y$5:$Y$601)*Master!$Y$5:$Y$601)) | I16: Ramp, Mana Rock, Defender Ramp, Cost Reducer
A17: Card draw / advantage | B17: 10 | C17: =SUMPRODUCT((((Master!$AF$5:$AF$601="Card Draw")+(Master!$AF$5:$AF$601="Card Advantage")+(Master!$AF$5:$AF$601="Card Selection")+(Master!$AF$5:$AF$601="Value Engine")+(Master!$AF$5:$AF$601="Discard/Looting")+(Master!$AF$5:$AF$601="Wheel"))>0)*((Master!$M$5:$M$601<Master!$T$5:$T$601)*Master!$M$5:$M$601+(Master!$M$5:$M$601>=Master!$T$5:$T$601)*Master!$T$5:$T$601)) | D17: =SUMPRODUCT((((Master!$AF$5:$AF$601="Card Draw")+(Master!$AF$5:$AF$601="Card Advantage")+(Master!$AF$5:$AF$601="Card Selection")+(Master!$AF$5:$AF$601="Value Engine")+(Master!$AF$5:$AF$601="Discard/Looting")+(Master!$AF$5:$AF$601="Wheel"))>0)*((Master!$N$5:$N$601<Master!$U$5:$U$601)*Master!$N$5:$N$601+(Master!$N$5:$N$601>=Master!$U$5:$U$601)*Master!$U$5:$U$601)) | E17: =SUMPRODUCT((((Master!$AF$5:$AF$601="Card Draw")+(Master!$AF$5:$AF$601="Card Advantage")+(Master!$AF$5:$AF$601="Card Selection")+(Master!$AF$5:$AF$601="Value Engine")+(Master!$AF$5:$AF$601="Discard/Looting")+(Master!$AF$5:$AF$601="Wheel"))>0)*((Master!$O$5:$O$601<Master!$V$5:$V$601)*Master!$O$5:$O$601+(Master!$O$5:$O$601>=Master!$V$5:$V$601)*Master!$V$5:$V$601)) | F17: =SUMPRODUCT((((Master!$AF$5:$AF$601="Card Draw")+(Master!$AF$5:$AF$601="Card Advantage")+(Master!$AF$5:$AF$601="Card Selection")+(Master!$AF$5:$AF$601="Value Engine")+(Master!$AF$5:$AF$601="Discard/Looting")+(Master!$AF$5:$AF$601="Wheel"))>0)*((Master!$P$5:$P$601<Master!$W$5:$W$601)*Master!$P$5:$P$601+(Master!$P$5:$P$601>=Master!$W$5:$W$601)*Master!$W$5:$W$601)) | G17: =SUMPRODUCT((((Master!$AF$5:$AF$601="Card Draw")+(Master!$AF$5:$AF$601="Card Advantage")+(Master!$AF$5:$AF$601="Card Selection")+(Master!$AF$5:$AF$601="Value Engine")+(Master!$AF$5:$AF$601="Discard/Looting")+(Master!$AF$5:$AF$601="Wheel"))>0)*((Master!$Q$5:$Q$601<Master!$X$5:$X$601)*Master!$Q$5:$Q$601+(Master!$Q$5:$Q$601>=Master!$X$5:$X$601)*Master!$X$5:$X$601)) | H17: =SUMPRODUCT((((Master!$AF$5:$AF$601="Card Draw")+(Master!$AF$5:$AF$601="Card Advantage")+(Master!$AF$5:$AF$601="Card Selection")+(Master!$AF$5:$AF$601="Value Engine")+(Master!$AF$5:$AF$601="Discard/Looting")+(Master!$AF$5:$AF$601="Wheel"))>0)*((Master!$R$5:$R$601<Master!$Y$5:$Y$601)*Master!$R$5:$R$601+(Master!$R$5:$R$601>=Master!$Y$5:$Y$601)*Master!$Y$5:$Y$601)) | I17: Card Draw, Card Advantage, Card Selection, Value Engine, Discard/Looting, Wheel
A18: Removal / interaction | B18: 8 | C18: =SUMPRODUCT((((Master!$AF$5:$AF$601="Removal")+(Master!$AF$5:$AF$601="Artifact/Enchantment Removal")+(Master!$AF$5:$AF$601="Interaction")+(Master!$AF$5:$AF$601="Burn")+(Master!$AF$5:$AF$601="Graveyard Hate")+(Master!$AF$5:$AF$601="Stax/Tax"))>0)*((Master!$M$5:$M$601<Master!$T$5:$T$601)*Master!$M$5:$M$601+(Master!$M$5:$M$601>=Master!$T$5:$T$601)*Master!$T$5:$T$601)) | D18: =SUMPRODUCT((((Master!$AF$5:$AF$601="Removal")+(Master!$AF$5:$AF$601="Artifact/Enchantment Removal")+(Master!$AF$5:$AF$601="Interaction")+(Master!$AF$5:$AF$601="Burn")+(Master!$AF$5:$AF$601="Graveyard Hate")+(Master!$AF$5:$AF$601="Stax/Tax"))>0)*((Master!$N$5:$N$601<Master!$U$5:$U$601)*Master!$N$5:$N$601+(Master!$N$5:$N$601>=Master!$U$5:$U$601)*Master!$U$5:$U$601)) | E18: =SUMPRODUCT((((Master!$AF$5:$AF$601="Removal")+(Master!$AF$5:$AF$601="Artifact/Enchantment Removal")+(Master!$AF$5:$AF$601="Interaction")+(Master!$AF$5:$AF$601="Burn")+(Master!$AF$5:$AF$601="Graveyard Hate")+(Master!$AF$5:$AF$601="Stax/Tax"))>0)*((Master!$O$5:$O$601<Master!$V$5:$V$601)*Master!$O$5:$O$601+(Master!$O$5:$O$601>=Master!$V$5:$V$601)*Master!$V$5:$V$601)) | F18: =SUMPRODUCT((((Master!$AF$5:$AF$601="Removal")+(Master!$AF$5:$AF$601="Artifact/Enchantment Removal")+(Master!$AF$5:$AF$601="Interaction")+(Master!$AF$5:$AF$601="Burn")+(Master!$AF$5:$AF$601="Graveyard Hate")+(Master!$AF$5:$AF$601="Stax/Tax"))>0)*((Master!$P$5:$P$601<Master!$W$5:$W$601)*Master!$P$5:$P$601+(Master!$P$5:$P$601>=Master!$W$5:$W$601)*Master!$W$5:$W$601)) | G18: =SUMPRODUCT((((Master!$AF$5:$AF$601="Removal")+(Master!$AF$5:$AF$601="Artifact/Enchantment Removal")+(Master!$AF$5:$AF$601="Interaction")+(Master!$AF$5:$AF$601="Burn")+(Master!$AF$5:$AF$601="Graveyard Hate")+(Master!$AF$5:$AF$601="Stax/Tax"))>0)*((Master!$Q$5:$Q$601<Master!$X$5:$X$601)*Master!$Q$5:$Q$601+(Master!$Q$5:$Q$601>=Master!$X$5:$X$601)*Master!$X$5:$X$601)) | H18: =SUMPRODUCT((((Master!$AF$5:$AF$601="Removal")+(Master!$AF$5:$AF$601="Artifact/Enchantment Removal")+(Master!$AF$5:$AF$601="Interaction")+(Master!$AF$5:$AF$601="Burn")+(Master!$AF$5:$AF$601="Graveyard Hate")+(Master!$AF$5:$AF$601="Stax/Tax"))>0)*((Master!$R$5:$R$601<Master!$Y$5:$Y$601)*Master!$R$5:$R$601+(Master!$R$5:$R$601>=Master!$Y$5:$Y$601)*Master!$Y$5:$Y$601)) | I18: Removal, Artifact/Enchantment Removal, Interaction, Burn, Graveyard Hate, Stax/Tax
A19: Board wipes | B19: 2 | C19: =SUMPRODUCT((((Master!$AF$5:$AF$601="Board Wipe"))>0)*((Master!$M$5:$M$601<Master!$T$5:$T$601)*Master!$M$5:$M$601+(Master!$M$5:$M$601>=Master!$T$5:$T$601)*Master!$T$5:$T$601)) | D19: =SUMPRODUCT((((Master!$AF$5:$AF$601="Board Wipe"))>0)*((Master!$N$5:$N$601<Master!$U$5:$U$601)*Master!$N$5:$N$601+(Master!$N$5:$N$601>=Master!$U$5:$U$601)*Master!$U$5:$U$601)) | E19: =SUMPRODUCT((((Master!$AF$5:$AF$601="Board Wipe"))>0)*((Master!$O$5:$O$601<Master!$V$5:$V$601)*Master!$O$5:$O$601+(Master!$O$5:$O$601>=Master!$V$5:$V$601)*Master!$V$5:$V$601)) | F19: =SUMPRODUCT((((Master!$AF$5:$AF$601="Board Wipe"))>0)*((Master!$P$5:$P$601<Master!$W$5:$W$601)*Master!$P$5:$P$601+(Master!$P$5:$P$601>=Master!$W$5:$W$601)*Master!$W$5:$W$601)) | G19: =SUMPRODUCT((((Master!$AF$5:$AF$601="Board Wipe"))>0)*((Master!$Q$5:$Q$601<Master!$X$5:$X$601)*Master!$Q$5:$Q$601+(Master!$Q$5:$Q$601>=Master!$X$5:$X$601)*Master!$X$5:$X$601)) | H19: =SUMPRODUCT((((Master!$AF$5:$AF$601="Board Wipe"))>0)*((Master!$R$5:$R$601<Master!$Y$5:$Y$601)*Master!$R$5:$R$601+(Master!$R$5:$R$601>=Master!$Y$5:$Y$601)*Master!$Y$5:$Y$601)) | I19: Board Wipe
A20: Protection | B20: 3 | C20: =SUMPRODUCT((((Master!$AF$5:$AF$601="Protection"))>0)*((Master!$M$5:$M$601<Master!$T$5:$T$601)*Master!$M$5:$M$601+(Master!$M$5:$M$601>=Master!$T$5:$T$601)*Master!$T$5:$T$601)) | D20: =SUMPRODUCT((((Master!$AF$5:$AF$601="Protection"))>0)*((Master!$N$5:$N$601<Master!$U$5:$U$601)*Master!$N$5:$N$601+(Master!$N$5:$N$601>=Master!$U$5:$U$601)*Master!$U$5:$U$601)) | E20: =SUMPRODUCT((((Master!$AF$5:$AF$601="Protection"))>0)*((Master!$O$5:$O$601<Master!$V$5:$V$601)*Master!$O$5:$O$601+(Master!$O$5:$O$601>=Master!$V$5:$V$601)*Master!$V$5:$V$601)) | F20: =SUMPRODUCT((((Master!$AF$5:$AF$601="Protection"))>0)*((Master!$P$5:$P$601<Master!$W$5:$W$601)*Master!$P$5:$P$601+(Master!$P$5:$P$601>=Master!$W$5:$W$601)*Master!$W$5:$W$601)) | G20: =SUMPRODUCT((((Master!$AF$5:$AF$601="Protection"))>0)*((Master!$Q$5:$Q$601<Master!$X$5:$X$601)*Master!$Q$5:$Q$601+(Master!$Q$5:$Q$601>=Master!$X$5:$X$601)*Master!$X$5:$X$601)) | H20: =SUMPRODUCT((((Master!$AF$5:$AF$601="Protection"))>0)*((Master!$R$5:$R$601<Master!$Y$5:$Y$601)*Master!$R$5:$R$601+(Master!$R$5:$R$601>=Master!$Y$5:$Y$601)*Master!$Y$5:$Y$601)) | I20: Protection
A21: Recursion / reanimation | B21: 3 | C21: =SUMPRODUCT((((Master!$AF$5:$AF$601="Recursion")+(Master!$AF$5:$AF$601="Reanimation"))>0)*((Master!$M$5:$M$601<Master!$T$5:$T$601)*Master!$M$5:$M$601+(Master!$M$5:$M$601>=Master!$T$5:$T$601)*Master!$T$5:$T$601)) | D21: =SUMPRODUCT((((Master!$AF$5:$AF$601="Recursion")+(Master!$AF$5:$AF$601="Reanimation"))>0)*((Master!$N$5:$N$601<Master!$U$5:$U$601)*Master!$N$5:$N$601+(Master!$N$5:$N$601>=Master!$U$5:$U$601)*Master!$U$5:$U$601)) | E21: =SUMPRODUCT((((Master!$AF$5:$AF$601="Recursion")+(Master!$AF$5:$AF$601="Reanimation"))>0)*((Master!$O$5:$O$601<Master!$V$5:$V$601)*Master!$O$5:$O$601+(Master!$O$5:$O$601>=Master!$V$5:$V$601)*Master!$V$5:$V$601)) | F21: =SUMPRODUCT((((Master!$AF$5:$AF$601="Recursion")+(Master!$AF$5:$AF$601="Reanimation"))>0)*((Master!$P$5:$P$601<Master!$W$5:$W$601)*Master!$P$5:$P$601+(Master!$P$5:$P$601>=Master!$W$5:$W$601)*Master!$W$5:$W$601)) | G21: =SUMPRODUCT((((Master!$AF$5:$AF$601="Recursion")+(Master!$AF$5:$AF$601="Reanimation"))>0)*((Master!$Q$5:$Q$601<Master!$X$5:$X$601)*Master!$Q$5:$Q$601+(Master!$Q$5:$Q$601>=Master!$X$5:$X$601)*Master!$X$5:$X$601)) | H21: =SUMPRODUCT((((Master!$AF$5:$AF$601="Recursion")+(Master!$AF$5:$AF$601="Reanimation"))>0)*((Master!$R$5:$R$601<Master!$Y$5:$Y$601)*Master!$R$5:$R$601+(Master!$R$5:$R$601>=Master!$Y$5:$Y$601)*Master!$Y$5:$Y$601)) | I21: Recursion, Reanimation
A22: Win / payoff | B22: 0 | C22: =SUMPRODUCT((((Master!$AF$5:$AF$601="Finisher")+(Master!$AF$5:$AF$601="Drain Payoff")+(Master!$AF$5:$AF$601="Toughness Payoff")+(Master!$AF$5:$AF$601="Counters Payoff")+(Master!$AF$5:$AF$601="Proliferate")+(Master!$AF$5:$AF$601="Aristocrats Payoff")+(Master!$AF$5:$AF$601="Lord/Anthem")+(Master!$AF$5:$AF$601="Token Producer")+(Master!$AF$5:$AF$601="Sacrifice Outlet")+(Master!$AF$5:$AF$601="Haste Enabler")+(Master!$AF$5:$AF$601="Blink")+(Master!$AF$5:$AF$601="Lifegain")+(Master!$AF$5:$AF$601="Combat Trick")+(Master!$AF$5:$AF$601="Evasion")+(Master!$AF$5:$AF$601="Copy/Clone")+(Master!$AF$5:$AF$601="Mana Sink")+(Master!$AF$5:$AF$601="Tutor")+(Master!$AF$5:$AF$601="Utility Creature"))>0)*((Master!$M$5:$M$601<Master!$T$5:$T$601)*Master!$M$5:$M$601+(Master!$M$5:$M$601>=Master!$T$5:$T$601)*Master!$T$5:$T$601)) | D22: =SUMPRODUCT((((Master!$AF$5:$AF$601="Finisher")+(Master!$AF$5:$AF$601="Drain Payoff")+(Master!$AF$5:$AF$601="Toughness Payoff")+(Master!$AF$5:$AF$601="Counters Payoff")+(Master!$AF$5:$AF$601="Proliferate")+(Master!$AF$5:$AF$601="Aristocrats Payoff")+(Master!$AF$5:$AF$601="Lord/Anthem")+(Master!$AF$5:$AF$601="Token Producer")+(Master!$AF$5:$AF$601="Sacrifice Outlet")+(Master!$AF$5:$AF$601="Haste Enabler")+(Master!$AF$5:$AF$601="Blink")+(Master!$AF$5:$AF$601="Lifegain")+(Master!$AF$5:$AF$601="Combat Trick")+(Master!$AF$5:$AF$601="Evasion")+(Master!$AF$5:$AF$601="Copy/Clone")+(Master!$AF$5:$AF$601="Mana Sink")+(Master!$AF$5:$AF$601="Tutor")+(Master!$AF$5:$AF$601="Utility Creature"))>0)*((Master!$N$5:$N$601<Master!$U$5:$U$601)*Master!$N$5:$N$601+(Master!$N$5:$N$601>=Master!$U$5:$U$601)*Master!$U$5:$U$601)) | E22: =SUMPRODUCT((((Master!$AF$5:$AF$601="Finisher")+(Master!$AF$5:$AF$601="Drain Payoff")+(Master!$AF$5:$AF$601="Toughness Payoff")+(Master!$AF$5:$AF$601="Counters Payoff")+(Master!$AF$5:$AF$601="Proliferate")+(Master!$AF$5:$AF$601="Aristocrats Payoff")+(Master!$AF$5:$AF$601="Lord/Anthem")+(Master!$AF$5:$AF$601="Token Producer")+(Master!$AF$5:$AF$601="Sacrifice Outlet")+(Master!$AF$5:$AF$601="Haste Enabler")+(Master!$AF$5:$AF$601="Blink")+(Master!$AF$5:$AF$601="Lifegain")+(Master!$AF$5:$AF$601="Combat Trick")+(Master!$AF$5:$AF$601="Evasion")+(Master!$AF$5:$AF$601="Copy/Clone")+(Master!$AF$5:$AF$601="Mana Sink")+(Master!$AF$5:$AF$601="Tutor")+(Master!$AF$5:$AF$601="Utility Creature"))>0)*((Master!$O$5:$O$601<Master!$V$5:$V$601)*Master!$O$5:$O$601+(Master!$O$5:$O$601>=Master!$V$5:$V$601)*Master!$V$5:$V$601)) | F22: =SUMPRODUCT((((Master!$AF$5:$AF$601="Finisher")+(Master!$AF$5:$AF$601="Drain Payoff")+(Master!$AF$5:$AF$601="Toughness Payoff")+(Master!$AF$5:$AF$601="Counters Payoff")+(Master!$AF$5:$AF$601="Proliferate")+(Master!$AF$5:$AF$601="Aristocrats Payoff")+(Master!$AF$5:$AF$601="Lord/Anthem")+(Master!$AF$5:$AF$601="Token Producer")+(Master!$AF$5:$AF$601="Sacrifice Outlet")+(Master!$AF$5:$AF$601="Haste Enabler")+(Master!$AF$5:$AF$601="Blink")+(Master!$AF$5:$AF$601="Lifegain")+(Master!$AF$5:$AF$601="Combat Trick")+(Master!$AF$5:$AF$601="Evasion")+(Master!$AF$5:$AF$601="Copy/Clone")+(Master!$AF$5:$AF$601="Mana Sink")+(Master!$AF$5:$AF$601="Tutor")+(Master!$AF$5:$AF$601="Utility Creature"))>0)*((Master!$P$5:$P$601<Master!$W$5:$W$601)*Master!$P$5:$P$601+(Master!$P$5:$P$601>=Master!$W$5:$W$601)*Master!$W$5:$W$601)) | G22: =SUMPRODUCT((((Master!$AF$5:$AF$601="Finisher")+(Master!$AF$5:$AF$601="Drain Payoff")+(Master!$AF$5:$AF$601="Toughness Payoff")+(Master!$AF$5:$AF$601="Counters Payoff")+(Master!$AF$5:$AF$601="Proliferate")+(Master!$AF$5:$AF$601="Aristocrats Payoff")+(Master!$AF$5:$AF$601="Lord/Anthem")+(Master!$AF$5:$AF$601="Token Producer")+(Master!$AF$5:$AF$601="Sacrifice Outlet")+(Master!$AF$5:$AF$601="Haste Enabler")+(Master!$AF$5:$AF$601="Blink")+(Master!$AF$5:$AF$601="Lifegain")+(Master!$AF$5:$AF$601="Combat Trick")+(Master!$AF$5:$AF$601="Evasion")+(Master!$AF$5:$AF$601="Copy/Clone")+(Master!$AF$5:$AF$601="Mana Sink")+(Master!$AF$5:$AF$601="Tutor")+(Master!$AF$5:$AF$601="Utility Creature"))>0)*((Master!$Q$5:$Q$601<Master!$X$5:$X$601)*Master!$Q$5:$Q$601+(Master!$Q$5:$Q$601>=Master!$X$5:$X$601)*Master!$X$5:$X$601)) | H22: =SUMPRODUCT((((Master!$AF$5:$AF$601="Finisher")+(Master!$AF$5:$AF$601="Drain Payoff")+(Master!$AF$5:$AF$601="Toughness Payoff")+(Master!$AF$5:$AF$601="Counters Payoff")+(Master!$AF$5:$AF$601="Proliferate")+(Master!$AF$5:$AF$601="Aristocrats Payoff")+(Master!$AF$5:$AF$601="Lord/Anthem")+(Master!$AF$5:$AF$601="Token Producer")+(Master!$AF$5:$AF$601="Sacrifice Outlet")+(Master!$AF$5:$AF$601="Haste Enabler")+(Master!$AF$5:$AF$601="Blink")+(Master!$AF$5:$AF$601="Lifegain")+(Master!$AF$5:$AF$601="Combat Trick")+(Master!$AF$5:$AF$601="Evasion")+(Master!$AF$5:$AF$601="Copy/Clone")+(Master!$AF$5:$AF$601="Mana Sink")+(Master!$AF$5:$AF$601="Tutor")+(Master!$AF$5:$AF$601="Utility Creature"))>0)*((Master!$R$5:$R$601<Master!$Y$5:$Y$601)*Master!$R$5:$R$601+(Master!$R$5:$R$601>=Master!$Y$5:$Y$601)*Master!$Y$5:$Y$601)) | I22: Finisher, Drain Payoff, Toughness Payoff, Counters Payoff, Proliferate, Aristocrats Payoff, Lord/Anthem, Token Producer, Sacrifice Outlet, Haste Enabler, Blink, Lifegain, Combat Trick, Evasion, Copy/Clone, Mana Sink, Tutor, Utility Creature
A24: Inventory and status
A25: Status | B25: Rows | C25: Meaning
A26: In Hand | B26: =COUNTIF(Master!$B$5:$B$601,"In Hand") | C26: Targeted and owned in full
A27: Ordered | B27: =COUNTIF(Master!$B$5:$B$601,"Ordered") | C27: Short copies are on order (I >= shortfall)
A28: To Buy | B28: =COUNTIF(Master!$B$5:$B$601,"To Buy") | C28: Targeted, not owned, not ordered
A29: Bench | B29: =COUNTIF(Master!$B$5:$B$601,"Bench") | C29: Owned, no target, sitting in the bench box
A30: Bench-Sub | B30: =COUNTIF(Master!$B$5:$B$601,"Bench-Sub") | C30: Owned, no target, sitting in a deck box as a placeholder
A31: Extra | B31: =COUNTIF(Master!$B$5:$B$601,"Extra") | C31: Owned more copies than targeted
A32: Extra-Sub | B32: =COUNTIF(Master!$B$5:$B$601,"Extra-Sub") | C32: Extra copy sitting in a deck box as a placeholder
A33: B3 Option | B33: =COUNTIF(Master!$B$5:$B$601,"B3 Option") | C33: Max-tier candidate, not targeted or owned
A34: Remove | B34: =COUNTIF(Master!$B$5:$B$601,"Remove") | C34: No target, not owned — superseded row, safe to delete
A36: Money
A37: Cards owned (all copies) | B37: =SUM(Master!$F$5:$F$601)
A38: Bench copies (B-A) | B38: =SUM(Master!$Z$5:$Z$601)
A39: Bench market value | B39: =SUMPRODUCT(Master!$Z$5:$Z$601*Master!$K$5:$K$601)
A40: Copies on order | B40: =SUM(Master!$J$5:$J$601)
A41: Value of copies on order | B41: =SUMPRODUCT(Master!$J$5:$J$601*Master!$K$5:$K$601)
A42: $ To Buy, all decks (Master K) | B42: =SUM(Master!$L$5:$L$601)
A43: Value of all six target builds | B43: =SUM(N5:N10)
A44: Value of everything owned | B44: =SUMPRODUCT(Master!$F$5:$F$601*Master!$K$5:$K$601)
A45: Deck value cap (each) | B45: 225
A46: B3 Option cards listed | B46: =COUNTIF(Master!$B$5:$B$601,"B3 Option")
A47: B3 Option total cost | B47: =SUMPRODUCT((Master!$B$5:$B$601="B3 Option")*Master!$K$5:$K$601)
A50: Checks
A51: Deck targets all = 100 | B51: =IF(AND(C5=100,C6=100,C7=100,C8=100,C9=100,C10=100),"OK","CHECK")
A52: Nonbasic targeted twice in one deck | B52: =SUMPRODUCT((Master!$M$5:$M$601>1)+(Master!$N$5:$N$601>1)+(Master!$O$5:$O$601>1)+(Master!$P$5:$P$601>1)+(Master!$Q$5:$Q$601>1)+(Master!$R$5:$R$601>1)-(LEFT(Master!$AA$5:$AA$601,5)="Basic")*6*((Master!$M$5:$M$601>1)+(Master!$N$5:$N$601>1)+(Master!$O$5:$O$601>1)+(Master!$P$5:$P$601>1)+(Master!$Q$5:$Q$601>1)+(Master!$R$5:$R$601>1))/6)
A53: Rows still marked In cart | B53: =COUNTIF(Master!$AJ$5:$AJ$601,"In cart:*")

Sheet Master
T1: 4 | U1: 13 | V1: 12 | W1: 37 | X1: 42 | Y1: 59
M2: =SUM(M$5:M$601) | N2: =SUM(N$5:N$601) | O2: =SUM(O$5:O$601) | P2: =SUM(P$5:P$601) | Q2: =SUM(Q$5:Q$601) | R2: =SUM(R$5:R$601) | T2: =SUM(T$5:T$601) | U2: =SUM(U$5:U$601) | V2: =SUM(V$5:V$601) | W2: =SUM(W$5:W$601) | X2: =SUM(X$5:X$601) | Y2: =SUM(Y$5:Y$601)
F3: =SUM(F5:F601) | J3: =SUM(J5:J601) | K3: =SUM(K5:K83) | M3: Target | R3: Bnch | S3: =SUM(S5:S601) | T3: Actual | Y3: Bnch | Z3: =SUM(Z5:Z601)
A4: Card | B4: Status | C4: My To Buy List | D4: Bracket | E4: Qty | F4: Own | G4: Extra (Bench) | H4: Buy Count | I4: In Cart | J4: Ordered | K4: $ Each | L4: $ To Buy | M4: D1-T | N4: D2-T | O4: D3-T | P4: D4-T | Q4: D5-T | R4: D6-T | S4: B-T | T4: D1-A | U4: D2-A | V4: D3-A | W4: D4-A | X4: D5-A | Y4: D6-A | Z4: B-A | AA4: Type | AB4: Sub-Type | AC4: Color | AD4: MV | AE4: Series | AF4: Primary Purpose | AG4: Primary Mechanic | AH4: Secondary Mechanic | AI4: Tertiary Mechanic | AJ4: Notes | AK4: Moves
A5: Elas il-Kor, Sadistic Pilgrim | B5: =IF(AND(F5<>0,E5=F5),"In Hand",IF(AND(E5<>0,E5<F5,SUM(M5:R5)=0,SUM(T5:Y5)>0),"Extra-Sub",IF(AND(E5=0,E5<F5,SUM(M5:R5)=0,SUM(T5:Y5)>0),"Bench-Sub",IF(AND(E5=0,F5>0),"Bench",IF(E5<F5,"Extra",IF(AND(J5="",E5>F5),"To Buy",IF(SUM(J5,F5)<E5,"To Buy",IF(AND(SUM(J5,F5)>=E5,J5<>""),"Ordered",IF(AND(E5=0,F5=0,D5="B3"),"B3 Option",IF(AND(E5=0,F5=0),"Remove","To Buy")))))))))) | C5: 1 | D5: B2 | E5: =SUM(M5:S5) | F5: =SUM(T5:Z5) | G5: =IF((F5-E5)>=0,F5-E5,0) | H5: =MAX(0,$E5-$F5-$J5) | K5: 3.11 | L5: =IF(AND($H5>0,ISNUMBER($K5)),$H5*$K5,0) | Q5: 1 | S5: =IF(AND(J5<>"",SUM(M5:R5)=0),J5,"") | AA5: Legendary Creature | AB5: Phyrexian Kor Cleric | AC5: Multi | AD5: 2 | AE5: Dominaria United | AF5: Drain Payoff | AG5: Gains you 1 life whenever another creature you control enters | AH5: Each opponent loses 1 life whenever another creature you control dies | AI5: Deathtouch body
A6: Fervor | B6: =IF(AND(F6<>0,E6=F6),"In Hand",IF(AND(E6<>0,E6<F6,SUM(M6:R6)=0,SUM(T6:Y6)>0),"Extra-Sub",IF(AND(E6=0,E6<F6,SUM(M6:R6)=0,SUM(T6:Y6)>0),"Bench-Sub",IF(AND(E6=0,F6>0),"Bench",IF(E6<F6,"Extra",IF(AND(J6="",E6>F6),"To Buy",IF(SUM(J6,F6)<E6,"To Buy",IF(AND(SUM(J6,F6)>=E6,J6<>""),"Ordered",IF(AND(E6=0,F6=0,D6="B3"),"B3 Option",IF(AND(E6=0,F6=0),"Remove","To Buy")))))))))) | C6: 1 | D6: B3 | E6: =SUM(M6:S6) | F6: =SUM(T6:Z6) | G6: =IF((F6-E6)>=0,F6-E6,0) | H6: =MAX(0,$E6-$F6-$J6) | K6: 4.21 | L6: =IF(AND($H6>0,ISNUMBER($K6)),$H6*$K6,0) | R6: 1 | S6: =IF(AND(J6<>"",SUM(M6:R6)=0),J6,"") | AA6: Enchantment | AC6: R | AD6: 3 | AE6: Weatherlight | AF6: Tuned add | AG6: Creatures you control have haste. (They can attack and {T} as soon as they come under your control.) | AJ6: D6 Tuned add; targeted 2026-09-02; replaces Akoum Hellhound | AK6: [T] targeted D6 (Tuned add, replaces Akoum Hellhound); [A later] ->D6 when bought
A7: Kambal, Consul of Allocation | B7: =IF(AND(F7<>0,E7=F7),"In Hand",IF(AND(E7<>0,E7<F7,SUM(M7:R7)=0,SUM(T7:Y7)>0),"Extra-Sub",IF(AND(E7=0,E7<F7,SUM(M7:R7)=0,SUM(T7:Y7)>0),"Bench-Sub",IF(AND(E7=0,F7>0),"Bench",IF(E7<F7,"Extra",IF(AND(J7="",E7>F7),"To Buy",IF(SUM(J7,F7)<E7,"To Buy",IF(AND(SUM(J7,F7)>=E7,J7<>""),"Ordered",IF(AND(E7=0,F7=0,D7="B3"),"B3 Option",IF(AND(E7=0,F7=0),"Remove","To Buy")))))))))) | C7: 1 | D7: B3 | E7: =SUM(M7:S7) | F7: =SUM(T7:Z7) | G7: =IF((F7-E7)>=0,F7-E7,0) | H7: =MAX(0,$E7-$F7-$J7) | K7: 10.17 | L7: =IF(AND($H7>0,ISNUMBER($K7)),$H7*$K7,0) | Q7: 1 | S7: =IF(AND(J7<>"",SUM(M7:R7)=0),J7,"") | AA7: Legendary Creature | AB7: Human Advisor | AC7: BW | AD7: 3 | AE7: Kaladesh | AF7: Tuned add | AG7: Whenever an opponent casts a noncreature spell, that player loses 2 life and you gain 2 life. | AJ7: D5 Tuned add; targeted 2026-09-02; replaces Great Fierce Bee | AK7: [T] targeted D5 (Tuned add, replaces Great Fierce Bee); [A later] ->D5 when bought
A8: Mentor of the Meek | B8: =IF(AND(F8<>0,E8=F8),"In Hand",IF(AND(E8<>0,E8<F8,SUM(M8:R8)=0,SUM(T8:Y8)>0),"Extra-Sub",IF(AND(E8=0,E8<F8,SUM(M8:R8)=0,SUM(T8:Y8)>0),"Bench-Sub",IF(AND(E8=0,F8>0),"Bench",IF(E8<F8,"Extra",IF(AND(J8="",E8>F8),"To Buy",IF(SUM(J8,F8)<E8,"To Buy",IF(AND(SUM(J8,F8)>=E8,J8<>""),"Ordered",IF(AND(E8=0,F8=0,D8="B3"),"B3 Option",IF(AND(E8=0,F8=0),"Remove","To Buy")))))))))) | C8: 1 | D8: B3 | E8: =SUM(M8:S8) | F8: =SUM(T8:Z8) | G8: =IF((F8-E8)>=0,F8-E8,0) | H8: =MAX(0,$E8-$F8-$J8) | K8: 4.95 | L8: =IF(AND($H8>0,ISNUMBER($K8)),$H8*$K8,0) | Q8: 1 | S8: =IF(AND(J8<>"",SUM(M8:R8)=0),J8,"") | AA8: Creature | AB8: Human Soldier | AC8: W | AD8: 3 | AE8: Innistrad | AF8: Tuned add | AG8: Whenever another creature you control with power 2 or less enters, you may pay {1}. If you do, draw a card. | AJ8: D5 Tuned add; targeted 2026-09-02; replaces Hemlock Vial | AK8: [T] targeted D5 (Tuned add, replaces Hemlock Vial); [A later] ->D5 when bought
A9: Molten Echoes | B9: =IF(AND(F9<>0,E9=F9),"In Hand",IF(AND(E9<>0,E9<F9,SUM(M9:R9)=0,SUM(T9:Y9)>0),"Extra-Sub",IF(AND(E9=0,E9<F9,SUM(M9:R9)=0,SUM(T9:Y9)>0),"Bench-Sub",IF(AND(E9=0,F9>0),"Bench",IF(E9<F9,"Extra",IF(AND(J9="",E9>F9),"To Buy",IF(SUM(J9,F9)<E9,"To Buy",IF(AND(SUM(J9,F9)>=E9,J9<>""),"Ordered",IF(AND(E9=0,F9=0,D9="B3"),"B3 Option",IF(AND(E9=0,F9=0),"Remove","To Buy")))))))))) | C9: 1 | D9: B3 | E9: =SUM(M9:S9) | F9: =SUM(T9:Z9) | G9: =IF((F9-E9)>=0,F9-E9,0) | H9: =MAX(0,$E9-$F9-$J9) | K9: 9.51 | L9: =IF(AND($H9>0,ISNUMBER($K9)),$H9*$K9,0) | R9: 1 | S9: =IF(AND(J9<>"",SUM(M9:R9)=0),J9,"") | AA9: Enchantment | AC9: R | AD9: 4 | AE9: Commander 2020 | AF9: Tuned add | AG9: As this enchantment enters, choose a creature type. Whenever a nontoken creature you control of the chosen type enters, | AJ9: D6 Tuned add; targeted 2026-09-02; replaces Monastery Raid | AK9: [T] targeted D6 (Tuned add, replaces Monastery Raid); [A later] ->D6 when bought
A10: Night's Whisper | B10: =IF(AND(F10<>0,E10=F10),"In Hand",IF(AND(E10<>0,E10<F10,SUM(M10:R10)=0,SUM(T10:Y10)>0),"Extra-Sub",IF(AND(E10=0,E10<F10,SUM(M10:R10)=0,SUM(T10:Y10)>0),"Bench-Sub",IF(AND(E10=0,F10>0),"Bench",IF(E10<F10,"Extra",IF(AND(J10="",E10>F10),"To Buy",IF(SUM(J10,F10)<E10,"To Buy",IF(AND(SUM(J10,F10)>=E10,J10<>""),"Ordered",IF(AND(E10=0,F10=0,D10="B3"),"B3 Option",IF(AND(E10=0,F10=0),"Remove","To Buy")))))))))) | C10: 1 | D10: B3 | E10: =SUM(M10:S10) | F10: =SUM(T10:Z10) | G10: =IF((F10-E10)>=0,F10-E10,0) | H10: =MAX(0,$E10-$F10-$J10) | K10: 5.42 | L10: =IF(AND($H10>0,ISNUMBER($K10)),$H10*$K10,0) | Q10: 1 | S10: =IF(AND(J10<>"",SUM(M10:R10)=0),J10,"") | AA10: Sorcery | AC10: B | AD10: 2 | AE10: Fifth Dawn | AF10: Tuned add | AG10: You draw two cards and lose 2 life. | AJ10: D5 Tuned add; targeted 2026-09-02; replaces Lake-town Lookout; B3/Max add for D3; NOT targeted; replaces Troll Negotiations when bought | AK10: [T] targeted D5 (Tuned add, replaces Lake-town Lookout); [A later] ->D5 when bought; [B3/Max, not targeted] when bought ->D3, replaces Troll Negotiations (Troll Negotiations->B)
A11: Ophiomancer | B11: =IF(AND(F11<>0,E11=F11),"In Hand",IF(AND(E11<>0,E11<F11,SUM(M11:R11)=0,SUM(T11:Y11)>0),"Extra-Sub",IF(AND(E11=0,E11<F11,SUM(M11:R11)=0,SUM(T11:Y11)>0),"Bench-Sub",IF(AND(E11=0,F11>0),"Bench",IF(E11<F11,"Extra",IF(AND(J11="",E11>F11),"To Buy",IF(SUM(J11,F11)<E11,"To Buy",IF(AND(SUM(J11,F11)>=E11,J11<>""),"Ordered",IF(AND(E11=0,F11=0,D11="B3"),"B3 Option",IF(AND(E11=0,F11=0),"Remove","To Buy")))))))))) | C11: 1 | D11: B2 | E11: =SUM(M11:S11) | F11: =SUM(T11:Z11) | G11: =IF((F11-E11)>=0,F11-E11,0) | H11: =MAX(0,$E11-$F11-$J11) | K11: 0.96 | L11: =IF(AND($H11>0,ISNUMBER($K11)),$H11*$K11,0) | Q11: 1 | S11: =IF(AND(J11<>"",SUM(M11:R11)=0),J11,"") | AA11: Creature | AB11: Human Shaman | AC11: B | AD11: 3 | AE11: Commander 2013 | AF11: Token Producer | AG11: Each upkeep, creates a 1/1 deathtouch Snake token if you control none | AJ11: Removed from cart 2026-09-02: only sellers with 1-3 cards had it (shipping >30% of package)
A12: Ruby Medallion | B12: =IF(AND(F12<>0,E12=F12),"In Hand",IF(AND(E12<>0,E12<F12,SUM(M12:R12)=0,SUM(T12:Y12)>0),"Extra-Sub",IF(AND(E12=0,E12<F12,SUM(M12:R12)=0,SUM(T12:Y12)>0),"Bench-Sub",IF(AND(E12=0,F12>0),"Bench",IF(E12<F12,"Extra",IF(AND(J12="",E12>F12),"To Buy",IF(SUM(J12,F12)<E12,"To Buy",IF(AND(SUM(J12,F12)>=E12,J12<>""),"Ordered",IF(AND(E12=0,F12=0,D12="B3"),"B3 Option",IF(AND(E12=0,F12=0),"Remove","To Buy")))))))))) | C12: 1 | D12: B3 | E12: =SUM(M12:S12) | F12: =SUM(T12:Z12) | G12: =IF((F12-E12)>=0,F12-E12,0) | H12: =MAX(0,$E12-$F12-$J12) | K12: 14.81 | L12: =IF(AND($H12>0,ISNUMBER($K12)),$H12*$K12,0) | R12: 1 | S12: =IF(AND(J12<>"",SUM(M12:R12)=0),J12,"") | AA12: Artifact | AC12: C | AD12: 2 | AE12: Tempest | AF12: Tuned add | AG12: Red spells you cast cost {1} less to cast. | AJ12: D6 Tuned add; targeted 2026-09-02; replaces Dwarven Mauler | AK12: [T] targeted D6 (Tuned add, replaces Dwarven Mauler); [A later] ->D6 when bought
A13: Rundvelt Hordemaster | B13: =IF(AND(F13<>0,E13=F13),"In Hand",IF(AND(E13<>0,E13<F13,SUM(M13:R13)=0,SUM(T13:Y13)>0),"Extra-Sub",IF(AND(E13=0,E13<F13,SUM(M13:R13)=0,SUM(T13:Y13)>0),"Bench-Sub",IF(AND(E13=0,F13>0),"Bench",IF(E13<F13,"Extra",IF(AND(J13="",E13>F13),"To Buy",IF(SUM(J13,F13)<E13,"To Buy",IF(AND(SUM(J13,F13)>=E13,J13<>""),"Ordered",IF(AND(E13=0,F13=0,D13="B3"),"B3 Option",IF(AND(E13=0,F13=0),"Remove","To Buy")))))))))) | C13: 1 | D13: B3 | E13: =SUM(M13:S13) | F13: =SUM(T13:Z13) | G13: =IF((F13-E13)>=0,F13-E13,0) | H13: =MAX(0,$E13-$F13-$J13) | K13: 4.87 | L13: =IF(AND($H13>0,ISNUMBER($K13)),$H13*$K13,0) | R13: 1 | S13: =IF(AND(J13<>"",SUM(M13:R13)=0),J13,"") | AA13: Creature | AB13: Goblin Warrior | AC13: R | AD13: 2 | AE13: Dominaria United | AF13: Tuned add | AG13: Other Goblins you control get +1/+1. Whenever this creature or another Goblin you control dies, exile the top card of yo | AJ13: D6 Tuned add; targeted 2026-09-02; replaces Burning Curiosity | AK13: [T] targeted D6 (Tuned add, replaces Burning Curiosity); [A later] ->D6 when bought
A14: Skullclamp | B14: =IF(AND(F14<>0,E14=F14),"In Hand",IF(AND(E14<>0,E14<F14,SUM(M14:R14)=0,SUM(T14:Y14)>0),"Extra-Sub",IF(AND(E14=0,E14<F14,SUM(M14:R14)=0,SUM(T14:Y14)>0),"Bench-Sub",IF(AND(E14=0,F14>0),"Bench",IF(E14<F14,"Extra",IF(AND(J14="",E14>F14),"To Buy",IF(SUM(J14,F14)<E14,"To Buy",IF(AND(SUM(J14,F14)>=E14,J14<>""),"Ordered",IF(AND(E14=0,F14=0,D14="B3"),"B3 Option",IF(AND(E14=0,F14=0),"Remove","To Buy")))))))))) | C14: 1 | D14: B2 | E14: =SUM(M14:S14) | F14: =SUM(T14:Z14) | G14: =IF((F14-E14)>=0,F14-E14,0) | H14: =MAX(0,$E14-$F14-$J14) | K14: 5.89 | L14: =IF(AND($H14>0,ISNUMBER($K14)),$H14*$K14,0) | M14: 1 | Q14: 1 | S14: =IF(AND(J14<>"",SUM(M14:R14)=0),J14,"") | T14: 1 | AA14: Artifact | AB14: Equipment | AC14: C | AD14: 1 | AE14: Darksteel | AF14: Card Draw | AG14: Equipped creature gets +1/-1 | AH14: Draw two cards whenever equipped creature dies | AJ14: Tuned add (2nd copy); NOT a Game Changer per the official list; D5 Tuned add; targeted 2026-09-02; replaces Suture Priest | AK14: [T] targeted D5 (Tuned add, replaces Suture Priest); [A later] ->D5 when bought
A15: Teysa Karlov | B15: =IF(AND(F15<>0,E15=F15),"In Hand",IF(AND(E15<>0,E15<F15,SUM(M15:R15)=0,SUM(T15:Y15)>0),"Extra-Sub",IF(AND(E15=0,E15<F15,SUM(M15:R15)=0,SUM(T15:Y15)>0),"Bench-Sub",IF(AND(E15=0,F15>0),"Bench",IF(E15<F15,"Extra",IF(AND(J15="",E15>F15),"To Buy",IF(SUM(J15,F15)<E15,"To Buy",IF(AND(SUM(J15,F15)>=E15,J15<>""),"Ordered",IF(AND(E15=0,F15=0,D15="B3"),"B3 Option",IF(AND(E15=0,F15=0),"Remove","To Buy")))))))))) | C15: 1 | D15: B3 | E15: =SUM(M15:S15) | F15: =SUM(T15:Z15) | G15: =IF((F15-E15)>=0,F15-E15,0) | H15: =MAX(0,$E15-$F15-$J15) | K15: 2.67 | L15: =IF(AND($H15>0,ISNUMBER($K15)),$H15*$K15,0) | Q15: 1 | S15: =IF(AND(J15<>"",SUM(M15:R15)=0),J15,"") | AA15: Legendary Creature | AB15: Human Advisor | AC15: BW | AD15: 4 | AE15: Ravnica Allegiance | AF15: Tuned add | AG15: If a creature dying causes a triggered ability of a permanent you control to trigger, that ability triggers an additiona | AJ15: D5 Tuned add; targeted 2026-09-02; replaces Prideful Feastling | AK15: [T] targeted D5 (Tuned add, replaces Prideful Feastling); [A later] ->D5 when bought
A16: Tree of Perdition | B16: =IF(AND(F16<>0,E16=F16),"In Hand",IF(AND(E16<>0,E16<F16,SUM(M16:R16)=0,SUM(T16:Y16)>0),"Extra-Sub",IF(AND(E16=0,E16<F16,SUM(M16:R16)=0,SUM(T16:Y16)>0),"Bench-Sub",IF(AND(E16=0,F16>0),"Bench",IF(E16<F16,"Extra",IF(AND(J16="",E16>F16),"To Buy",IF(SUM(J16,F16)<E16,"To Buy",IF(AND(SUM(J16,F16)>=E16,J16<>""),"Ordered",IF(AND(E16=0,F16=0,D16="B3"),"B3 Option",IF(AND(E16=0,F16=0),"Remove","To Buy")))))))))) | C16: 1 | D16: B2 | E16: =SUM(M16:S16) | F16: =SUM(T16:Z16) | G16: =IF((F16-E16)>=0,F16-E16,0) | H16: =MAX(0,$E16-$F16-$J16) | K16: 2.94 | L16: =IF(AND($H16>0,ISNUMBER($K16)),$H16*$K16,0) | P16: 1 | S16: =IF(AND(J16<>"",SUM(M16:R16)=0),J16,"") | AA16: Creature | AB16: Plant | AC16: B | AD16: 4 | AE16: Eldritch Moon | AF16: Finisher | AG16: Tap: swap target opponent's life total with this creature's toughness | AH16: Defender body | AJ16: Tuned add
A17: Brushland | B17: =IF(AND(F17<>0,E17=F17),"In Hand",IF(AND(E17<>0,E17<F17,SUM(M17:R17)=0,SUM(T17:Y17)>0),"Extra-Sub",IF(AND(E17=0,E17<F17,SUM(M17:R17)=0,SUM(T17:Y17)>0),"Bench-Sub",IF(AND(E17=0,F17>0),"Bench",IF(E17<F17,"Extra",IF(AND(J17="",E17>F17),"To Buy",IF(SUM(J17,F17)<E17,"To Buy",IF(AND(SUM(J17,F17)>=E17,J17<>""),"Ordered",IF(AND(E17=0,F17=0,D17="B3"),"B3 Option",IF(AND(E17=0,F17=0),"Remove","To Buy")))))))))) | D17: B2 | E17: =SUM(M17:S17) | F17: =SUM(T17:Z17) | G17: =IF((F17-E17)>=0,F17-E17,0) | H17: =MAX(0,$E17-$F17-$J17) | K17: 1.71 | L17: =IF(AND($H17>0,ISNUMBER($K17)),$H17*$K17,0) | S17: =IF(AND(J17<>"",SUM(M17:R17)=0),J17,"") | AA17: Land | AC17: L | AD17: 0 | AE17: Ice Age | AF17: Land | AG17: Taps for {C}, or {G}/{W} at the cost of 1 damage to you | AJ17: Bench sub available in D3: Drowned Catacomb (2026-09-02); D3 target removed 2026-09-02 (bench sub in place)
A18: Colfenor, the Last Yew | B18: =IF(AND(F18<>0,E18=F18),"In Hand",IF(AND(E18<>0,E18<F18,SUM(M18:R18)=0,SUM(T18:Y18)>0),"Extra-Sub",IF(AND(E18=0,E18<F18,SUM(M18:R18)=0,SUM(T18:Y18)>0),"Bench-Sub",IF(AND(E18=0,F18>0),"Bench",IF(E18<F18,"Extra",IF(AND(J18="",E18>F18),"To Buy",IF(SUM(J18,F18)<E18,"To Buy",IF(AND(SUM(J18,F18)>=E18,J18<>""),"Ordered",IF(AND(E18=0,F18=0,D18="B3"),"B3 Option",IF(AND(E18=0,F18=0),"Remove","To Buy")))))))))) | D18: B2 | E18: =SUM(M18:S18) | F18: =SUM(T18:Z18) | G18: =IF((F18-E18)>=0,F18-E18,0) | H18: =MAX(0,$E18-$F18-$J18) | K18: 0.54 | L18: =IF(AND($H18>0,ISNUMBER($K18)),$H18*$K18,0) | S18: =IF(AND(J18<>"",SUM(M18:R18)=0),J18,"") | AA18: Legendary Creature | AB18: Treefolk Shaman | AC18: Multi | AD18: 6 | AE18: Commander Legends | AF18: Recursion | AG18: Returns a creature card with lesser toughness from graveyard to hand when it or another creature you control dies | AH18: Reach, vigilance body | AJ18: Tuned add; Bench sub available in D4: Sun Titan (2026-09-02); D4 target removed 2026-09-02 (bench sub in place)
A19: Concealed Courtyard | B19: =IF(AND(F19<>0,E19=F19),"In Hand",IF(AND(E19<>0,E19<F19,SUM(M19:R19)=0,SUM(T19:Y19)>0),"Extra-Sub",IF(AND(E19=0,E19<F19,SUM(M19:R19)=0,SUM(T19:Y19)>0),"Bench-Sub",IF(AND(E19=0,F19>0),"Bench",IF(E19<F19,"Extra",IF(AND(J19="",E19>F19),"To Buy",IF(SUM(J19,F19)<E19,"To Buy",IF(AND(SUM(J19,F19)>=E19,J19<>""),"Ordered",IF(AND(E19=0,F19=0,D19="B3"),"B3 Option",IF(AND(E19=0,F19=0),"Remove","To Buy")))))))))) | D19: B2 | E19: =SUM(M19:S19) | F19: =SUM(T19:Z19) | G19: =IF((F19-E19)>=0,F19-E19,0) | H19: =MAX(0,$E19-$F19-$J19) | K19: 1 | L19: =IF(AND($H19>0,ISNUMBER($K19)),$H19*$K19,0) | S19: =IF(AND(J19<>"",SUM(M19:R19)=0),J19,"") | AA19: Land | AC19: L | AD19: 0 | AE19: Kaladesh | AF19: Land | AG19: Taps for {W} or {B} | AH19: Enters tapped unless you control two or fewer other lands | AJ19: Bench sub available in D5: Isolated Chapel (2026-09-02); D5 target removed 2026-09-02 (bench sub in place)
A20: Costly Plunder | B20: =IF(AND(F20<>0,E20=F20),"In Hand",IF(AND(E20<>0,E20<F20,SUM(M20:R20)=0,SUM(T20:Y20)>0),"Extra-Sub",IF(AND(E20=0,E20<F20,SUM(M20:R20)=0,SUM(T20:Y20)>0),"Bench-Sub",IF(AND(E20=0,F20>0),"Bench",IF(E20<F20,"Extra",IF(AND(J20="",E20>F20),"To Buy",IF(SUM(J20,F20)<E20,"To Buy",IF(AND(SUM(J20,F20)>=E20,J20<>""),"Ordered",IF(AND(E20=0,F20=0,D20="B3"),"B3 Option",IF(AND(E20=0,F20=0),"Remove","To Buy")))))))))) | D20: B2 | E20: =SUM(M20:S20) | F20: =SUM(T20:Z20) | G20: =IF((F20-E20)>=0,F20-E20,0) | H20: =MAX(0,$E20-$F20-$J20) | K20: 0.24 | L20: =IF(AND($H20>0,ISNUMBER($K20)),$H20*$K20,0) | S20: =IF(AND(J20<>"",SUM(M20:R20)=0),J20,"") | AA20: Instant | AC20: B | AD20: 2 | AE20: Ixalan | AF20: Sacrifice Outlet | AG20: Sacrifice an artifact or creature to draw two cards | AJ20: Cut in Tuned; D5 target removed 2026-09-02: replaced by Tuned upgrade Ossification (within $2)
A21: Doomed Traveler | B21: =IF(AND(F21<>0,E21=F21),"In Hand",IF(AND(E21<>0,E21<F21,SUM(M21:R21)=0,SUM(T21:Y21)>0),"Extra-Sub",IF(AND(E21=0,E21<F21,SUM(M21:R21)=0,SUM(T21:Y21)>0),"Bench-Sub",IF(AND(E21=0,F21>0),"Bench",IF(E21<F21,"Extra",IF(AND(J21="",E21>F21),"To Buy",IF(SUM(J21,F21)<E21,"To Buy",IF(AND(SUM(J21,F21)>=E21,J21<>""),"Ordered",IF(AND(E21=0,F21=0,D21="B3"),"B3 Option",IF(AND(E21=0,F21=0),"Remove","To Buy")))))))))) | D21: B2 | E21: =SUM(M21:S21) | F21: =SUM(T21:Z21) | G21: =IF((F21-E21)>=0,F21-E21,0) | H21: =MAX(0,$E21-$F21-$J21) | K21: 0.09 | L21: =IF(AND($H21>0,ISNUMBER($K21)),$H21*$K21,0) | S21: =IF(AND(J21<>"",SUM(M21:R21)=0),J21,"") | AA21: Creature | AB21: Human Soldier | AC21: W | AD21: 1 | AE21: Innistrad | AF21: Token Producer | AG21: Creates a 1/1 flying Spirit token when it dies | AJ21: Bench sub available in D5: Lake-town Lookout (2026-09-02); D5 target removed 2026-09-02 (bench sub in place)
A22: Eternal Witness | B22: =IF(AND(F22<>0,E22=F22),"In Hand",IF(AND(E22<>0,E22<F22,SUM(M22:R22)=0,SUM(T22:Y22)>0),"Extra-Sub",IF(AND(E22=0,E22<F22,SUM(M22:R22)=0,SUM(T22:Y22)>0),"Bench-Sub",IF(AND(E22=0,F22>0),"Bench",IF(E22<F22,"Extra",IF(AND(J22="",E22>F22),"To Buy",IF(SUM(J22,F22)<E22,"To Buy",IF(AND(SUM(J22,F22)>=E22,J22<>""),"Ordered",IF(AND(E22=0,F22=0,D22="B3"),"B3 Option",IF(AND(E22=0,F22=0),"Remove","To Buy")))))))))) | D22: B2 | E22: =SUM(M22:S22) | F22: =SUM(T22:Z22) | G22: =IF((F22-E22)>=0,F22-E22,0) | H22: =MAX(0,$E22-$F22-$J22) | K22: 2.52 | L22: =IF(AND($H22>0,ISNUMBER($K22)),$H22*$K22,0) | S22: =IF(AND(J22<>"",SUM(M22:R22)=0),J22,"") | AA22: Creature | AB22: Human Shaman | AC22: G | AD22: 3 | AE22: Fifth Dawn | AF22: Recursion | AG22: Returns target card from your graveyard to hand when it enters | AJ22: Tuned add; Bench sub available in D2: Dundoolin Weaver (2026-09-02); D2 target removed 2026-09-02 (bench sub in place)
A23: Fire Diamond | B23: =IF(AND(F23<>0,E23=F23),"In Hand",IF(AND(E23<>0,E23<F23,SUM(M23:R23)=0,SUM(T23:Y23)>0),"Extra-Sub",IF(AND(E23=0,E23<F23,SUM(M23:R23)=0,SUM(T23:Y23)>0),"Bench-Sub",IF(AND(E23=0,F23>0),"Bench",IF(E23<F23,"Extra",IF(AND(J23="",E23>F23),"To Buy",IF(SUM(J23,F23)<E23,"To Buy",IF(AND(SUM(J23,F23)>=E23,J23<>""),"Ordered",IF(AND(E23=0,F23=0,D23="B3"),"B3 Option",IF(AND(E23=0,F23=0),"Remove","To Buy")))))))))) | D23: B2 | E23: =SUM(M23:S23) | F23: =SUM(T23:Z23) | G23: =IF((F23-E23)>=0,F23-E23,0) | H23: =MAX(0,$E23-$F23-$J23) | K23: 0.36 | L23: =IF(AND($H23>0,ISNUMBER($K23)),$H23*$K23,0) | S23: =IF(AND(J23<>"",SUM(M23:R23)=0),J23,"") | AA23: Artifact | AC23: R | AD23: 2 | AE23: Mirage | AF23: Mana Rock | AG23: Taps for {R} (enters tapped) | AJ23: Cut in Tuned; D6 target removed 2026-09-02 (bench sub Sword of the Animist in place)
A24: Gather the Townsfolk | B24: =IF(AND(F24<>0,E24=F24),"In Hand",IF(AND(E24<>0,E24<F24,SUM(M24:R24)=0,SUM(T24:Y24)>0),"Extra-Sub",IF(AND(E24=0,E24<F24,SUM(M24:R24)=0,SUM(T24:Y24)>0),"Bench-Sub",IF(AND(E24=0,F24>0),"Bench",IF(E24<F24,"Extra",IF(AND(J24="",E24>F24),"To Buy",IF(SUM(J24,F24)<E24,"To Buy",IF(AND(SUM(J24,F24)>=E24,J24<>""),"Ordered",IF(AND(E24=0,F24=0,D24="B3"),"B3 Option",IF(AND(E24=0,F24=0),"Remove","To Buy")))))))))) | D24: B2 | E24: =SUM(M24:S24) | F24: =SUM(T24:Z24) | G24: =IF((F24-E24)>=0,F24-E24,0) | H24: =MAX(0,$E24-$F24-$J24) | K24: 0.13 | L24: =IF(AND($H24>0,ISNUMBER($K24)),$H24*$K24,0) | S24: =IF(AND(J24<>"",SUM(M24:R24)=0),J24,"") | AA24: Sorcery | AC24: W | AD24: 2 | AE24: Dark Ascension | AF24: Token Producer | AG24: Creates two 1/1 Human tokens (five instead if you have 5 or less life) | AJ24: Bench sub available in D5: Clachan Festival (2026-09-02); D5 target removed 2026-09-02 (bench sub in place)
A25: Goblin Motivator | B25: =IF(AND(F25<>0,E25=F25),"In Hand",IF(AND(E25<>0,E25<F25,SUM(M25:R25)=0,SUM(T25:Y25)>0),"Extra-Sub",IF(AND(E25=0,E25<F25,SUM(M25:R25)=0,SUM(T25:Y25)>0),"Bench-Sub",IF(AND(E25=0,F25>0),"Bench",IF(E25<F25,"Extra",IF(AND(J25="",E25>F25),"To Buy",IF(SUM(J25,F25)<E25,"To Buy",IF(AND(SUM(J25,F25)>=E25,J25<>""),"Ordered",IF(AND(E25=0,F25=0,D25="B3"),"B3 Option",IF(AND(E25=0,F25=0),"Remove","To Buy")))))))))) | D25: B2 | E25: =SUM(M25:S25) | F25: =SUM(T25:Z25) | G25: =IF((F25-E25)>=0,F25-E25,0) | H25: =MAX(0,$E25-$F25-$J25) | K25: 0.26 | L25: =IF(AND($H25>0,ISNUMBER($K25)),$H25*$K25,0) | S25: =IF(AND(J25<>"",SUM(M25:R25)=0),J25,"") | AA25: Creature | AB25: Goblin Warrior | AC25: R | AD25: 1 | AE25: Core Set 2019 | AF25: Haste Enabler | AG25: Tap: target creature gains haste until end of turn | AJ25: Cut in Tuned; D6 target removed 2026-09-02: replaced by Tuned upgrade Purphoros's Intervention (within $2)
A26: Goblin Oriflamme | B26: =IF(AND(F26<>0,E26=F26),"In Hand",IF(AND(E26<>0,E26<F26,SUM(M26:R26)=0,SUM(T26:Y26)>0),"Extra-Sub",IF(AND(E26=0,E26<F26,SUM(M26:R26)=0,SUM(T26:Y26)>0),"Bench-Sub",IF(AND(E26=0,F26>0),"Bench",IF(E26<F26,"Extra",IF(AND(J26="",E26>F26),"To Buy",IF(SUM(J26,F26)<E26,"To Buy",IF(AND(SUM(J26,F26)>=E26,J26<>""),"Ordered",IF(AND(E26=0,F26=0,D26="B3"),"B3 Option",IF(AND(E26=0,F26=0),"Remove","To Buy")))))))))) | D26: B2 | E26: =SUM(M26:S26) | F26: =SUM(T26:Z26) | G26: =IF((F26-E26)>=0,F26-E26,0) | H26: =MAX(0,$E26-$F26-$J26) | K26: 0.53 | L26: =IF(AND($H26>0,ISNUMBER($K26)),$H26*$K26,0) | S26: =IF(AND(J26<>"",SUM(M26:R26)=0),J26,"") | AA26: Enchantment | AC26: R | AD26: 2 | AE26: Modern Horizons | AF26: Lord/Anthem | AG26: Attacking creatures you control get +1/+0 | AJ26: Cut in Tuned; D6 target removed 2026-09-02: replaced by Tuned upgrade Goblin Rabblemaster (within $2)
A27: Great Furnace | B27: =IF(AND(F27<>0,E27=F27),"In Hand",IF(AND(E27<>0,E27<F27,SUM(M27:R27)=0,SUM(T27:Y27)>0),"Extra-Sub",IF(AND(E27=0,E27<F27,SUM(M27:R27)=0,SUM(T27:Y27)>0),"Bench-Sub",IF(AND(E27=0,F27>0),"Bench",IF(E27<F27,"Extra",IF(AND(J27="",E27>F27),"To Buy",IF(SUM(J27,F27)<E27,"To Buy",IF(AND(SUM(J27,F27)>=E27,J27<>""),"Ordered",IF(AND(E27=0,F27=0,D27="B3"),"B3 Option",IF(AND(E27=0,F27=0),"Remove","To Buy")))))))))) | D27: B2 | E27: =SUM(M27:S27) | F27: =SUM(T27:Z27) | G27: =IF((F27-E27)>=0,F27-E27,0) | H27: =MAX(0,$E27-$F27-$J27) | K27: 2.43 | L27: =IF(AND($H27>0,ISNUMBER($K27)),$H27*$K27,0) | S27: =IF(AND(J27<>"",SUM(M27:R27)=0),J27,"") | AA27: Artifact Land | AC27: R | AD27: 0 | AE27: Mirrodin | AF27: Land | AG27: Taps for {R} | AJ27: Bench sub available in D6: Mountain (2026-09-02); D6 target removed 2026-09-02 (bench sub in place)
A28: Hunted Witness | B28: =IF(AND(F28<>0,E28=F28),"In Hand",IF(AND(E28<>0,E28<F28,SUM(M28:R28)=0,SUM(T28:Y28)>0),"Extra-Sub",IF(AND(E28=0,E28<F28,SUM(M28:R28)=0,SUM(T28:Y28)>0),"Bench-Sub",IF(AND(E28=0,F28>0),"Bench",IF(E28<F28,"Extra",IF(AND(J28="",E28>F28),"To Buy",IF(SUM(J28,F28)<E28,"To Buy",IF(AND(SUM(J28,F28)>=E28,J28<>""),"Ordered",IF(AND(E28=0,F28=0,D28="B3"),"B3 Option",IF(AND(E28=0,F28=0),"Remove","To Buy")))))))))) | D28: B2 | E28: =SUM(M28:S28) | F28: =SUM(T28:Z28) | G28: =IF((F28-E28)>=0,F28-E28,0) | H28: =MAX(0,$E28-$F28-$J28) | K28: 0.29 | L28: =IF(AND($H28>0,ISNUMBER($K28)),$H28*$K28,0) | S28: =IF(AND(J28<>"",SUM(M28:R28)=0),J28,"") | AA28: Creature | AB28: Human | AC28: W | AD28: 1 | AE28: Guilds of Ravnica | AF28: Token Producer | AG28: Creates a 1/1 lifelink Soldier token when it dies | AJ28: Bench sub available in D5: Pretending Poxbearers (2026-09-02); D5 target removed 2026-09-02 (bench sub in place)
A29: Inspiring Overseer | B29: =IF(AND(F29<>0,E29=F29),"In Hand",IF(AND(E29<>0,E29<F29,SUM(M29:R29)=0,SUM(T29:Y29)>0),"Extra-Sub",IF(AND(E29=0,E29<F29,SUM(M29:R29)=0,SUM(T29:Y29)>0),"Bench-Sub",IF(AND(E29=0,F29>0),"Bench",IF(E29<F29,"Extra",IF(AND(J29="",E29>F29),"To Buy",IF(SUM(J29,F29)<E29,"To Buy",IF(AND(SUM(J29,F29)>=E29,J29<>""),"Ordered",IF(AND(E29=0,F29=0,D29="B3"),"B3 Option",IF(AND(E29=0,F29=0),"Remove","To Buy")))))))))) | D29: B2 | E29: =SUM(M29:S29) | F29: =SUM(T29:Z29) | G29: =IF((F29-E29)>=0,F29-E29,0) | H29: =MAX(0,$E29-$F29-$J29) | K29: 0.28 | L29: =IF(AND($H29>0,ISNUMBER($K29)),$H29*$K29,0) | S29: =IF(AND(J29<>"",SUM(M29:R29)=0),J29,"") | AA29: Creature | AB29: Angel Cleric | AC29: W | AD29: 3 | AE29: Streets of New Capenna | AF29: Card Draw | AG29: Gains 1 life and draws a card when it enters | AH29: Flying body | AJ29: Cut in Tuned; D5 target removed 2026-09-02: replaced by Tuned upgrade Requiem Angel (within $2)
A30: Llanowar Wastes | B30: =IF(AND(F30<>0,E30=F30),"In Hand",IF(AND(E30<>0,E30<F30,SUM(M30:R30)=0,SUM(T30:Y30)>0),"Extra-Sub",IF(AND(E30=0,E30<F30,SUM(M30:R30)=0,SUM(T30:Y30)>0),"Bench-Sub",IF(AND(E30=0,F30>0),"Bench",IF(E30<F30,"Extra",IF(AND(J30="",E30>F30),"To Buy",IF(SUM(J30,F30)<E30,"To Buy",IF(AND(SUM(J30,F30)>=E30,J30<>""),"Ordered",IF(AND(E30=0,F30=0,D30="B3"),"B3 Option",IF(AND(E30=0,F30=0),"Remove","To Buy")))))))))) | D30: B2 | E30: =SUM(M30:S30) | F30: =SUM(T30:Z30) | G30: =IF((F30-E30)>=0,F30-E30,0) | H30: =MAX(0,$E30-$F30-$J30) | K30: 0.69 | L30: =IF(AND($H30>0,ISNUMBER($K30)),$H30*$K30,0) | S30: =IF(AND(J30<>"",SUM(M30:R30)=0),J30,"") | AA30: Land | AC30: L | AD30: 0 | AE30: Apocalypse | AF30: Land | AG30: Taps for {C}, or {B}/{G} at the cost of 1 damage to you | AJ30: Bench sub available in D4: Blossoming Sands (2026-09-02); Bench sub available in D3: Arcane Sanctum (2026-09-02); D4 target removed 2026-09-02 (bench sub in place); D3 target removed 2026-09-02 (bench sub in place)
A31: Priest of Fell Rites | B31: =IF(AND(F31<>0,E31=F31),"In Hand",IF(AND(E31<>0,E31<F31,SUM(M31:R31)=0,SUM(T31:Y31)>0),"Extra-Sub",IF(AND(E31=0,E31<F31,SUM(M31:R31)=0,SUM(T31:Y31)>0),"Bench-Sub",IF(AND(E31=0,F31>0),"Bench",IF(E31<F31,"Extra",IF(AND(J31="",E31>F31),"To Buy",IF(SUM(J31,F31)<E31,"To Buy",IF(AND(SUM(J31,F31)>=E31,J31<>""),"Ordered",IF(AND(E31=0,F31=0,D31="B3"),"B3 Option",IF(AND(E31=0,F31=0),"Remove","To Buy")))))))))) | D31: B2 | E31: =SUM(M31:S31) | F31: =SUM(T31:Z31) | G31: =IF((F31-E31)>=0,F31-E31,0) | H31: =MAX(0,$E31-$F31-$J31) | K31: 0.36 | L31: =IF(AND($H31>0,ISNUMBER($K31)),$H31*$K31,0) | S31: =IF(AND(J31<>"",SUM(M31:R31)=0),J31,"") | AA31: Creature | AB31: Human Warlock | AC31: Multi | AD31: 2 | AE31: Modern Horizons 2 | AF31: Reanimation | AG31: Tap, pay 3 life, sacrifice: return target creature card from graveyard to the battlefield | AH31: Unearth {3}{W}{B} to return from graveyard with haste temporarily | AJ31: Bench sub available in D5: Unbury (2026-09-02); D5 target removed 2026-09-02 (bench sub in place)
A32: Rummaging Goblin | B32: =IF(AND(F32<>0,E32=F32),"In Hand",IF(AND(E32<>0,E32<F32,SUM(M32:R32)=0,SUM(T32:Y32)>0),"Extra-Sub",IF(AND(E32=0,E32<F32,SUM(M32:R32)=0,SUM(T32:Y32)>0),"Bench-Sub",IF(AND(E32=0,F32>0),"Bench",IF(E32<F32,"Extra",IF(AND(J32="",E32>F32),"To Buy",IF(SUM(J32,F32)<E32,"To Buy",IF(AND(SUM(J32,F32)>=E32,J32<>""),"Ordered",IF(AND(E32=0,F32=0,D32="B3"),"B3 Option",IF(AND(E32=0,F32=0),"Remove","To Buy")))))))))) | D32: B2 | E32: =SUM(M32:S32) | F32: =SUM(T32:Z32) | G32: =IF((F32-E32)>=0,F32-E32,0) | H32: =MAX(0,$E32-$F32-$J32) | K32: 0.2 | L32: =IF(AND($H32>0,ISNUMBER($K32)),$H32*$K32,0) | S32: =IF(AND(J32<>"",SUM(M32:R32)=0),J32,"") | AA32: Creature | AB32: Goblin Rogue | AC32: R | AD32: 3 | AE32: Magic 2013 | AF32: Discard/Looting | AG32: Tap, discard a card: draw a card | AJ32: Cut in Tuned; Bench sub available in D6: Gundabad Opportunist (2026-09-02); D6 target removed 2026-09-02 (bench sub in place)
A33: Shineshadow Snarl | B33: =IF(AND(F33<>0,E33=F33),"In Hand",IF(AND(E33<>0,E33<F33,SUM(M33:R33)=0,SUM(T33:Y33)>0),"Extra-Sub",IF(AND(E33=0,E33<F33,SUM(M33:R33)=0,SUM(T33:Y33)>0),"Bench-Sub",IF(AND(E33=0,F33>0),"Bench",IF(E33<F33,"Extra",IF(AND(J33="",E33>F33),"To Buy",IF(SUM(J33,F33)<E33,"To Buy",IF(AND(SUM(J33,F33)>=E33,J33<>""),"Ordered",IF(AND(E33=0,F33=0,D33="B3"),"B3 Option",IF(AND(E33=0,F33=0),"Remove","To Buy")))))))))) | D33: B2 | E33: =SUM(M33:S33) | F33: =SUM(T33:Z33) | G33: =IF((F33-E33)>=0,F33-E33,0) | H33: =MAX(0,$E33-$F33-$J33) | K33: 0.33 | L33: =IF(AND($H33>0,ISNUMBER($K33)),$H33*$K33,0) | S33: =IF(AND(J33<>"",SUM(M33:R33)=0),J33,"") | AA33: Land | AC33: L | AD33: 0 | AE33: Strixhaven: School of Mages | AF33: Land | AG33: Taps for {W} or {B} | AH33: Enters untapped if you reveal a Plains or Swamp | AJ33: Bench sub available in D5: Plains (2026-09-02); D5 target removed 2026-09-02 (bench sub in place)
A34: Sign in Blood | B34: =IF(AND(F34<>0,E34=F34),"In Hand",IF(AND(E34<>0,E34<F34,SUM(M34:R34)=0,SUM(T34:Y34)>0),"Extra-Sub",IF(AND(E34=0,E34<F34,SUM(M34:R34)=0,SUM(T34:Y34)>0),"Bench-Sub",IF(AND(E34=0,F34>0),"Bench",IF(E34<F34,"Extra",IF(AND(J34="",E34>F34),"To Buy",IF(SUM(J34,F34)<E34,"To Buy",IF(AND(SUM(J34,F34)>=E34,J34<>""),"Ordered",IF(AND(E34=0,F34=0,D34="B3"),"B3 Option",IF(AND(E34=0,F34=0),"Remove","To Buy")))))))))) | D34: B2 | E34: =SUM(M34:S34) | F34: =SUM(T34:Z34) | G34: =IF((F34-E34)>=0,F34-E34,0) | H34: =MAX(0,$E34-$F34-$J34) | K34: 3.67 | L34: =IF(AND($H34>0,ISNUMBER($K34)),$H34*$K34,0) | S34: =IF(AND(J34<>"",SUM(M34:R34)=0),J34,"") | AA34: Sorcery | AC34: B | AD34: 2 | AE34: Magic 2010 | AF34: Card Draw | AG34: Target player draws two cards and loses 2 life | AJ34: Bench sub available in D5: Secret Rendezvous (2026-09-02); D5 target removed 2026-09-02 (bench sub in place)
A35: Silverquill Campus | B35: =IF(AND(F35<>0,E35=F35),"In Hand",IF(AND(E35<>0,E35<F35,SUM(M35:R35)=0,SUM(T35:Y35)>0),"Extra-Sub",IF(AND(E35=0,E35<F35,SUM(M35:R35)=0,SUM(T35:Y35)>0),"Bench-Sub",IF(AND(E35=0,F35>0),"Bench",IF(E35<F35,"Extra",IF(AND(J35="",E35>F35),"To Buy",IF(SUM(J35,F35)<E35,"To Buy",IF(AND(SUM(J35,F35)>=E35,J35<>""),"Ordered",IF(AND(E35=0,F35=0,D35="B3"),"B3 Option",IF(AND(E35=0,F35=0),"Remove","To Buy")))))))))) | D35: B2 | E35: =SUM(M35:S35) | F35: =SUM(T35:Z35) | G35: =IF((F35-E35)>=0,F35-E35,0) | H35: =MAX(0,$E35-$F35-$J35) | K35: 0.29 | L35: =IF(AND($H35>0,ISNUMBER($K35)),$H35*$K35,0) | S35: =IF(AND(J35<>"",SUM(M35:R35)=0),J35,"") | AA35: Land | AC35: L | AD35: 0 | AE35: Strixhaven: School of Mages | AF35: Land | AG35: Taps for {W} or {B} (enters tapped) | AH35: {4}, tap: Scry 1 | AJ35: Bench sub available in D5: Swamp (2026-09-02); D5 target removed 2026-09-02 (bench sub in place)
A36: Slaughter Specialist | B36: =IF(AND(F36<>0,E36=F36),"In Hand",IF(AND(E36<>0,E36<F36,SUM(M36:R36)=0,SUM(T36:Y36)>0),"Extra-Sub",IF(AND(E36=0,E36<F36,SUM(M36:R36)=0,SUM(T36:Y36)>0),"Bench-Sub",IF(AND(E36=0,F36>0),"Bench",IF(E36<F36,"Extra",IF(AND(J36="",E36>F36),"To Buy",IF(SUM(J36,F36)<E36,"To Buy",IF(AND(SUM(J36,F36)>=E36,J36<>""),"Ordered",IF(AND(E36=0,F36=0,D36="B3"),"B3 Option",IF(AND(E36=0,F36=0),"Remove","To Buy")))))))))) | D36: B2 | E36: =SUM(M36:S36) | F36: =SUM(T36:Z36) | G36: =IF((F36-E36)>=0,F36-E36,0) | H36: =MAX(0,$E36-$F36-$J36) | K36: 0.88 | L36: =IF(AND($H36>0,ISNUMBER($K36)),$H36*$K36,0) | S36: =IF(AND(J36<>"",SUM(M36:R36)=0),J36,"") | AA36: Creature | AB36: Vampire Warrior | AC36: B | AD36: 2 | AE36: Innistrad: Midnight Hunt | AF36: Toughness Payoff | AG36: Gives each opponent a 1/1 Human token when it enters | AH36: Gets a +1/+1 counter whenever an opponent's creature dies | AJ36: Tuned add; Bench sub available in D4: Canopy Gargantuan (2026-09-02); D4 target removed 2026-09-02 (bench sub in place)
A37: Solemn Simulacrum | B37: =IF(AND(F37<>0,E37=F37),"In Hand",IF(AND(E37<>0,E37<F37,SUM(M37:R37)=0,SUM(T37:Y37)>0),"Extra-Sub",IF(AND(E37=0,E37<F37,SUM(M37:R37)=0,SUM(T37:Y37)>0),"Bench-Sub",IF(AND(E37=0,F37>0),"Bench",IF(E37<F37,"Extra",IF(AND(J37="",E37>F37),"To Buy",IF(SUM(J37,F37)<E37,"To Buy",IF(AND(SUM(J37,F37)>=E37,J37<>""),"Ordered",IF(AND(E37=0,F37=0,D37="B3"),"B3 Option",IF(AND(E37=0,F37=0),"Remove","To Buy")))))))))) | D37: B2 | E37: =SUM(M37:S37) | F37: =SUM(T37:Z37) | G37: =IF((F37-E37)>=0,F37-E37,0) | H37: =MAX(0,$E37-$F37-$J37) | K37: 0.29 | L37: =IF(AND($H37>0,ISNUMBER($K37)),$H37*$K37,0) | S37: =IF(AND(J37<>"",SUM(M37:R37)=0),J37,"") | AA37: Artifact Creature | AB37: Golem | AC37: C | AD37: 4 | AE37: Mirrodin | AF37: Ramp | AG37: Searches for a basic land and puts it onto the battlefield tapped when it enters | AH37: Draws a card when it dies | AJ37: Bench sub available in D4: Kor Cartographer (2026-09-02); D4 target removed 2026-09-02 (bench sub in place)
A38: Suture Priest | B38: =IF(AND(F38<>0,E38=F38),"In Hand",IF(AND(E38<>0,E38<F38,SUM(M38:R38)=0,SUM(T38:Y38)>0),"Extra-Sub",IF(AND(E38=0,E38<F38,SUM(M38:R38)=0,SUM(T38:Y38)>0),"Bench-Sub",IF(AND(E38=0,F38>0),"Bench",IF(E38<F38,"Extra",IF(AND(J38="",E38>F38),"To Buy",IF(SUM(J38,F38)<E38,"To Buy",IF(AND(SUM(J38,F38)>=E38,J38<>""),"Ordered",IF(AND(E38=0,F38=0,D38="B3"),"B3 Option",IF(AND(E38=0,F38=0),"Remove","To Buy")))))))))) | D38: B2 | E38: =SUM(M38:S38) | F38: =SUM(T38:Z38) | G38: =IF((F38-E38)>=0,F38-E38,0) | H38: =MAX(0,$E38-$F38-$J38) | K38: 4.67 | L38: =IF(AND($H38>0,ISNUMBER($K38)),$H38*$K38,0) | S38: =IF(AND(J38<>"",SUM(M38:R38)=0),J38,"") | AA38: Creature | AB38: Phyrexian Cleric | AC38: W | AD38: 2 | AE38: New Phyrexia | AF38: Drain Payoff | AG38: Gains you 1 life whenever another creature you control enters | AH38: May cause an opponent to lose 1 life whenever a creature they control enters | AJ38: Cut in Tuned; Removed from TCG cart 2026-09-02: on D5 Tuned CUT list; buy Skullclamp at the con instead; D5 target removed 2026-09-02: Tuned add Skullclamp takes the slot | AK38: [T] D5 target removed (not owned); buy Skullclamp instead
A39: Utter End | B39: =IF(AND(F39<>0,E39=F39),"In Hand",IF(AND(E39<>0,E39<F39,SUM(M39:R39)=0,SUM(T39:Y39)>0),"Extra-Sub",IF(AND(E39=0,E39<F39,SUM(M39:R39)=0,SUM(T39:Y39)>0),"Bench-Sub",IF(AND(E39=0,F39>0),"Bench",IF(E39<F39,"Extra",IF(AND(J39="",E39>F39),"To Buy",IF(SUM(J39,F39)<E39,"To Buy",IF(AND(SUM(J39,F39)>=E39,J39<>""),"Ordered",IF(AND(E39=0,F39=0,D39="B3"),"B3 Option",IF(AND(E39=0,F39=0),"Remove","To Buy")))))))))) | D39: B2 | E39: =SUM(M39:S39) | F39: =SUM(T39:Z39) | G39: =IF((F39-E39)>=0,F39-E39,0) | H39: =MAX(0,$E39-$F39-$J39) | K39: 0.29 | L39: =IF(AND($H39>0,ISNUMBER($K39)),$H39*$K39,0) | S39: =IF(AND(J39<>"",SUM(M39:R39)=0),J39,"") | AA39: Instant | AC39: Multi | AD39: 4 | AE39: Khans of Tarkir | AF39: Removal | AG39: Exiles target nonland permanent | AJ39: Bench sub available in D5: Chain Assassination (2026-09-02); D5 target removed 2026-09-02 (bench sub in place)
A40: Wall of Blossoms | B40: =IF(AND(F40<>0,E40=F40),"In Hand",IF(AND(E40<>0,E40<F40,SUM(M40:R40)=0,SUM(T40:Y40)>0),"Extra-Sub",IF(AND(E40=0,E40<F40,SUM(M40:R40)=0,SUM(T40:Y40)>0),"Bench-Sub",IF(AND(E40=0,F40>0),"Bench",IF(E40<F40,"Extra",IF(AND(J40="",E40>F40),"To Buy",IF(SUM(J40,F40)<E40,"To Buy",IF(AND(SUM(J40,F40)>=E40,J40<>""),"Ordered",IF(AND(E40=0,F40=0,D40="B3"),"B3 Option",IF(AND(E40=0,F40=0),"Remove","To Buy")))))))))) | D40: B2 | E40: =SUM(M40:S40) | F40: =SUM(T40:Z40) | G40: =IF((F40-E40)>=0,F40-E40,0) | H40: =MAX(0,$E40-$F40-$J40) | K40: 0.29 | L40: =IF(AND($H40>0,ISNUMBER($K40)),$H40*$K40,0) | S40: =IF(AND(J40<>"",SUM(M40:R40)=0),J40,"") | AA40: Creature | AB40: Plant Wall | AC40: G | AD40: 2 | AE40: Stronghold | AF40: Card Draw | AG40: Draws a card when it enters | AH40: Defender body | AJ40: Bench sub available in D4: Portcullis Vine (2026-09-02); D4 target removed 2026-09-02 (bench sub in place)
A41: Shared Animosity | B41: =IF(AND(F41<>0,E41=F41),"In Hand",IF(AND(E41<>0,E41<F41,SUM(M41:R41)=0,SUM(T41:Y41)>0),"Extra-Sub",IF(AND(E41=0,E41<F41,SUM(M41:R41)=0,SUM(T41:Y41)>0),"Bench-Sub",IF(AND(E41=0,F41>0),"Bench",IF(E41<F41,"Extra",IF(AND(J41="",E41>F41),"To Buy",IF(SUM(J41,F41)<E41,"To Buy",IF(AND(SUM(J41,F41)>=E41,J41<>""),"Ordered",IF(AND(E41=0,F41=0,D41="B3"),"B3 Option",IF(AND(E41=0,F41=0),"Remove","To Buy")))))))))) | D41: B3 | E41: =SUM(M41:S41) | F41: =SUM(T41:Z41) | G41: =IF((F41-E41)>=0,F41-E41,0) | H41: =MAX(0,$E41-$F41-$J41) | I41: WF | J41: 1 | K41: 4.47 | L41: =IF(AND($H41>0,ISNUMBER($K41)),$H41*$K41,0) | R41: 1 | S41: =IF(AND(J41<>"",SUM(M41:R41)=0),J41,"") | AA41: Enchantment | AC41: R | AD41: 3 | AE41: Morningtide | AF41: Tuned add | AG41: Whenever a creature you control attacks, it gets +1/+0 until end of turn for each other attacking creature that shares a | AJ41: D6 Tuned add; targeted 2026-09-02; replaces Alexios, Deimos of Kosmos; In cart: Game Theory Wake Forest $4.10 Near Mint [C20] (2026-09-03) | AK41: [T] targeted D6 (Tuned add, replaces Alexios, Deimos of Kosmos); [A later] ->D6 when bought
A42: Aetherize | B42: =IF(AND(F42<>0,E42=F42),"In Hand",IF(AND(E42<>0,E42<F42,SUM(M42:R42)=0,SUM(T42:Y42)>0),"Extra-Sub",IF(AND(E42=0,E42<F42,SUM(M42:R42)=0,SUM(T42:Y42)>0),"Bench-Sub",IF(AND(E42=0,F42>0),"Bench",IF(E42<F42,"Extra",IF(AND(J42="",E42>F42),"To Buy",IF(SUM(J42,F42)<E42,"To Buy",IF(AND(SUM(J42,F42)>=E42,J42<>""),"Ordered",IF(AND(E42=0,F42=0,D42="B3"),"B3 Option",IF(AND(E42=0,F42=0),"Remove","To Buy")))))))))) | D42: B2 | E42: =SUM(M42:S42) | F42: =SUM(T42:Z42) | G42: =IF((F42-E42)>=0,F42-E42,0) | H42: =MAX(0,$E42-$F42-$J42) | I42: TCG | J42: 1 | K42: 0.62 | L42: =IF(AND($H42>0,ISNUMBER($K42)),$H42*$K42,0) | N42: 1 | S42: =IF(AND(J42<>"",SUM(M42:R42)=0),J42,"") | AA42: Instant | AC42: U | AD42: 4 | AE42: Gatecrash | AF42: Interaction | AG42: Returns all attacking creatures to their owners' hands | AJ42: Tuned add; bounce all attackers - token-swarm answer; Ordered 2026-09-02: TCGplayer $0.39 NM from NostalgiAtog
A43: Anguished Unmaking | B43: =IF(AND(F43<>0,E43=F43),"In Hand",IF(AND(E43<>0,E43<F43,SUM(M43:R43)=0,SUM(T43:Y43)>0),"Extra-Sub",IF(AND(E43=0,E43<F43,SUM(M43:R43)=0,SUM(T43:Y43)>0),"Bench-Sub",IF(AND(E43=0,F43>0),"Bench",IF(E43<F43,"Extra",IF(AND(J43="",E43>F43),"To Buy",IF(SUM(J43,F43)<E43,"To Buy",IF(AND(SUM(J43,F43)>=E43,J43<>""),"Ordered",IF(AND(E43=0,F43=0,D43="B3"),"B3 Option",IF(AND(E43=0,F43=0),"Remove","To Buy")))))))))) | D43: B2 | E43: =SUM(M43:S43) | F43: =SUM(T43:Z43) | G43: =IF((F43-E43)>=0,F43-E43,0) | H43: =MAX(0,$E43-$F43-$J43) | I43: TCG | J43: 1 | K43: 1.46 | L43: =IF(AND($H43>0,ISNUMBER($K43)),$H43*$K43,0) | O43: 1 | P43: 1 | S43: =IF(AND(J43<>"",SUM(M43:R43)=0),J43,"") | V43: 1 | AA43: Instant | AC43: Multi | AD43: 3 | AE43: Shadows over Innistrad | AF43: Removal | AG43: Exiles target nonland permanent | AH43: You lose 3 life | AJ43: 1 on order
A44: Arboreal Grazer | B44: =IF(AND(F44<>0,E44=F44),"In Hand",IF(AND(E44<>0,E44<F44,SUM(M44:R44)=0,SUM(T44:Y44)>0),"Extra-Sub",IF(AND(E44=0,E44<F44,SUM(M44:R44)=0,SUM(T44:Y44)>0),"Bench-Sub",IF(AND(E44=0,F44>0),"Bench",IF(E44<F44,"Extra",IF(AND(J44="",E44>F44),"To Buy",IF(SUM(J44,F44)<E44,"To Buy",IF(AND(SUM(J44,F44)>=E44,J44<>""),"Ordered",IF(AND(E44=0,F44=0,D44="B3"),"B3 Option",IF(AND(E44=0,F44=0),"Remove","To Buy")))))))))) | D44: B2 | E44: =SUM(M44:S44) | F44: =SUM(T44:Z44) | G44: =IF((F44-E44)>=0,F44-E44,0) | H44: =MAX(0,$E44-$F44-$J44) | I44: TCG | J44: 1 | K44: 0.23 | L44: =IF(AND($H44>0,ISNUMBER($K44)),$H44*$K44,0) | P44: 1 | S44: =IF(AND(J44<>"",SUM(M44:R44)=0),J44,"") | AA44: Creature | AB44: Sloth Beast | AC44: G | AD44: 1 | AE44: War of the Spark | AF44: Ramp | AG44: Puts a land from your hand onto the battlefield tapped, on ETB | AH44: Reach body
A45: Argentum Masticore | B45: =IF(AND(F45<>0,E45=F45),"In Hand",IF(AND(E45<>0,E45<F45,SUM(M45:R45)=0,SUM(T45:Y45)>0),"Extra-Sub",IF(AND(E45=0,E45<F45,SUM(M45:R45)=0,SUM(T45:Y45)>0),"Bench-Sub",IF(AND(E45=0,F45>0),"Bench",IF(E45<F45,"Extra",IF(AND(J45="",E45>F45),"To Buy",IF(SUM(J45,F45)<E45,"To Buy",IF(AND(SUM(J45,F45)>=E45,J45<>""),"Ordered",IF(AND(E45=0,F45=0,D45="B3"),"B3 Option",IF(AND(E45=0,F45=0),"Remove","To Buy")))))))))) | D45: B2 | E45: =SUM(M45:S45) | F45: =SUM(T45:Z45) | G45: =IF((F45-E45)>=0,F45-E45,0) | H45: =MAX(0,$E45-$F45-$J45) | I45: TCG | J45: 1 | K45: 0.32 | L45: =IF(AND($H45>0,ISNUMBER($K45)),$H45*$K45,0) | Q45: 1 | S45: =IF(AND(J45<>"",SUM(M45:R45)=0),J45,"") | AA45: Artifact Creature | AB45: Phyrexian Masticore | AC45: C | AD45: 5 | AE45: Phyrexia: All Will Be One | AF45: Removal | AG45: Discard a card each upkeep or sacrifice this creature | AH45: Discarding destroys an opponent's permanent MV ≤ the discarded card | AI45: First strike, protection from multicolored body
A46: Artisan of Kozilek | B46: =IF(AND(F46<>0,E46=F46),"In Hand",IF(AND(E46<>0,E46<F46,SUM(M46:R46)=0,SUM(T46:Y46)>0),"Extra-Sub",IF(AND(E46=0,E46<F46,SUM(M46:R46)=0,SUM(T46:Y46)>0),"Bench-Sub",IF(AND(E46=0,F46>0),"Bench",IF(E46<F46,"Extra",IF(AND(J46="",E46>F46),"To Buy",IF(SUM(J46,F46)<E46,"To Buy",IF(AND(SUM(J46,F46)>=E46,J46<>""),"Ordered",IF(AND(E46=0,F46=0,D46="B3"),"B3 Option",IF(AND(E46=0,F46=0),"Remove","To Buy")))))))))) | D46: B2 | E46: =SUM(M46:S46) | F46: =SUM(T46:Z46) | G46: =IF((F46-E46)>=0,F46-E46,0) | H46: =MAX(0,$E46-$F46-$J46) | I46: TCG | J46: 1 | L46: =IF(AND($H46>0,ISNUMBER($K46)),$H46*$K46,0) | S46: =IF(AND(J46<>"",SUM(M46:R46)=0),J46,"") | AA46: ? | AB46: Eldrazi | AC46: C | AD46: 9 | AE46: Rise of the Eldrazi | AF46: Reanimation | AG46: Returns a creature card from graveyard to battlefield when cast | AH46: Annihilator 2 (opponent sacrifices two permanents when it attacks) | AI46: 9-mana Eldrazi body | AJ46: arrives -> Bench (slot was upgraded)
A47: Ash Barrens | B47: =IF(AND(F47<>0,E47=F47),"In Hand",IF(AND(E47<>0,E47<F47,SUM(M47:R47)=0,SUM(T47:Y47)>0),"Extra-Sub",IF(AND(E47=0,E47<F47,SUM(M47:R47)=0,SUM(T47:Y47)>0),"Bench-Sub",IF(AND(E47=0,F47>0),"Bench",IF(E47<F47,"Extra",IF(AND(J47="",E47>F47),"To Buy",IF(SUM(J47,F47)<E47,"To Buy",IF(AND(SUM(J47,F47)>=E47,J47<>""),"Ordered",IF(AND(E47=0,F47=0,D47="B3"),"B3 Option",IF(AND(E47=0,F47=0),"Remove","To Buy")))))))))) | D47: B2 | E47: =SUM(M47:S47) | F47: =SUM(T47:Z47) | G47: =IF((F47-E47)>=0,F47-E47,0) | H47: =MAX(0,$E47-$F47-$J47) | I47: TCG | J47: 1 | K47: 0.25 | L47: =IF(AND($H47>0,ISNUMBER($K47)),$H47*$K47,0) | P47: 1 | S47: =IF(AND(J47<>"",SUM(M47:R47)=0),J47,"") | AA47: Land | AC47: L | AD47: 0 | AE47: Commander 2016 | AF47: Land | AG47: Taps for {C} | AH47: Basic landcycling {1}: discard to fetch a basic land
A48: Assault Formation | B48: =IF(AND(F48<>0,E48=F48),"In Hand",IF(AND(E48<>0,E48<F48,SUM(M48:R48)=0,SUM(T48:Y48)>0),"Extra-Sub",IF(AND(E48=0,E48<F48,SUM(M48:R48)=0,SUM(T48:Y48)>0),"Bench-Sub",IF(AND(E48=0,F48>0),"Bench",IF(E48<F48,"Extra",IF(AND(J48="",E48>F48),"To Buy",IF(SUM(J48,F48)<E48,"To Buy",IF(AND(SUM(J48,F48)>=E48,J48<>""),"Ordered",IF(AND(E48=0,F48=0,D48="B3"),"B3 Option",IF(AND(E48=0,F48=0),"Remove","To Buy")))))))))) | D48: B2 | E48: =SUM(M48:S48) | F48: =SUM(T48:Z48) | G48: =IF((F48-E48)>=0,F48-E48,0) | H48: =MAX(0,$E48-$F48-$J48) | I48: TCG | J48: 1 | K48: 0.72 | L48: =IF(AND($H48>0,ISNUMBER($K48)),$H48*$K48,0) | P48: 1 | S48: =IF(AND(J48<>"",SUM(M48:R48)=0),J48,"") | AA48: Enchantment | AC48: G | AD48: 2 | AE48: Dragons of Tarkir | AF48: Toughness Payoff | AG48: Your creatures assign combat damage equal to toughness rather than power | AH48: {G}: Target defender can attack this turn | AI48: {2}{G}: Creatures you control get +0/+1
A49: Azorius Chancery | B49: =IF(AND(F49<>0,E49=F49),"In Hand",IF(AND(E49<>0,E49<F49,SUM(M49:R49)=0,SUM(T49:Y49)>0),"Extra-Sub",IF(AND(E49=0,E49<F49,SUM(M49:R49)=0,SUM(T49:Y49)>0),"Bench-Sub",IF(AND(E49=0,F49>0),"Bench",IF(E49<F49,"Extra",IF(AND(J49="",E49>F49),"To Buy",IF(SUM(J49,F49)<E49,"To Buy",IF(AND(SUM(J49,F49)>=E49,J49<>""),"Ordered",IF(AND(E49=0,F49=0,D49="B3"),"B3 Option",IF(AND(E49=0,F49=0),"Remove","To Buy")))))))))) | D49: B2 | E49: =SUM(M49:S49) | F49: =SUM(T49:Z49) | G49: =IF((F49-E49)>=0,F49-E49,0) | H49: =MAX(0,$E49-$F49-$J49) | I49: TCG | J49: 1 | K49: 0.32 | L49: =IF(AND($H49>0,ISNUMBER($K49)),$H49*$K49,0) | N49: 1 | S49: =IF(AND(J49<>"",SUM(M49:R49)=0),J49,"") | AA49: Land | AC49: L | AD49: 0 | AE49: Dissension | AF49: Land | AG49: Taps for {W}{U} | AH49: Enters tapped; bounces a land you control when it enters | AJ49: Tuned add
A50: Azorius Signet | B50: =IF(AND(F50<>0,E50=F50),"In Hand",IF(AND(E50<>0,E50<F50,SUM(M50:R50)=0,SUM(T50:Y50)>0),"Extra-Sub",IF(AND(E50=0,E50<F50,SUM(M50:R50)=0,SUM(T50:Y50)>0),"Bench-Sub",IF(AND(E50=0,F50>0),"Bench",IF(E50<F50,"Extra",IF(AND(J50="",E50>F50),"To Buy",IF(SUM(J50,F50)<E50,"To Buy",IF(AND(SUM(J50,F50)>=E50,J50<>""),"Ordered",IF(AND(E50=0,F50=0,D50="B3"),"B3 Option",IF(AND(E50=0,F50=0),"Remove","To Buy")))))))))) | D50: B2 | E50: =SUM(M50:S50) | F50: =SUM(T50:Z50) | G50: =IF((F50-E50)>=0,F50-E50,0) | H50: =MAX(0,$E50-$F50-$J50) | I50: TCG | J50: 1 | K50: 0.3 | L50: =IF(AND($H50>0,ISNUMBER($K50)),$H50*$K50,0) | O50: 1 | S50: =IF(AND(J50<>"",SUM(M50:R50)=0),J50,"") | AA50: Artifact | AC50: Multi | AD50: 2 | AE50: Dissension | AF50: Mana Rock | AG50: {1}, tap: add {W}{U} | AJ50: Tuned add; mana fixing; Ordered 2026-09-02: TCGplayer $0.25 NM from NostalgiAtog
A51: Bastion of Remembrance | B51: =IF(AND(F51<>0,E51=F51),"In Hand",IF(AND(E51<>0,E51<F51,SUM(M51:R51)=0,SUM(T51:Y51)>0),"Extra-Sub",IF(AND(E51=0,E51<F51,SUM(M51:R51)=0,SUM(T51:Y51)>0),"Bench-Sub",IF(AND(E51=0,F51>0),"Bench",IF(E51<F51,"Extra",IF(AND(J51="",E51>F51),"To Buy",IF(SUM(J51,F51)<E51,"To Buy",IF(AND(SUM(J51,F51)>=E51,J51<>""),"Ordered",IF(AND(E51=0,F51=0,D51="B3"),"B3 Option",IF(AND(E51=0,F51=0),"Remove","To Buy")))))))))) | D51: B2 | E51: =SUM(M51:S51) | F51: =SUM(T51:Z51) | G51: =IF((F51-E51)>=0,F51-E51,0) | H51: =MAX(0,$E51-$F51-$J51) | I51: TCG | J51: 1 | K51: 0.36 | L51: =IF(AND($H51>0,ISNUMBER($K51)),$H51*$K51,0) | Q51: 1 | S51: =IF(AND(J51<>"",SUM(M51:R51)=0),J51,"") | AA51: Enchantment | AC51: B | AD51: 3 | AE51: Ikoria: Lair of Behemoths | AF51: Drain Payoff | AG51: Whenever a creature you control dies, each opponent loses 1 life and you gain 1 life | AH51: Creates a 1/1 Human Soldier token when it enters | AJ51: Ordered 2026-09-02: TCGplayer $0.31 NM from NostalgiAtog
A52: Beetleback Chief | B52: =IF(AND(F52<>0,E52=F52),"In Hand",IF(AND(E52<>0,E52<F52,SUM(M52:R52)=0,SUM(T52:Y52)>0),"Extra-Sub",IF(AND(E52=0,E52<F52,SUM(M52:R52)=0,SUM(T52:Y52)>0),"Bench-Sub",IF(AND(E52=0,F52>0),"Bench",IF(E52<F52,"Extra",IF(AND(J52="",E52>F52),"To Buy",IF(SUM(J52,F52)<E52,"To Buy",IF(AND(SUM(J52,F52)>=E52,J52<>""),"Ordered",IF(AND(E52=0,F52=0,D52="B3"),"B3 Option",IF(AND(E52=0,F52=0),"Remove","To Buy")))))))))) | D52: B2 | E52: =SUM(M52:S52) | F52: =SUM(T52:Z52) | G52: =IF((F52-E52)>=0,F52-E52,0) | H52: =MAX(0,$E52-$F52-$J52) | I52: TCG | J52: 1 | K52: 0.31 | L52: =IF(AND($H52>0,ISNUMBER($K52)),$H52*$K52,0) | R52: 1 | S52: =IF(AND(J52<>"",SUM(M52:R52)=0),J52,"") | AA52: Creature | AB52: Goblin Warrior | AC52: R | AD52: 4 | AE52: Planechase 2012 | AF52: Token Producer | AG52: Creates two 1/1 Goblin tokens when it enters | AJ52: Ordered 2026-09-02: TCGplayer $0.24 LP from The WKGR Online
A53: Big Score | B53: =IF(AND(F53<>0,E53=F53),"In Hand",IF(AND(E53<>0,E53<F53,SUM(M53:R53)=0,SUM(T53:Y53)>0),"Extra-Sub",IF(AND(E53=0,E53<F53,SUM(M53:R53)=0,SUM(T53:Y53)>0),"Bench-Sub",IF(AND(E53=0,F53>0),"Bench",IF(E53<F53,"Extra",IF(AND(J53="",E53>F53),"To Buy",IF(SUM(J53,F53)<E53,"To Buy",IF(AND(SUM(J53,F53)>=E53,J53<>""),"Ordered",IF(AND(E53=0,F53=0,D53="B3"),"B3 Option",IF(AND(E53=0,F53=0),"Remove","To Buy")))))))))) | D53: B2 | E53: =SUM(M53:S53) | F53: =SUM(T53:Z53) | G53: =IF((F53-E53)>=0,F53-E53,0) | H53: =MAX(0,$E53-$F53-$J53) | I53: TCG | J53: 1 | K53: 0.45 | L53: =IF(AND($H53>0,ISNUMBER($K53)),$H53*$K53,0) | R53: 1 | S53: =IF(AND(J53<>"",SUM(M53:R53)=0),J53,"") | AA53: Instant | AC53: R | AD53: 4 | AE53: Streets of New Capenna | AF53: Card Draw | AG53: Discard a card to draw two cards and create two Treasure tokens | AJ53: Ordered 2026-09-02: TCGplayer $1.33 LPF from The WKGR Online
A54: Blasphemous Act | B54: =IF(AND(F54<>0,E54=F54),"In Hand",IF(AND(E54<>0,E54<F54,SUM(M54:R54)=0,SUM(T54:Y54)>0),"Extra-Sub",IF(AND(E54=0,E54<F54,SUM(M54:R54)=0,SUM(T54:Y54)>0),"Bench-Sub",IF(AND(E54=0,F54>0),"Bench",IF(E54<F54,"Extra",IF(AND(J54="",E54>F54),"To Buy",IF(SUM(J54,F54)<E54,"To Buy",IF(AND(SUM(J54,F54)>=E54,J54<>""),"Ordered",IF(AND(E54=0,F54=0,D54="B3"),"B3 Option",IF(AND(E54=0,F54=0),"Remove","To Buy")))))))))) | D54: B2 | E54: =SUM(M54:S54) | F54: =SUM(T54:Z54) | G54: =IF((F54-E54)>=0,F54-E54,0) | H54: =MAX(0,$E54-$F54-$J54) | I54: TCG | J54: 1 | K54: 0.98 | L54: =IF(AND($H54>0,ISNUMBER($K54)),$H54*$K54,0) | R54: 1 | S54: =IF(AND(J54<>"",SUM(M54:R54)=0),J54,"") | AA54: Sorcery | AC54: R | AD54: 9 | AE54: Innistrad | AF54: Board Wipe | AG54: Deals 13 damage to each creature | AH54: Costs {1} less for each creature on the battlefield | AJ54: Ordered 2026-09-02: TCGplayer $0.91 NM from NostalgiAtog
A55: Buried Ruin | B55: =IF(AND(F55<>0,E55=F55),"In Hand",IF(AND(E55<>0,E55<F55,SUM(M55:R55)=0,SUM(T55:Y55)>0),"Extra-Sub",IF(AND(E55=0,E55<F55,SUM(M55:R55)=0,SUM(T55:Y55)>0),"Bench-Sub",IF(AND(E55=0,F55>0),"Bench",IF(E55<F55,"Extra",IF(AND(J55="",E55>F55),"To Buy",IF(SUM(J55,F55)<E55,"To Buy",IF(AND(SUM(J55,F55)>=E55,J55<>""),"Ordered",IF(AND(E55=0,F55=0,D55="B3"),"B3 Option",IF(AND(E55=0,F55=0),"Remove","To Buy")))))))))) | D55: B2 | E55: =SUM(M55:S55) | F55: =SUM(T55:Z55) | G55: =IF((F55-E55)>=0,F55-E55,0) | H55: =MAX(0,$E55-$F55-$J55) | I55: TCG | J55: 1 | K55: 0.39 | L55: =IF(AND($H55>0,ISNUMBER($K55)),$H55*$K55,0) | R55: 1 | S55: =IF(AND(J55<>"",SUM(M55:R55)=0),J55,"") | AA55: Land | AC55: L | AD55: 0 | AE55: Magic 2012 | AF55: Land | AG55: Taps for {C} | AH55: Sacrifice plus {2}: return target artifact card from graveyard to hand | AJ55: Ordered 2026-09-02: TCGplayer $0.82 LP from The WKGR Online
A56: Carven Caryatid | B56: =IF(AND(F56<>0,E56=F56),"In Hand",IF(AND(E56<>0,E56<F56,SUM(M56:R56)=0,SUM(T56:Y56)>0),"Extra-Sub",IF(AND(E56=0,E56<F56,SUM(M56:R56)=0,SUM(T56:Y56)>0),"Bench-Sub",IF(AND(E56=0,F56>0),"Bench",IF(E56<F56,"Extra",IF(AND(J56="",E56>F56),"To Buy",IF(SUM(J56,F56)<E56,"To Buy",IF(AND(SUM(J56,F56)>=E56,J56<>""),"Ordered",IF(AND(E56=0,F56=0,D56="B3"),"B3 Option",IF(AND(E56=0,F56=0),"Remove","To Buy")))))))))) | D56: B2 | E56: =SUM(M56:S56) | F56: =SUM(T56:Z56) | G56: =IF((F56-E56)>=0,F56-E56,0) | H56: =MAX(0,$E56-$F56-$J56) | I56: TCG | J56: 1 | K56: 0.23 | L56: =IF(AND($H56>0,ISNUMBER($K56)),$H56*$K56,0) | P56: 1 | S56: =IF(AND(J56<>"",SUM(M56:R56)=0),J56,"") | AA56: Creature | AB56: Spirit | AC56: G | AD56: 3 | AE56: Ravnica: City of Guilds | AF56: Card Draw | AG56: Draws a card when it enters | AH56: Defender body
A57: Castle Ardenvale | B57: =IF(AND(F57<>0,E57=F57),"In Hand",IF(AND(E57<>0,E57<F57,SUM(M57:R57)=0,SUM(T57:Y57)>0),"Extra-Sub",IF(AND(E57=0,E57<F57,SUM(M57:R57)=0,SUM(T57:Y57)>0),"Bench-Sub",IF(AND(E57=0,F57>0),"Bench",IF(E57<F57,"Extra",IF(AND(J57="",E57>F57),"To Buy",IF(SUM(J57,F57)<E57,"To Buy",IF(AND(SUM(J57,F57)>=E57,J57<>""),"Ordered",IF(AND(E57=0,F57=0,D57="B3"),"B3 Option",IF(AND(E57=0,F57=0),"Remove","To Buy")))))))))) | D57: B2 | E57: =SUM(M57:S57) | F57: =SUM(T57:Z57) | G57: =IF((F57-E57)>=0,F57-E57,0) | H57: =MAX(0,$E57-$F57-$J57) | I57: TCG | J57: 1 | K57: 0.25 | L57: =IF(AND($H57>0,ISNUMBER($K57)),$H57*$K57,0) | Q57: 1 | S57: =IF(AND(J57<>"",SUM(M57:R57)=0),J57,"") | AA57: Land | AC57: L | AD57: 0 | AE57: Throne of Eldraine | AF57: Land | AG57: Taps for {W} | AH57: {2}{W}{W}, tap: creates a 1/1 Human token | AJ57: Ordered 2026-09-02: TCGplayer $0.19 LP from The WKGR Online
A58: Castle Embereth | B58: =IF(AND(F58<>0,E58=F58),"In Hand",IF(AND(E58<>0,E58<F58,SUM(M58:R58)=0,SUM(T58:Y58)>0),"Extra-Sub",IF(AND(E58=0,E58<F58,SUM(M58:R58)=0,SUM(T58:Y58)>0),"Bench-Sub",IF(AND(E58=0,F58>0),"Bench",IF(E58<F58,"Extra",IF(AND(J58="",E58>F58),"To Buy",IF(SUM(J58,F58)<E58,"To Buy",IF(AND(SUM(J58,F58)>=E58,J58<>""),"Ordered",IF(AND(E58=0,F58=0,D58="B3"),"B3 Option",IF(AND(E58=0,F58=0),"Remove","To Buy")))))))))) | D58: B2 | E58: =SUM(M58:S58) | F58: =SUM(T58:Z58) | G58: =IF((F58-E58)>=0,F58-E58,0) | H58: =MAX(0,$E58-$F58-$J58) | I58: TCG | J58: 1 | K58: 0.3 | L58: =IF(AND($H58>0,ISNUMBER($K58)),$H58*$K58,0) | R58: 1 | S58: =IF(AND(J58<>"",SUM(M58:R58)=0),J58,"") | AA58: Land | AC58: L | AD58: 0 | AE58: Throne of Eldraine | AF58: Land | AG58: Taps for {R} | AH58: {1}{R}{R}, tap: creatures you control get +1/+0 | AJ58: Ordered 2026-09-02: TCGplayer $0.35 NM from The WKGR Online
A59: Caves of Koilos | B59: =IF(AND(F59<>0,E59=F59),"In Hand",IF(AND(E59<>0,E59<F59,SUM(M59:R59)=0,SUM(T59:Y59)>0),"Extra-Sub",IF(AND(E59=0,E59<F59,SUM(M59:R59)=0,SUM(T59:Y59)>0),"Bench-Sub",IF(AND(E59=0,F59>0),"Bench",IF(E59<F59,"Extra",IF(AND(J59="",E59>F59),"To Buy",IF(SUM(J59,F59)<E59,"To Buy",IF(AND(SUM(J59,F59)>=E59,J59<>""),"Ordered",IF(AND(E59=0,F59=0,D59="B3"),"B3 Option",IF(AND(E59=0,F59=0),"Remove","To Buy")))))))))) | D59: B2 | E59: =SUM(M59:S59) | F59: =SUM(T59:Z59) | G59: =IF((F59-E59)>=0,F59-E59,0) | H59: =MAX(0,$E59-$F59-$J59) | I59: TCG | J59: 1 | K59: 0.75 | L59: =IF(AND($H59>0,ISNUMBER($K59)),$H59*$K59,0) | Q59: 1 | S59: =IF(AND(J59<>"",SUM(M59:R59)=0),J59,"") | AA59: Land | AC59: L | AD59: 0 | AE59: Apocalypse | AF59: Land | AG59: Taps for {C}, or {W}/{B} at the cost of 1 damage to you | AJ59: Ordered 2026-09-02: TCGplayer $0.67 LP from The Next Level Games
A60: Chaos Warp | B60: =IF(AND(F60<>0,E60=F60),"In Hand",IF(AND(E60<>0,E60<F60,SUM(M60:R60)=0,SUM(T60:Y60)>0),"Extra-Sub",IF(AND(E60=0,E60<F60,SUM(M60:R60)=0,SUM(T60:Y60)>0),"Bench-Sub",IF(AND(E60=0,F60>0),"Bench",IF(E60<F60,"Extra",IF(AND(J60="",E60>F60),"To Buy",IF(SUM(J60,F60)<E60,"To Buy",IF(AND(SUM(J60,F60)>=E60,J60<>""),"Ordered",IF(AND(E60=0,F60=0,D60="B3"),"B3 Option",IF(AND(E60=0,F60=0),"Remove","To Buy")))))))))) | D60: B2 | E60: =SUM(M60:S60) | F60: =SUM(T60:Z60) | G60: =IF((F60-E60)>=0,F60-E60,0) | H60: =MAX(0,$E60-$F60-$J60) | I60: TCG | J60: 1 | K60: 0.34 | L60: =IF(AND($H60>0,ISNUMBER($K60)),$H60*$K60,0) | R60: 1 | S60: =IF(AND(J60<>"",SUM(M60:R60)=0),J60,"") | AA60: Instant | AC60: R | AD60: 3 | AE60: Commander 2011 | AF60: Removal | AG60: Shuffles target permanent into its owner's library, who may hit a new permanent off the top | AJ60: Ordered 2026-09-02: TCGplayer $0.34 NM from NostalgiAtog
A61: Charming Prince | B61: =IF(AND(F61<>0,E61=F61),"In Hand",IF(AND(E61<>0,E61<F61,SUM(M61:R61)=0,SUM(T61:Y61)>0),"Extra-Sub",IF(AND(E61=0,E61<F61,SUM(M61:R61)=0,SUM(T61:Y61)>0),"Bench-Sub",IF(AND(E61=0,F61>0),"Bench",IF(E61<F61,"Extra",IF(AND(J61="",E61>F61),"To Buy",IF(SUM(J61,F61)<E61,"To Buy",IF(AND(SUM(J61,F61)>=E61,J61<>""),"Ordered",IF(AND(E61=0,F61=0,D61="B3"),"B3 Option",IF(AND(E61=0,F61=0),"Remove","To Buy")))))))))) | D61: B2 | E61: =SUM(M61:S61) | F61: =SUM(T61:Z61) | G61: =IF((F61-E61)>=0,F61-E61,0) | H61: =MAX(0,$E61-$F61-$J61) | I61: TCG | J61: 1 | K61: 0.31 | L61: =IF(AND($H61>0,ISNUMBER($K61)),$H61*$K61,0) | N61: 1 | S61: =IF(AND(J61<>"",SUM(M61:R61)=0),J61,"") | AA61: Creature | AB61: Human Noble | AC61: W | AD61: 2 | AE61: Throne of Eldraine | AF61: Blink | AG61: Choose one when it enters: Scry 2, gain 3 life, or blink another target creature you own | AJ61: Ordered 2026-09-02: TCGplayer $0.36 NM from NostalgiAtog
A62: Chocobo Knights | B62: =IF(AND(F62<>0,E62=F62),"In Hand",IF(AND(E62<>0,E62<F62,SUM(M62:R62)=0,SUM(T62:Y62)>0),"Extra-Sub",IF(AND(E62=0,E62<F62,SUM(M62:R62)=0,SUM(T62:Y62)>0),"Bench-Sub",IF(AND(E62=0,F62>0),"Bench",IF(E62<F62,"Extra",IF(AND(J62="",E62>F62),"To Buy",IF(SUM(J62,F62)<E62,"To Buy",IF(AND(SUM(J62,F62)>=E62,J62<>""),"Ordered",IF(AND(E62=0,F62=0,D62="B3"),"B3 Option",IF(AND(E62=0,F62=0),"Remove","To Buy")))))))))) | D62: B2 | E62: =SUM(M62:S62) | F62: =SUM(T62:Z62) | G62: =IF((F62-E62)>=0,F62-E62,0) | H62: =MAX(0,$E62-$F62-$J62) | I62: TCG | J62: 1 | K62: 0.34 | L62: =IF(AND($H62>0,ISNUMBER($K62)),$H62*$K62,0) | Q62: 1 | S62: =IF(AND(J62<>"",SUM(M62:R62)=0),J62,"") | AA62: Creature | AB62: Human Knight | AC62: W | AD62: 4 | AE62: Final Fantasy Commander | AF62: Counters Payoff | AG62: Creatures you control with counters gain double strike when you attack | AK62: [B3 later] D5->B when Dictate of Erebos is bought
A63: Chulane, Teller of Tales | B63: =IF(AND(F63<>0,E63=F63),"In Hand",IF(AND(E63<>0,E63<F63,SUM(M63:R63)=0,SUM(T63:Y63)>0),"Extra-Sub",IF(AND(E63=0,E63<F63,SUM(M63:R63)=0,SUM(T63:Y63)>0),"Bench-Sub",IF(AND(E63=0,F63>0),"Bench",IF(E63<F63,"Extra",IF(AND(J63="",E63>F63),"To Buy",IF(SUM(J63,F63)<E63,"To Buy",IF(AND(SUM(J63,F63)>=E63,J63<>""),"Ordered",IF(AND(E63=0,F63=0,D63="B3"),"B3 Option",IF(AND(E63=0,F63=0),"Remove","To Buy")))))))))) | D63: B2 | E63: =SUM(M63:S63) | F63: =SUM(T63:Z63) | G63: =IF((F63-E63)>=0,F63-E63,0) | H63: =MAX(0,$E63-$F63-$J63) | I63: TCG | J63: 1 | K63: 6.15 | L63: =IF(AND($H63>0,ISNUMBER($K63)),$H63*$K63,0) | N63: 1 | S63: =IF(AND(J63<>"",SUM(M63:R63)=0),J63,"") | AA63: Legendary Creature | AB63: Human Druid | AC63: Multi | AD63: 5 | AE63: Throne of Eldraine | AF63: Commander | AG63: Draw a card and may put a land from hand onto the battlefield whenever you cast a creature spell | AH63: {3}, tap: return target creature you control to hand | AI63: Vigilance body | AJ63: Commander - D2; Ordered 2026-09-02: TCGplayer $5.44 LP Foil from The WKGR Online (added by Rob)
A64: Cloudblazer | B64: =IF(AND(F64<>0,E64=F64),"In Hand",IF(AND(E64<>0,E64<F64,SUM(M64:R64)=0,SUM(T64:Y64)>0),"Extra-Sub",IF(AND(E64=0,E64<F64,SUM(M64:R64)=0,SUM(T64:Y64)>0),"Bench-Sub",IF(AND(E64=0,F64>0),"Bench",IF(E64<F64,"Extra",IF(AND(J64="",E64>F64),"To Buy",IF(SUM(J64,F64)<E64,"To Buy",IF(AND(SUM(J64,F64)>=E64,J64<>""),"Ordered",IF(AND(E64=0,F64=0,D64="B3"),"B3 Option",IF(AND(E64=0,F64=0),"Remove","To Buy")))))))))) | D64: B2 | E64: =SUM(M64:S64) | F64: =SUM(T64:Z64) | G64: =IF((F64-E64)>=0,F64-E64,0) | H64: =MAX(0,$E64-$F64-$J64) | I64: TCG | J64: 1 | K64: 0.14 | L64: =IF(AND($H64>0,ISNUMBER($K64)),$H64*$K64,0) | N64: 1 | S64: =IF(AND(J64<>"",SUM(M64:R64)=0),J64,"") | AA64: Creature | AB64: Human Scout | AC64: Multi | AD64: 5 | AE64: Kaladesh | AF64: Card Draw | AG64: Gain 2 life and draw two cards when it enters | AH64: Flying body | AJ64: Tuned add
A65: Contagion Clasp | B65: =IF(AND(F65<>0,E65=F65),"In Hand",IF(AND(E65<>0,E65<F65,SUM(M65:R65)=0,SUM(T65:Y65)>0),"Extra-Sub",IF(AND(E65=0,E65<F65,SUM(M65:R65)=0,SUM(T65:Y65)>0),"Bench-Sub",IF(AND(E65=0,F65>0),"Bench",IF(E65<F65,"Extra",IF(AND(J65="",E65>F65),"To Buy",IF(SUM(J65,F65)<E65,"To Buy",IF(AND(SUM(J65,F65)>=E65,J65<>""),"Ordered",IF(AND(E65=0,F65=0,D65="B3"),"B3 Option",IF(AND(E65=0,F65=0),"Remove","To Buy")))))))))) | D65: B2 | E65: =SUM(M65:S65) | F65: =SUM(T65:Z65) | G65: =IF((F65-E65)>=0,F65-E65,0) | H65: =MAX(0,$E65-$F65-$J65) | I65: TCG | J65: 1 | K65: 0.38 | L65: =IF(AND($H65>0,ISNUMBER($K65)),$H65*$K65,0) | O65: 1 | S65: =IF(AND(J65<>"",SUM(M65:R65)=0),J65,"") | AA65: Artifact | AC65: C | AD65: 2 | AE65: Duel Decks: Elspeth vs. Tezzeret | AF65: Proliferate | AG65: Puts a -1/-1 counter on target creature when it enters | AH65: {4}, tap: Proliferate | AJ65: Tuned add
A66: Corpse Knight | B66: =IF(AND(F66<>0,E66=F66),"In Hand",IF(AND(E66<>0,E66<F66,SUM(M66:R66)=0,SUM(T66:Y66)>0),"Extra-Sub",IF(AND(E66=0,E66<F66,SUM(M66:R66)=0,SUM(T66:Y66)>0),"Bench-Sub",IF(AND(E66=0,F66>0),"Bench",IF(E66<F66,"Extra",IF(AND(J66="",E66>F66),"To Buy",IF(SUM(J66,F66)<E66,"To Buy",IF(AND(SUM(J66,F66)>=E66,J66<>""),"Ordered",IF(AND(E66=0,F66=0,D66="B3"),"B3 Option",IF(AND(E66=0,F66=0),"Remove","To Buy")))))))))) | D66: B2 | E66: =SUM(M66:S66) | F66: =SUM(T66:Z66) | G66: =IF((F66-E66)>=0,F66-E66,0) | H66: =MAX(0,$E66-$F66-$J66) | I66: TCG | J66: 1 | K66: 0.69 | L66: =IF(AND($H66>0,ISNUMBER($K66)),$H66*$K66,0) | Q66: 1 | S66: =IF(AND(J66<>"",SUM(M66:R66)=0),J66,"") | AA66: Creature | AB66: Zombie Knight | AC66: Multi | AD66: 2 | AE66: Core Set 2020 | AF66: Drain Payoff | AG66: Whenever another creature you control enters, each opponent loses 1 life | AJ66: Ordered 2026-09-02: TCGplayer $0.39 NM from NostalgiAtog
A67: Cruel Celebrant | B67: =IF(AND(F67<>0,E67=F67),"In Hand",IF(AND(E67<>0,E67<F67,SUM(M67:R67)=0,SUM(T67:Y67)>0),"Extra-Sub",IF(AND(E67=0,E67<F67,SUM(M67:R67)=0,SUM(T67:Y67)>0),"Bench-Sub",IF(AND(E67=0,F67>0),"Bench",IF(E67<F67,"Extra",IF(AND(J67="",E67>F67),"To Buy",IF(SUM(J67,F67)<E67,"To Buy",IF(AND(SUM(J67,F67)>=E67,J67<>""),"Ordered",IF(AND(E67=0,F67=0,D67="B3"),"B3 Option",IF(AND(E67=0,F67=0),"Remove","To Buy")))))))))) | D67: B2 | E67: =SUM(M67:S67) | F67: =SUM(T67:Z67) | G67: =IF((F67-E67)>=0,F67-E67,0) | H67: =MAX(0,$E67-$F67-$J67) | I67: TCG | J67: 1 | K67: 1.68 | L67: =IF(AND($H67>0,ISNUMBER($K67)),$H67*$K67,0) | Q67: 1 | S67: =IF(AND(J67<>"",SUM(M67:R67)=0),J67,"") | AA67: Creature | AB67: Vampire | AC67: Multi | AD67: 2 | AE67: War of the Spark | AF67: Drain Payoff | AG67: Whenever it or another creature/planeswalker you control dies, each opponent loses 1 life and you gain 1 life | AJ67: Ordered 2026-09-02: TCGplayer $0.56 LP from The Next Level Games
A68: Cultivate | B68: =IF(AND(F68<>0,E68=F68),"In Hand",IF(AND(E68<>0,E68<F68,SUM(M68:R68)=0,SUM(T68:Y68)>0),"Extra-Sub",IF(AND(E68=0,E68<F68,SUM(M68:R68)=0,SUM(T68:Y68)>0),"Bench-Sub",IF(AND(E68=0,F68>0),"Bench",IF(E68<F68,"Extra",IF(AND(J68="",E68>F68),"To Buy",IF(SUM(J68,F68)<E68,"To Buy",IF(AND(SUM(J68,F68)>=E68,J68<>""),"Ordered",IF(AND(E68=0,F68=0,D68="B3"),"B3 Option",IF(AND(E68=0,F68=0),"Remove","To Buy")))))))))) | D68: B2 | E68: =SUM(M68:S68) | F68: =SUM(T68:Z68) | G68: =IF((F68-E68)>=0,F68-E68,0) | H68: =MAX(0,$E68-$F68-$J68) | I68: TCG | J68: 1 | K68: 0.36 | L68: =IF(AND($H68>0,ISNUMBER($K68)),$H68*$K68,0) | N68: 1 | S68: =IF(AND(J68<>"",SUM(M68:R68)=0),J68,"") | AA68: Sorcery | AC68: G | AD68: 3 | AE68: Magic 2011 | AF68: Ramp | AG68: Searches for two basic lands; puts one onto the battlefield tapped, one to hand | AJ68: Ordered 2026-09-02: TCGplayer $0.39 NM from NostalgiAtog
A69: Danitha Capashen, Paragon | B69: =IF(AND(F69<>0,E69=F69),"In Hand",IF(AND(E69<>0,E69<F69,SUM(M69:R69)=0,SUM(T69:Y69)>0),"Extra-Sub",IF(AND(E69=0,E69<F69,SUM(M69:R69)=0,SUM(T69:Y69)>0),"Bench-Sub",IF(AND(E69=0,F69>0),"Bench",IF(E69<F69,"Extra",IF(AND(J69="",E69>F69),"To Buy",IF(SUM(J69,F69)<E69,"To Buy",IF(AND(SUM(J69,F69)>=E69,J69<>""),"Ordered",IF(AND(E69=0,F69=0,D69="B3"),"B3 Option",IF(AND(E69=0,F69=0),"Remove","To Buy")))))))))) | D69: B2 | E69: =SUM(M69:S69) | F69: =SUM(T69:Z69) | G69: =IF((F69-E69)>=0,F69-E69,0) | H69: =MAX(0,$E69-$F69-$J69) | I69: TCG | J69: 1 | L69: =IF(AND($H69>0,ISNUMBER($K69)),$H69*$K69,0) | S69: =IF(AND(J69<>"",SUM(M69:R69)=0),J69,"") | AA69: ? | AB69: Human Knight | AC69: C | AD69: 3 | AE69: Dominaria | AF69: Cost Reducer | AG69: Reduces your Aura and Equipment spells by {1} | AH69: First strike, vigilance, lifelink body | AJ69: arrives -> Bench (slot was upgraded)
A70: Day of Judgment | B70: =IF(AND(F70<>0,E70=F70),"In Hand",IF(AND(E70<>0,E70<F70,SUM(M70:R70)=0,SUM(T70:Y70)>0),"Extra-Sub",IF(AND(E70=0,E70<F70,SUM(M70:R70)=0,SUM(T70:Y70)>0),"Bench-Sub",IF(AND(E70=0,F70>0),"Bench",IF(E70<F70,"Extra",IF(AND(J70="",E70>F70),"To Buy",IF(SUM(J70,F70)<E70,"To Buy",IF(AND(SUM(J70,F70)>=E70,J70<>""),"Ordered",IF(AND(E70=0,F70=0,D70="B3"),"B3 Option",IF(AND(E70=0,F70=0),"Remove","To Buy")))))))))) | D70: B3 | E70: =SUM(M70:S70) | F70: =SUM(T70:Z70) | G70: =IF((F70-E70)>=0,F70-E70,0) | H70: =MAX(0,$E70-$F70-$J70) | I70: TCG | J70: 1 | K70: 1.09 | L70: =IF(AND($H70>0,ISNUMBER($K70)),$H70*$K70,0) | Q70: 1 | S70: =IF(AND(J70<>"",SUM(M70:R70)=0),J70,"") | AA70: Sorcery | AC70: W | AD70: 4 | AE70: Zendikar | AF70: Board Wipe | AG70: Destroys all creatures | AJ70: D5 Tuned add bought in place of Timid Shieldbearer (2026-09-02); Ordered 2026-09-02: TCGplayer $1.09 LP from The Next Level Games
A71: Deadly Dispute | B71: =IF(AND(F71<>0,E71=F71),"In Hand",IF(AND(E71<>0,E71<F71,SUM(M71:R71)=0,SUM(T71:Y71)>0),"Extra-Sub",IF(AND(E71=0,E71<F71,SUM(M71:R71)=0,SUM(T71:Y71)>0),"Bench-Sub",IF(AND(E71=0,F71>0),"Bench",IF(E71<F71,"Extra",IF(AND(J71="",E71>F71),"To Buy",IF(SUM(J71,F71)<E71,"To Buy",IF(AND(SUM(J71,F71)>=E71,J71<>""),"Ordered",IF(AND(E71=0,F71=0,D71="B3"),"B3 Option",IF(AND(E71=0,F71=0),"Remove","To Buy")))))))))) | D71: B2 | E71: =SUM(M71:S71) | F71: =SUM(T71:Z71) | G71: =IF((F71-E71)>=0,F71-E71,0) | H71: =MAX(0,$E71-$F71-$J71) | I71: TCG | J71: 1 | K71: 0.26 | L71: =IF(AND($H71>0,ISNUMBER($K71)),$H71*$K71,0) | Q71: 1 | S71: =IF(AND(J71<>"",SUM(M71:R71)=0),J71,"") | AA71: Instant | AC71: B | AD71: 2 | AE71: Adventures in the Forgotten Realms | AF71: Sacrifice Outlet | AG71: Sacrifice an artifact or creature to draw two cards and make a Treasure token | AJ71: Ordered 2026-09-02: TCGplayer $0.37 NM from NostalgiAtog
A72: Deepglow Skate | B72: =IF(AND(F72<>0,E72=F72),"In Hand",IF(AND(E72<>0,E72<F72,SUM(M72:R72)=0,SUM(T72:Y72)>0),"Extra-Sub",IF(AND(E72=0,E72<F72,SUM(M72:R72)=0,SUM(T72:Y72)>0),"Bench-Sub",IF(AND(E72=0,F72>0),"Bench",IF(E72<F72,"Extra",IF(AND(J72="",E72>F72),"To Buy",IF(SUM(J72,F72)<E72,"To Buy",IF(AND(SUM(J72,F72)>=E72,J72<>""),"Ordered",IF(AND(E72=0,F72=0,D72="B3"),"B3 Option",IF(AND(E72=0,F72=0),"Remove","To Buy")))))))))) | D72: B2 | E72: =SUM(M72:S72) | F72: =SUM(T72:Z72) | G72: =IF((F72-E72)>=0,F72-E72,0) | H72: =MAX(0,$E72-$F72-$J72) | I72: TCG | J72: 1 | K72: 0.28 | L72: =IF(AND($H72>0,ISNUMBER($K72)),$H72*$K72,0) | O72: 1 | S72: =IF(AND(J72<>"",SUM(M72:R72)=0),J72,"") | AA72: Creature | AB72: Fish | AC72: U | AD72: 5 | AE72: Commander 2016 | AF72: Proliferate | AG72: Doubles each kind of counter on any number of target permanents when it enters | AJ72: Ordered 2026-09-02: TCGplayer $0.30 NM from NostalgiAtog
A73: Dreadhorde Invasion | B73: =IF(AND(F73<>0,E73=F73),"In Hand",IF(AND(E73<>0,E73<F73,SUM(M73:R73)=0,SUM(T73:Y73)>0),"Extra-Sub",IF(AND(E73=0,E73<F73,SUM(M73:R73)=0,SUM(T73:Y73)>0),"Bench-Sub",IF(AND(E73=0,F73>0),"Bench",IF(E73<F73,"Extra",IF(AND(J73="",E73>F73),"To Buy",IF(SUM(J73,F73)<E73,"To Buy",IF(AND(SUM(J73,F73)>=E73,J73<>""),"Ordered",IF(AND(E73=0,F73=0,D73="B3"),"B3 Option",IF(AND(E73=0,F73=0),"Remove","To Buy")))))))))) | D73: B2 | E73: =SUM(M73:S73) | F73: =SUM(T73:Z73) | G73: =IF((F73-E73)>=0,F73-E73,0) | H73: =MAX(0,$E73-$F73-$J73) | I73: TCG | J73: 1 | K73: 1.02 | L73: =IF(AND($H73>0,ISNUMBER($K73)),$H73*$K73,0) | Q73: 1 | S73: =IF(AND(J73<>"",SUM(M73:R73)=0),J73,"") | AA73: Enchantment | AC73: B | AD73: 2 | AE73: War of the Spark | AF73: Token Producer | AG73: Each upkeep, lose 1 life and put a counter on (or create) a Zombie Army token | AH73: Big Zombie tokens gain lifelink when attacking | AJ73: Ordered 2026-09-02: TCGplayer $0.46 NM from NostalgiAtog
A74: Elspeth, Sun's Nemesis | B74: =IF(AND(F74<>0,E74=F74),"In Hand",IF(AND(E74<>0,E74<F74,SUM(M74:R74)=0,SUM(T74:Y74)>0),"Extra-Sub",IF(AND(E74=0,E74<F74,SUM(M74:R74)=0,SUM(T74:Y74)>0),"Bench-Sub",IF(AND(E74=0,F74>0),"Bench",IF(E74<F74,"Extra",IF(AND(J74="",E74>F74),"To Buy",IF(SUM(J74,F74)<E74,"To Buy",IF(AND(SUM(J74,F74)>=E74,J74<>""),"Ordered",IF(AND(E74=0,F74=0,D74="B3"),"B3 Option",IF(AND(E74=0,F74=0),"Remove","To Buy")))))))))) | D74: B3 | E74: =SUM(M74:S74) | F74: =SUM(T74:Z74) | G74: =IF((F74-E74)>=0,F74-E74,0) | H74: =MAX(0,$E74-$F74-$J74) | I74: TCG | J74: 1 | K74: 1 | L74: =IF(AND($H74>0,ISNUMBER($K74)),$H74*$K74,0) | Q74: 1 | S74: =IF(AND(J74<>"",SUM(M74:R74)=0),J74,"") | AA74: Legendary Planeswalker | AB74: Elspeth | AC74: W | AD74: 4 | AE74: Theros Beyond Death | AF74: Token Producer | AG74: -1: Up to two creatures get +2/+1 until end of turn | AH74: -2: Create two 1/1 Human Soldier tokens | AI74: Escape from the graveyard by exiling four cards | AJ74: D5 Tuned add bought in place of Curious Farm Animals (2026-09-02); Ordered 2026-09-02: TCGplayer $1.00 NM from The Next Level Games
A75: Empty the Warrens | B75: =IF(AND(F75<>0,E75=F75),"In Hand",IF(AND(E75<>0,E75<F75,SUM(M75:R75)=0,SUM(T75:Y75)>0),"Extra-Sub",IF(AND(E75=0,E75<F75,SUM(M75:R75)=0,SUM(T75:Y75)>0),"Bench-Sub",IF(AND(E75=0,F75>0),"Bench",IF(E75<F75,"Extra",IF(AND(J75="",E75>F75),"To Buy",IF(SUM(J75,F75)<E75,"To Buy",IF(AND(SUM(J75,F75)>=E75,J75<>""),"Ordered",IF(AND(E75=0,F75=0,D75="B3"),"B3 Option",IF(AND(E75=0,F75=0),"Remove","To Buy")))))))))) | D75: B2 | E75: =SUM(M75:S75) | F75: =SUM(T75:Z75) | G75: =IF((F75-E75)>=0,F75-E75,0) | H75: =MAX(0,$E75-$F75-$J75) | I75: TCG | J75: 1 | K75: 0.15 | L75: =IF(AND($H75>0,ISNUMBER($K75)),$H75*$K75,0) | R75: 1 | S75: =IF(AND(J75<>"",SUM(M75:R75)=0),J75,"") | AA75: Sorcery | AC75: R | AD75: 4 | AE75: Time Spiral | AF75: Token Producer | AG75: Creates two 1/1 Goblin tokens | AH75: Copied for each spell already cast this turn (Storm) | AJ75: Ordered 2026-09-02: TCGplayer $0.20 LP from The WKGR Online
A76: Everflowing Chalice | B76: =IF(AND(F76<>0,E76=F76),"In Hand",IF(AND(E76<>0,E76<F76,SUM(M76:R76)=0,SUM(T76:Y76)>0),"Extra-Sub",IF(AND(E76=0,E76<F76,SUM(M76:R76)=0,SUM(T76:Y76)>0),"Bench-Sub",IF(AND(E76=0,F76>0),"Bench",IF(E76<F76,"Extra",IF(AND(J76="",E76>F76),"To Buy",IF(SUM(J76,F76)<E76,"To Buy",IF(AND(SUM(J76,F76)>=E76,J76<>""),"Ordered",IF(AND(E76=0,F76=0,D76="B3"),"B3 Option",IF(AND(E76=0,F76=0),"Remove","To Buy")))))))))) | D76: B2 | E76: =SUM(M76:S76) | F76: =SUM(T76:Z76) | G76: =IF((F76-E76)>=0,F76-E76,0) | H76: =MAX(0,$E76-$F76-$J76) | I76: TCG | J76: 1 | K76: 0.29 | L76: =IF(AND($H76>0,ISNUMBER($K76)),$H76*$K76,0) | O76: 1 | S76: =IF(AND(J76<>"",SUM(M76:R76)=0),J76,"") | AA76: Artifact | AC76: C | AD76: 0 | AE76: Worldwake | AF76: Mana Rock | AG76: Taps for {C} equal to charge counters on it | AH76: Enters with more counters if kicked for extra {2} payments | AJ76: Ordered 2026-09-02: TCGplayer $0.31 NM from NostalgiAtog
A77: Evolution Sage | B77: =IF(AND(F77<>0,E77=F77),"In Hand",IF(AND(E77<>0,E77<F77,SUM(M77:R77)=0,SUM(T77:Y77)>0),"Extra-Sub",IF(AND(E77=0,E77<F77,SUM(M77:R77)=0,SUM(T77:Y77)>0),"Bench-Sub",IF(AND(E77=0,F77>0),"Bench",IF(E77<F77,"Extra",IF(AND(J77="",E77>F77),"To Buy",IF(SUM(J77,F77)<E77,"To Buy",IF(AND(SUM(J77,F77)>=E77,J77<>""),"Ordered",IF(AND(E77=0,F77=0,D77="B3"),"B3 Option",IF(AND(E77=0,F77=0),"Remove","To Buy")))))))))) | D77: B2 | E77: =SUM(M77:S77) | F77: =SUM(T77:Z77) | G77: =IF((F77-E77)>=0,F77-E77,0) | H77: =MAX(0,$E77-$F77-$J77) | I77: TCG | J77: 1 | K77: 2.33 | L77: =IF(AND($H77>0,ISNUMBER($K77)),$H77*$K77,0) | O77: 1 | S77: =IF(AND(J77<>"",SUM(M77:R77)=0),J77,"") | AA77: Creature | AB77: Elf Druid | AC77: G | AD77: 3 | AE77: War of the Spark | AF77: Proliferate | AG77: Proliferate whenever a land you control enters | AJ77: Tuned add
A78: Faithless Looting | B78: =IF(AND(F78<>0,E78=F78),"In Hand",IF(AND(E78<>0,E78<F78,SUM(M78:R78)=0,SUM(T78:Y78)>0),"Extra-Sub",IF(AND(E78=0,E78<F78,SUM(M78:R78)=0,SUM(T78:Y78)>0),"Bench-Sub",IF(AND(E78=0,F78>0),"Bench",IF(E78<F78,"Extra",IF(AND(J78="",E78>F78),"To Buy",IF(SUM(J78,F78)<E78,"To Buy",IF(AND(SUM(J78,F78)>=E78,J78<>""),"Ordered",IF(AND(E78=0,F78=0,D78="B3"),"B3 Option",IF(AND(E78=0,F78=0),"Remove","To Buy")))))))))) | D78: B2 | E78: =SUM(M78:S78) | F78: =SUM(T78:Z78) | G78: =IF((F78-E78)>=0,F78-E78,0) | H78: =MAX(0,$E78-$F78-$J78) | I78: TCG | J78: 1 | K78: 0.39 | L78: =IF(AND($H78>0,ISNUMBER($K78)),$H78*$K78,0) | M78: 1 | R78: 1 | S78: =IF(AND(J78<>"",SUM(M78:R78)=0),J78,"") | T78: 1 | AA78: Sorcery | AC78: R | AD78: 1 | AE78: Dark Ascension | AF78: Discard/Looting | AG78: Draw two cards, then discard two cards | AH78: Flashback lets you cast it again from graveyard | AJ78: own 1 of 2 needed; Ordered 2026-09-02: TCGplayer $0.34 NM from NostalgiAtog
A79: Fateful Absence | B79: =IF(AND(F79<>0,E79=F79),"In Hand",IF(AND(E79<>0,E79<F79,SUM(M79:R79)=0,SUM(T79:Y79)>0),"Extra-Sub",IF(AND(E79=0,E79<F79,SUM(M79:R79)=0,SUM(T79:Y79)>0),"Bench-Sub",IF(AND(E79=0,F79>0),"Bench",IF(E79<F79,"Extra",IF(AND(J79="",E79>F79),"To Buy",IF(SUM(J79,F79)<E79,"To Buy",IF(AND(SUM(J79,F79)>=E79,J79<>""),"Ordered",IF(AND(E79=0,F79=0,D79="B3"),"B3 Option",IF(AND(E79=0,F79=0),"Remove","To Buy")))))))))) | D79: B2 | E79: =SUM(M79:S79) | F79: =SUM(T79:Z79) | G79: =IF((F79-E79)>=0,F79-E79,0) | H79: =MAX(0,$E79-$F79-$J79) | I79: TCG | J79: 1 | K79: 0.41 | L79: =IF(AND($H79>0,ISNUMBER($K79)),$H79*$K79,0) | P79: 1 | S79: =IF(AND(J79<>"",SUM(M79:R79)=0),J79,"") | AA79: Instant | AC79: W | AD79: 2 | AE79: Innistrad: Midnight Hunt | AF79: Removal | AG79: Destroys target creature or planeswalker | AH79: Its controller creates a Clue token
A80: Forgotten Ancient | B80: =IF(AND(F80<>0,E80=F80),"In Hand",IF(AND(E80<>0,E80<F80,SUM(M80:R80)=0,SUM(T80:Y80)>0),"Extra-Sub",IF(AND(E80=0,E80<F80,SUM(M80:R80)=0,SUM(T80:Y80)>0),"Bench-Sub",IF(AND(E80=0,F80>0),"Bench",IF(E80<F80,"Extra",IF(AND(J80="",E80>F80),"To Buy",IF(SUM(J80,F80)<E80,"To Buy",IF(AND(SUM(J80,F80)>=E80,J80<>""),"Ordered",IF(AND(E80=0,F80=0,D80="B3"),"B3 Option",IF(AND(E80=0,F80=0),"Remove","To Buy")))))))))) | D80: B2 | E80: =SUM(M80:S80) | F80: =SUM(T80:Z80) | G80: =IF((F80-E80)>=0,F80-E80,0) | H80: =MAX(0,$E80-$F80-$J80) | I80: TCG | J80: 1 | K80: 0.33 | L80: =IF(AND($H80>0,ISNUMBER($K80)),$H80*$K80,0) | O80: 1 | S80: =IF(AND(J80<>"",SUM(M80:R80)=0),J80,"") | AA80: Creature | AB80: Elemental | AC80: G | AD80: 4 | AE80: Scourge | AF80: Counters Payoff | AG80: Gets a +1/+1 counter whenever any player casts a spell | AH80: Moves any number of +1/+1 counters to other creatures each upkeep | AJ80: Tuned add
A81: Frontline Medic | B81: =IF(AND(F81<>0,E81=F81),"In Hand",IF(AND(E81<>0,E81<F81,SUM(M81:R81)=0,SUM(T81:Y81)>0),"Extra-Sub",IF(AND(E81=0,E81<F81,SUM(M81:R81)=0,SUM(T81:Y81)>0),"Bench-Sub",IF(AND(E81=0,F81>0),"Bench",IF(E81<F81,"Extra",IF(AND(J81="",E81>F81),"To Buy",IF(SUM(J81,F81)<E81,"To Buy",IF(AND(SUM(J81,F81)>=E81,J81<>""),"Ordered",IF(AND(E81=0,F81=0,D81="B3"),"B3 Option",IF(AND(E81=0,F81=0),"Remove","To Buy")))))))))) | D81: B2 | E81: =SUM(M81:S81) | F81: =SUM(T81:Z81) | G81: =IF((F81-E81)>=0,F81-E81,0) | H81: =MAX(0,$E81-$F81-$J81) | I81: TCG | J81: 1 | K81: 0.2 | L81: =IF(AND($H81>0,ISNUMBER($K81)),$H81*$K81,0) | S81: =IF(AND(J81<>"",SUM(M81:R81)=0),J81,"") | AA81: Creature | AB81: Human Cleric | AC81: W | AD81: 3 | AE81: Gatecrash | AF81: Protection | AG81: Battalion: your creatures gain indestructible when 3+ attack | AH81: Sacrifice: counter a spell with {X} in its cost unless they pay {3} | AJ81: D4 target removed 2026-09-02 (bench sub Grazing Gladehart in place)
A82: Generous Gift | B82: =IF(AND(F82<>0,E82=F82),"In Hand",IF(AND(E82<>0,E82<F82,SUM(M82:R82)=0,SUM(T82:Y82)>0),"Extra-Sub",IF(AND(E82=0,E82<F82,SUM(M82:R82)=0,SUM(T82:Y82)>0),"Bench-Sub",IF(AND(E82=0,F82>0),"Bench",IF(E82<F82,"Extra",IF(AND(J82="",E82>F82),"To Buy",IF(SUM(J82,F82)<E82,"To Buy",IF(AND(SUM(J82,F82)>=E82,J82<>""),"Ordered",IF(AND(E82=0,F82=0,D82="B3"),"B3 Option",IF(AND(E82=0,F82=0),"Remove","To Buy")))))))))) | D82: B2 | E82: =SUM(M82:S82) | F82: =SUM(T82:Z82) | G82: =IF((F82-E82)>=0,F82-E82,0) | H82: =MAX(0,$E82-$F82-$J82) | I82: TCG | J82: 1 | K82: 0.85 | L82: =IF(AND($H82>0,ISNUMBER($K82)),$H82*$K82,0) | M82: 1 | S82: =IF(AND(J82<>"",SUM(M82:R82)=0),J82,"") | AA82: Instant | AC82: W | AD82: 3 | AE82: Modern Horizons | AF82: Removal | AG82: Destroys target permanent | AH82: Its controller creates a 3/3 Elephant token | AJ82: Ordered 2026-09-02: TCGplayer $1.31 LP from The WKGR Online
A83: Genesis Chamber | B83: =IF(AND(F83<>0,E83=F83),"In Hand",IF(AND(E83<>0,E83<F83,SUM(M83:R83)=0,SUM(T83:Y83)>0),"Extra-Sub",IF(AND(E83=0,E83<F83,SUM(M83:R83)=0,SUM(T83:Y83)>0),"Bench-Sub",IF(AND(E83=0,F83>0),"Bench",IF(E83<F83,"Extra",IF(AND(J83="",E83>F83),"To Buy",IF(SUM(J83,F83)<E83,"To Buy",IF(AND(SUM(J83,F83)>=E83,J83<>""),"Ordered",IF(AND(E83=0,F83=0,D83="B3"),"B3 Option",IF(AND(E83=0,F83=0),"Remove","To Buy")))))))))) | D83: B2 | E83: =SUM(M83:S83) | F83: =SUM(T83:Z83) | G83: =IF((F83-E83)>=0,F83-E83,0) | H83: =MAX(0,$E83-$F83-$J83) | I83: TCG | J83: 1 | K83: 3.47 | L83: =IF(AND($H83>0,ISNUMBER($K83)),$H83*$K83,0) | R83: 1 | S83: =IF(AND(J83<>"",SUM(M83:R83)=0),J83,"") | AA83: Artifact | AC83: C | AD83: 2 | AE83: Darksteel | AF83: Token Producer | AG83: Whenever a nontoken creature enters, its controller creates a 1/1 Myr token (while this is untapped) | AJ83: Ordered 2026-09-02: TCGplayer $3.26 LP from Harb's Cards
A84: Glacial Fortress | B84: =IF(AND(F84<>0,E84=F84),"In Hand",IF(AND(E84<>0,E84<F84,SUM(M84:R84)=0,SUM(T84:Y84)>0),"Extra-Sub",IF(AND(E84=0,E84<F84,SUM(M84:R84)=0,SUM(T84:Y84)>0),"Bench-Sub",IF(AND(E84=0,F84>0),"Bench",IF(E84<F84,"Extra",IF(AND(J84="",E84>F84),"To Buy",IF(SUM(J84,F84)<E84,"To Buy",IF(AND(SUM(J84,F84)>=E84,J84<>""),"Ordered",IF(AND(E84=0,F84=0,D84="B3"),"B3 Option",IF(AND(E84=0,F84=0),"Remove","To Buy")))))))))) | D84: B2 | E84: =SUM(M84:S84) | F84: =SUM(T84:Z84) | G84: =IF((F84-E84)>=0,F84-E84,0) | H84: =MAX(0,$E84-$F84-$J84) | I84: TCG | J84: 1 | K84: 0.32 | L84: =IF(AND($H84>0,ISNUMBER($K84)),$H84*$K84,0) | N84: 1 | S84: =IF(AND(J84<>"",SUM(M84:R84)=0),J84,"") | AA84: Land | AC84: L | AD84: 0 | AE84: Magic 2010 | AF84: Land | AG84: Taps for {W} or {U} | AH84: Enters untapped if you control a Plains or Island | AJ84: Ordered 2026-09-02: TCGplayer $0.24 NM from The WKGR Online
A85: Goblin Bombardment | B85: =IF(AND(F85<>0,E85=F85),"In Hand",IF(AND(E85<>0,E85<F85,SUM(M85:R85)=0,SUM(T85:Y85)>0),"Extra-Sub",IF(AND(E85=0,E85<F85,SUM(M85:R85)=0,SUM(T85:Y85)>0),"Bench-Sub",IF(AND(E85=0,F85>0),"Bench",IF(E85<F85,"Extra",IF(AND(J85="",E85>F85),"To Buy",IF(SUM(J85,F85)<E85,"To Buy",IF(AND(SUM(J85,F85)>=E85,J85<>""),"Ordered",IF(AND(E85=0,F85=0,D85="B3"),"B3 Option",IF(AND(E85=0,F85=0),"Remove","To Buy")))))))))) | D85: B2 | E85: =SUM(M85:S85) | F85: =SUM(T85:Z85) | G85: =IF((F85-E85)>=0,F85-E85,0) | H85: =MAX(0,$E85-$F85-$J85) | I85: TCG | J85: 1 | K85: 2.85 | L85: =IF(AND($H85>0,ISNUMBER($K85)),$H85*$K85,0) | R85: 1 | S85: =IF(AND(J85<>"",SUM(M85:R85)=0),J85,"") | AA85: Enchantment | AC85: R | AD85: 2 | AE85: Tempest | AF85: Sacrifice Outlet | AG85: Sacrifice a creature: deals 1 damage to any target | AJ85: Ordered 2026-09-02: TCGplayer $2.79 LP from The WKGR Online
A86: Goblin Instigator | B86: =IF(AND(F86<>0,E86=F86),"In Hand",IF(AND(E86<>0,E86<F86,SUM(M86:R86)=0,SUM(T86:Y86)>0),"Extra-Sub",IF(AND(E86=0,E86<F86,SUM(M86:R86)=0,SUM(T86:Y86)>0),"Bench-Sub",IF(AND(E86=0,F86>0),"Bench",IF(E86<F86,"Extra",IF(AND(J86="",E86>F86),"To Buy",IF(SUM(J86,F86)<E86,"To Buy",IF(AND(SUM(J86,F86)>=E86,J86<>""),"Ordered",IF(AND(E86=0,F86=0,D86="B3"),"B3 Option",IF(AND(E86=0,F86=0),"Remove","To Buy")))))))))) | D86: B2 | E86: =SUM(M86:S86) | F86: =SUM(T86:Z86) | G86: =IF((F86-E86)>=0,F86-E86,0) | H86: =MAX(0,$E86-$F86-$J86) | I86: TCG | J86: 1 | K86: 0.39 | L86: =IF(AND($H86>0,ISNUMBER($K86)),$H86*$K86,0) | R86: 1 | S86: =IF(AND(J86<>"",SUM(M86:R86)=0),J86,"") | AA86: Creature | AB86: Goblin Rogue | AC86: R | AD86: 2 | AE86: Core Set 2019 | AF86: Token Producer | AG86: Creates a 1/1 Goblin token when it enters | AJ86: Ordered 2026-09-02: TCGplayer $0.30 LP from The WKGR Online
A87: Goblin Matron | B87: =IF(AND(F87<>0,E87=F87),"In Hand",IF(AND(E87<>0,E87<F87,SUM(M87:R87)=0,SUM(T87:Y87)>0),"Extra-Sub",IF(AND(E87=0,E87<F87,SUM(M87:R87)=0,SUM(T87:Y87)>0),"Bench-Sub",IF(AND(E87=0,F87>0),"Bench",IF(E87<F87,"Extra",IF(AND(J87="",E87>F87),"To Buy",IF(SUM(J87,F87)<E87,"To Buy",IF(AND(SUM(J87,F87)>=E87,J87<>""),"Ordered",IF(AND(E87=0,F87=0,D87="B3"),"B3 Option",IF(AND(E87=0,F87=0),"Remove","To Buy")))))))))) | D87: B2 | E87: =SUM(M87:S87) | F87: =SUM(T87:Z87) | G87: =IF((F87-E87)>=0,F87-E87,0) | H87: =MAX(0,$E87-$F87-$J87) | I87: TCG | J87: 1 | K87: 0.32 | L87: =IF(AND($H87>0,ISNUMBER($K87)),$H87*$K87,0) | R87: 1 | S87: =IF(AND(J87<>"",SUM(M87:R87)=0),J87,"") | AA87: Creature | AB87: Goblin | AC87: R | AD87: 3 | AE87: Portal Second Age | AF87: Tutor | AG87: Searches library for a Goblin card to hand when it enters | AJ87: Ordered 2026-09-02: TCGplayer $0.31 LP from The WKGR Online
A88: Goblin Ringleader | B88: =IF(AND(F88<>0,E88=F88),"In Hand",IF(AND(E88<>0,E88<F88,SUM(M88:R88)=0,SUM(T88:Y88)>0),"Extra-Sub",IF(AND(E88=0,E88<F88,SUM(M88:R88)=0,SUM(T88:Y88)>0),"Bench-Sub",IF(AND(E88=0,F88>0),"Bench",IF(E88<F88,"Extra",IF(AND(J88="",E88>F88),"To Buy",IF(SUM(J88,F88)<E88,"To Buy",IF(AND(SUM(J88,F88)>=E88,J88<>""),"Ordered",IF(AND(E88=0,F88=0,D88="B3"),"B3 Option",IF(AND(E88=0,F88=0),"Remove","To Buy")))))))))) | D88: B2 | E88: =SUM(M88:S88) | F88: =SUM(T88:Z88) | G88: =IF((F88-E88)>=0,F88-E88,0) | H88: =MAX(0,$E88-$F88-$J88) | I88: TCG | J88: 1 | K88: 0.99 | L88: =IF(AND($H88>0,ISNUMBER($K88)),$H88*$K88,0) | R88: 1 | S88: =IF(AND(J88<>"",SUM(M88:R88)=0),J88,"") | AA88: Creature | AB88: Goblin | AC88: R | AD88: 4 | AE88: Apocalypse | AF88: Tutor | AG88: Reveals top four cards, puts all Goblin cards found into hand | AH88: Can attack immediately when it enters (haste) | AJ88: Ordered 2026-09-02: TCGplayer $0.52 LP from The WKGR Online
A89: Goblin Warchief | B89: =IF(AND(F89<>0,E89=F89),"In Hand",IF(AND(E89<>0,E89<F89,SUM(M89:R89)=0,SUM(T89:Y89)>0),"Extra-Sub",IF(AND(E89=0,E89<F89,SUM(M89:R89)=0,SUM(T89:Y89)>0),"Bench-Sub",IF(AND(E89=0,F89>0),"Bench",IF(E89<F89,"Extra",IF(AND(J89="",E89>F89),"To Buy",IF(SUM(J89,F89)<E89,"To Buy",IF(AND(SUM(J89,F89)>=E89,J89<>""),"Ordered",IF(AND(E89=0,F89=0,D89="B3"),"B3 Option",IF(AND(E89=0,F89=0),"Remove","To Buy")))))))))) | D89: B2 | E89: =SUM(M89:S89) | F89: =SUM(T89:Z89) | G89: =IF((F89-E89)>=0,F89-E89,0) | H89: =MAX(0,$E89-$F89-$J89) | I89: TCG | J89: 1 | K89: 1.14 | L89: =IF(AND($H89>0,ISNUMBER($K89)),$H89*$K89,0) | R89: 1 | S89: =IF(AND(J89<>"",SUM(M89:R89)=0),J89,"") | AA89: Creature | AB89: Goblin Warrior | AC89: R | AD89: 3 | AE89: Scourge | AF89: Cost Reducer | AG89: Goblin spells you cast cost {1} less | AH89: Goblins you control have haste | AJ89: Ordered 2026-09-02: TCGplayer $1.27 LP from The WKGR Online
A90: Golgari Signet | B90: =IF(AND(F90<>0,E90=F90),"In Hand",IF(AND(E90<>0,E90<F90,SUM(M90:R90)=0,SUM(T90:Y90)>0),"Extra-Sub",IF(AND(E90=0,E90<F90,SUM(M90:R90)=0,SUM(T90:Y90)>0),"Bench-Sub",IF(AND(E90=0,F90>0),"Bench",IF(E90<F90,"Extra",IF(AND(J90="",E90>F90),"To Buy",IF(SUM(J90,F90)<E90,"To Buy",IF(AND(SUM(J90,F90)>=E90,J90<>""),"Ordered",IF(AND(E90=0,F90=0,D90="B3"),"B3 Option",IF(AND(E90=0,F90=0),"Remove","To Buy")))))))))) | D90: B2 | E90: =SUM(M90:S90) | F90: =SUM(T90:Z90) | G90: =IF((F90-E90)>=0,F90-E90,0) | H90: =MAX(0,$E90-$F90-$J90) | I90: TCG | J90: 1 | K90: 0.32 | L90: =IF(AND($H90>0,ISNUMBER($K90)),$H90*$K90,0) | P90: 1 | S90: =IF(AND(J90<>"",SUM(M90:R90)=0),J90,"") | AA90: Artifact | AC90: Multi | AD90: 2 | AE90: Ravnica: City of Guilds | AF90: Mana Rock | AG90: {1}, tap: add {B}{G} | AJ90: Ordered 2026-09-02: TCGplayer $0.33 LP from The WKGR Online
A91: Grateful Apparition | B91: =IF(AND(F91<>0,E91=F91),"In Hand",IF(AND(E91<>0,E91<F91,SUM(M91:R91)=0,SUM(T91:Y91)>0),"Extra-Sub",IF(AND(E91=0,E91<F91,SUM(M91:R91)=0,SUM(T91:Y91)>0),"Bench-Sub",IF(AND(E91=0,F91>0),"Bench",IF(E91<F91,"Extra",IF(AND(J91="",E91>F91),"To Buy",IF(SUM(J91,F91)<E91,"To Buy",IF(AND(SUM(J91,F91)>=E91,J91<>""),"Ordered",IF(AND(E91=0,F91=0,D91="B3"),"B3 Option",IF(AND(E91=0,F91=0),"Remove","To Buy")))))))))) | D91: B2 | E91: =SUM(M91:S91) | F91: =SUM(T91:Z91) | G91: =IF((F91-E91)>=0,F91-E91,0) | H91: =MAX(0,$E91-$F91-$J91) | I91: TCG | J91: 1 | K91: 0.19 | L91: =IF(AND($H91>0,ISNUMBER($K91)),$H91*$K91,0) | O91: 1 | S91: =IF(AND(J91<>"",SUM(M91:R91)=0),J91,"") | AA91: Creature | AB91: Spirit | AC91: W | AD91: 2 | AE91: War of the Spark | AF91: Proliferate | AG91: Proliferates whenever it deals combat damage to a player or planeswalker | AH91: Flying body | AJ91: Ordered 2026-09-02: TCGplayer $0.23 LP from The WKGR Online
A92: Hidden Stockpile | B92: =IF(AND(F92<>0,E92=F92),"In Hand",IF(AND(E92<>0,E92<F92,SUM(M92:R92)=0,SUM(T92:Y92)>0),"Extra-Sub",IF(AND(E92=0,E92<F92,SUM(M92:R92)=0,SUM(T92:Y92)>0),"Bench-Sub",IF(AND(E92=0,F92>0),"Bench",IF(E92<F92,"Extra",IF(AND(J92="",E92>F92),"To Buy",IF(SUM(J92,F92)<E92,"To Buy",IF(AND(SUM(J92,F92)>=E92,J92<>""),"Ordered",IF(AND(E92=0,F92=0,D92="B3"),"B3 Option",IF(AND(E92=0,F92=0),"Remove","To Buy")))))))))) | D92: B2 | E92: =SUM(M92:S92) | F92: =SUM(T92:Z92) | G92: =IF((F92-E92)>=0,F92-E92,0) | H92: =MAX(0,$E92-$F92-$J92) | I92: TCG | J92: 1 | K92: 0.32 | L92: =IF(AND($H92>0,ISNUMBER($K92)),$H92*$K92,0) | Q92: 1 | S92: =IF(AND(J92<>"",SUM(M92:R92)=0),J92,"") | AA92: Enchantment | AC92: Multi | AD92: 2 | AE92: Aether Revolt | AF92: Token Producer | AG92: End step: creates a 1/1 Servo token if a permanent left the battlefield under your control this turn | AH92: {1}, sacrifice a creature: Scry 1 | AJ92: Ordered 2026-09-02: TCGplayer $0.19 LP from The WKGR Online
A93: Hordeling Outburst | B93: =IF(AND(F93<>0,E93=F93),"In Hand",IF(AND(E93<>0,E93<F93,SUM(M93:R93)=0,SUM(T93:Y93)>0),"Extra-Sub",IF(AND(E93=0,E93<F93,SUM(M93:R93)=0,SUM(T93:Y93)>0),"Bench-Sub",IF(AND(E93=0,F93>0),"Bench",IF(E93<F93,"Extra",IF(AND(J93="",E93>F93),"To Buy",IF(SUM(J93,F93)<E93,"To Buy",IF(AND(SUM(J93,F93)>=E93,J93<>""),"Ordered",IF(AND(E93=0,F93=0,D93="B3"),"B3 Option",IF(AND(E93=0,F93=0),"Remove","To Buy")))))))))) | D93: B2 | E93: =SUM(M93:S93) | F93: =SUM(T93:Z93) | G93: =IF((F93-E93)>=0,F93-E93,0) | H93: =MAX(0,$E93-$F93-$J93) | I93: TCG | J93: 1 | K93: 0.45 | L93: =IF(AND($H93>0,ISNUMBER($K93)),$H93*$K93,0) | R93: 1 | S93: =IF(AND(J93<>"",SUM(M93:R93)=0),J93,"") | AA93: Sorcery | AC93: R | AD93: 3 | AE93: Khans of Tarkir | AF93: Token Producer | AG93: Creates three 1/1 Goblin tokens | AJ93: Ordered 2026-09-02: TCGplayer $0.34 LP from The WKGR Online
A94: Huatli, the Sun's Heart | B94: =IF(AND(F94<>0,E94=F94),"In Hand",IF(AND(E94<>0,E94<F94,SUM(M94:R94)=0,SUM(T94:Y94)>0),"Extra-Sub",IF(AND(E94=0,E94<F94,SUM(M94:R94)=0,SUM(T94:Y94)>0),"Bench-Sub",IF(AND(E94=0,F94>0),"Bench",IF(E94<F94,"Extra",IF(AND(J94="",E94>F94),"To Buy",IF(SUM(J94,F94)<E94,"To Buy",IF(AND(SUM(J94,F94)>=E94,J94<>""),"Ordered",IF(AND(E94=0,F94=0,D94="B3"),"B3 Option",IF(AND(E94=0,F94=0),"Remove","To Buy")))))))))) | D94: B2 | E94: =SUM(M94:S94) | F94: =SUM(T94:Z94) | G94: =IF((F94-E94)>=0,F94-E94,0) | H94: =MAX(0,$E94-$F94-$J94) | I94: TCG | J94: 1 | K94: 0.46 | L94: =IF(AND($H94>0,ISNUMBER($K94)),$H94*$K94,0) | P94: 1 | S94: =IF(AND(J94<>"",SUM(M94:R94)=0),J94,"") | AA94: Legendary Planeswalker | AB94: Huatli | AC94: Multi | AD94: 3 | AE94: War of the Spark | AF94: Toughness Payoff | AG94: Your creatures assign combat damage equal to toughness | AH94: -3: gain life equal to the greatest toughness among your creatures
A95: Ichor Wellspring | B95: =IF(AND(F95<>0,E95=F95),"In Hand",IF(AND(E95<>0,E95<F95,SUM(M95:R95)=0,SUM(T95:Y95)>0),"Extra-Sub",IF(AND(E95=0,E95<F95,SUM(M95:R95)=0,SUM(T95:Y95)>0),"Bench-Sub",IF(AND(E95=0,F95>0),"Bench",IF(E95<F95,"Extra",IF(AND(J95="",E95>F95),"To Buy",IF(SUM(J95,F95)<E95,"To Buy",IF(AND(SUM(J95,F95)>=E95,J95<>""),"Ordered",IF(AND(E95=0,F95=0,D95="B3"),"B3 Option",IF(AND(E95=0,F95=0),"Remove","To Buy")))))))))) | D95: B2 | E95: =SUM(M95:S95) | F95: =SUM(T95:Z95) | G95: =IF((F95-E95)>=0,F95-E95,0) | H95: =MAX(0,$E95-$F95-$J95) | I95: TCG | J95: 1 | K95: 1.45 | L95: =IF(AND($H95>0,ISNUMBER($K95)),$H95*$K95,0) | Q95: 1 | S95: =IF(AND(J95<>"",SUM(M95:R95)=0),J95,"") | AA95: Artifact | AC95: C | AD95: 2 | AE95: Mirrodin Besieged | AF95: Card Draw | AG95: Draws a card when it enters or is put into a graveyard from the battlefield
A96: Impact Tremors | B96: =IF(AND(F96<>0,E96=F96),"In Hand",IF(AND(E96<>0,E96<F96,SUM(M96:R96)=0,SUM(T96:Y96)>0),"Extra-Sub",IF(AND(E96=0,E96<F96,SUM(M96:R96)=0,SUM(T96:Y96)>0),"Bench-Sub",IF(AND(E96=0,F96>0),"Bench",IF(E96<F96,"Extra",IF(AND(J96="",E96>F96),"To Buy",IF(SUM(J96,F96)<E96,"To Buy",IF(AND(SUM(J96,F96)>=E96,J96<>""),"Ordered",IF(AND(E96=0,F96=0,D96="B3"),"B3 Option",IF(AND(E96=0,F96=0),"Remove","To Buy")))))))))) | D96: B2 | E96: =SUM(M96:S96) | F96: =SUM(T96:Z96) | G96: =IF((F96-E96)>=0,F96-E96,0) | H96: =MAX(0,$E96-$F96-$J96) | I96: TCG | J96: 1 | K96: 2.1 | L96: =IF(AND($H96>0,ISNUMBER($K96)),$H96*$K96,0) | R96: 1 | S96: =IF(AND(J96<>"",SUM(M96:R96)=0),J96,"") | AA96: Enchantment | AC96: R | AD96: 2 | AE96: Dragons of Tarkir | AF96: Burn | AG96: Whenever a creature you control enters, deals 1 damage to each opponent | AJ96: Ordered 2026-09-02: TCGplayer $2.10 NMF from NostalgiAtog
A97: Inexorable Tide | B97: =IF(AND(F97<>0,E97=F97),"In Hand",IF(AND(E97<>0,E97<F97,SUM(M97:R97)=0,SUM(T97:Y97)>0),"Extra-Sub",IF(AND(E97=0,E97<F97,SUM(M97:R97)=0,SUM(T97:Y97)>0),"Bench-Sub",IF(AND(E97=0,F97>0),"Bench",IF(E97<F97,"Extra",IF(AND(J97="",E97>F97),"To Buy",IF(SUM(J97,F97)<E97,"To Buy",IF(AND(SUM(J97,F97)>=E97,J97<>""),"Ordered",IF(AND(E97=0,F97=0,D97="B3"),"B3 Option",IF(AND(E97=0,F97=0),"Remove","To Buy")))))))))) | D97: B2 | E97: =SUM(M97:S97) | F97: =SUM(T97:Z97) | G97: =IF((F97-E97)>=0,F97-E97,0) | H97: =MAX(0,$E97-$F97-$J97) | I97: TCG | J97: 1 | K97: 3.66 | L97: =IF(AND($H97>0,ISNUMBER($K97)),$H97*$K97,0) | O97: 1 | S97: =IF(AND(J97<>"",SUM(M97:R97)=0),J97,"") | AA97: Enchantment | AC97: U | AD97: 5 | AE97: Scars of Mirrodin | AF97: Proliferate | AG97: Whenever you cast a spell, proliferate | AJ97: Tuned add; Ordered 2026-09-02: TCGplayer $3.33 LP from The WKGR Online
A98: Inspiring Call | B98: =IF(AND(F98<>0,E98=F98),"In Hand",IF(AND(E98<>0,E98<F98,SUM(M98:R98)=0,SUM(T98:Y98)>0),"Extra-Sub",IF(AND(E98=0,E98<F98,SUM(M98:R98)=0,SUM(T98:Y98)>0),"Bench-Sub",IF(AND(E98=0,F98>0),"Bench",IF(E98<F98,"Extra",IF(AND(J98="",E98>F98),"To Buy",IF(SUM(J98,F98)<E98,"To Buy",IF(AND(SUM(J98,F98)>=E98,J98<>""),"Ordered",IF(AND(E98=0,F98=0,D98="B3"),"B3 Option",IF(AND(E98=0,F98=0),"Remove","To Buy")))))))))) | D98: B2 | E98: =SUM(M98:S98) | F98: =SUM(T98:Z98) | G98: =IF((F98-E98)>=0,F98-E98,0) | H98: =MAX(0,$E98-$F98-$J98) | I98: TCG | J98: 1 | K98: 0.42 | L98: =IF(AND($H98>0,ISNUMBER($K98)),$H98*$K98,0) | P98: 1 | S98: =IF(AND(J98<>"",SUM(M98:R98)=0),J98,"") | AA98: Instant | AC98: G | AD98: 3 | AE98: Dragons of Tarkir | AF98: Protection | AG98: Draws a card for each creature you control with a +1/+1 counter | AH98: Those creatures gain indestructible until end of turn | AJ98: Ordered 2026-09-02: TCGplayer $0.28 LP from The WKGR Online
A99: Jaddi Offshoot | B99: =IF(AND(F99<>0,E99=F99),"In Hand",IF(AND(E99<>0,E99<F99,SUM(M99:R99)=0,SUM(T99:Y99)>0),"Extra-Sub",IF(AND(E99=0,E99<F99,SUM(M99:R99)=0,SUM(T99:Y99)>0),"Bench-Sub",IF(AND(E99=0,F99>0),"Bench",IF(E99<F99,"Extra",IF(AND(J99="",E99>F99),"To Buy",IF(SUM(J99,F99)<E99,"To Buy",IF(AND(SUM(J99,F99)>=E99,J99<>""),"Ordered",IF(AND(E99=0,F99=0,D99="B3"),"B3 Option",IF(AND(E99=0,F99=0),"Remove","To Buy")))))))))) | D99: B2 | E99: =SUM(M99:S99) | F99: =SUM(T99:Z99) | G99: =IF((F99-E99)>=0,F99-E99,0) | H99: =MAX(0,$E99-$F99-$J99) | I99: TCG | J99: 1 | K99: 0.24 | L99: =IF(AND($H99>0,ISNUMBER($K99)),$H99*$K99,0) | P99: 1 | S99: =IF(AND(J99<>"",SUM(M99:R99)=0),J99,"") | AA99: Creature | AB99: Plant | AC99: G | AD99: 1 | AE99: Battle for Zendikar | AF99: Lifegain | AG99: Gain 1 life whenever a land you control enters | AH99: Defender body
A100: Keeper of the Accord | B100: =IF(AND(F100<>0,E100=F100),"In Hand",IF(AND(E100<>0,E100<F100,SUM(M100:R100)=0,SUM(T100:Y100)>0),"Extra-Sub",IF(AND(E100=0,E100<F100,SUM(M100:R100)=0,SUM(T100:Y100)>0),"Bench-Sub",IF(AND(E100=0,F100>0),"Bench",IF(E100<F100,"Extra",IF(AND(J100="",E100>F100),"To Buy",IF(SUM(J100,F100)<E100,"To Buy",IF(AND(SUM(J100,F100)>=E100,J100<>""),"Ordered",IF(AND(E100=0,F100=0,D100="B3"),"B3 Option",IF(AND(E100=0,F100=0),"Remove","To Buy")))))))))) | D100: B2 | E100: =SUM(M100:S100) | F100: =SUM(T100:Z100) | G100: =IF((F100-E100)>=0,F100-E100,0) | H100: =MAX(0,$E100-$F100-$J100) | I100: TCG | J100: 1 | K100: 0.57 | L100: =IF(AND($H100>0,ISNUMBER($K100)),$H100*$K100,0) | M100: 1 | S100: =IF(AND(J100<>"",SUM(M100:R100)=0),J100,"") | AA100: Creature | AB100: Human Soldier | AC100: W | AD100: 4 | AE100: Commander Legends | AF100: Value Engine | AG100: Each opponent's end step: if they have more creatures, create a 1/1 Soldier token | AH100: Each opponent's end step: if they have more lands, may search for a Plains onto the battlefield tapped | AJ100: Ordered 2026-09-02: TCGplayer $0.99 LP from The WKGR Online
...

Sheet Upgrades (D5-D6)
A1: Deck | B1: Action | D1: Card | E1: Qty | F1: Status | G1: $ Each | H1: $ To Buy | I1: Type | J1: Color | K1: MV | L1: Notes
A2: D5 | B2: ADD | D2: Day of Judgment | E2: 1 | F2: In TCGPlayer Cart | G2: 0.88 | H2: =IF(OR($F2="To Buy",$F2="In TCGPlayer Cart"),$E2*$G2,0) | I2: Sorcery | J2: W | L2: Tuned add for D5
A3: D5 | B3: ADD | D3: Elspeth, Sun's Nemesis | E3: 1 | F3: In TCGPlayer Cart | G3: 0.78 | H3: =IF(OR($F3="To Buy",$F3="In TCGPlayer Cart"),$E3*$G3,0) | I3: Legendary Planeswalker | J3: W | L3: Tuned add for D5
A4: Card | B4: ADD | C4: My To Buy List | D4: Bracket | E4: Qty | F4: To Buy | G4: 10.17 | H4: =IF(OR($F4="To Buy",$F4="In TCGPlayer Cart"),$E4*$G4,0) | I4: Legendary Creature | J4: BW | L4: Tuned add for D5 | targeted on Master 2026-09-02
A5: D5 | B5: ADD | D5: Mentor of the Meek | E5: 1 | F5: To Buy | G5: 4.95 | H5: =IF(OR($F5="To Buy",$F5="In TCGPlayer Cart"),$E5*$G5,0) | I5: Creature | J5: W | L5: Tuned add for D5 | targeted on Master 2026-09-02
A6: D5 | B6: ADD | D6: Night's Whisper | E6: 1 | F6: To Buy | G6: 5.42 | H6: =IF(OR($F6="To Buy",$F6="In TCGPlayer Cart"),$E6*$G6,0) | I6: Sorcery | J6: B | K6: 2 | L6: Tuned add for D5 | targeted on Master 2026-09-02
A7: D5 | B7: ADD | D7: Ossification | E7: 1 | F7: In TCGPlayer Cart | G7: 0.34 | H7: =IF(OR($F7="To Buy",$F7="In TCGPlayer Cart"),$E7*$G7,0) | I7: Enchantment | J7: W | L7: Tuned add for D5
A8: D5 | B8: ADD | D8: Requiem Angel | E8: 1 | F8: In Wake Forest Cart | G8: 0.84 | H8: =IF(OR($F8="To Buy",$F8="In TCGPlayer Cart"),$E8*$G8,0) | I8: Creature | J8: W | L8: Tuned add for D5
A9: D5 | B9: ADD | D9: Skullclamp | E9: 1 | F9: To Buy (con list) | G9: 5.89 | H9: =IF(OR($F9="To Buy",$F9="In TCGPlayer Cart"),$E9*$G9,0) | I9: Artifact | J9: C | K9: 1 | L9: Tuned add for D5 | targeted on Master 2026-09-02
A10: D5 | B10: ADD | D10: Teysa Karlov | E10: 1 | F10: To Buy | G10: 2.67 | H10: =IF(OR($F10="To Buy",$F10="In TCGPlayer Cart"),$E10*$G10,0) | I10: Legendary Creature | J10: BW | L10: Tuned add for D5 | targeted on Master 2026-09-02
A11: D5 | B11: CUT | D11: Costly Plunder | E11: 1 | F11: -> Bench | G11: 0.24 | I11: Instant | J11: B | K11: 2 | L11: Comes out at Tuned; move to Bench box
A12: D5 | B12: CUT | D12: Curious Farm Animals | E12: 1 | F12: -> Bench (cut 2026-09-02) | I12: Creature | J12: W | K12: 1 | L12: Comes out at Tuned; move to Bench box
A13: D5 | B13: CUT | D13: Explorer's Scope | E13: 1 | F13: -> Bench | I13: Artifact | J13: C | K13: 1 | L13: Comes out at Tuned; move to Bench box
A14: D5 | B14: CUT | D14: Goldvein Pick | E14: 1 | F14: -> Bench | I14: Artifact | J14: C | K14: 2 | L14: Comes out at Tuned; move to Bench box
A15: D5 | B15: CUT | D15: Haystack | E15: 1 | F15: -> Bench | I15: Artifact | J15: W | K15: 2 | L15: Comes out at Tuned; move to Bench box
A16: D5 | B16: CUT | D16: Inspiring Overseer | E16: 1 | F16: -> Bench | G16: 0.28 | I16: Creature | J16: W | K16: 3 | L16: Comes out at Tuned; move to Bench box
A17: D5 | B17: CUT | D17: Suture Priest | E17: 1 | F17: -> Bench (not bought; Skullclamp pending) | G17: 4.67 | I17: Creature | J17: W | K17: 2 | L17: Comes out at Tuned; move to Bench box
A18: D5 | B18: CUT | D18: B3 | E18: 1 | F18: -> Bench (cut 2026-09-02) | I18: Creature | J18: W | K18: 2 | L18: Comes out at Tuned; move to Bench box
A19: D5 | B19: CUT | D19: Wild Pack Squad | E19: 1 | F19: -> Bench | I19: Creature | J19: W | K19: 3 | L19: Comes out at Tuned; move to Bench box
A20: D6 | B20: ADD | D20: Conspicuous Snoop | E20: 1 | F20: To Buy | G20: 4.85 | H20: =IF(OR($F20="To Buy",$F20="In TCGPlayer Cart"),$E20*$G20,0) | I20: Creature | J20: R | L20: Tuned add for D6 | targeted on Master 2026-09-02
A21: D6 | B21: ADD | D21: Fervor | E21: 1 | F21: To Buy | G21: 4.21 | H21: =IF(OR($F21="To Buy",$F21="In TCGPlayer Cart"),$E21*$G21,0) | I21: Enchantment | J21: R | L21: Tuned add for D6 | targeted on Master 2026-09-02
A22: D6 | B22: ADD | D22: Goblin Chieftain | E22: 1 | F22: To Buy | G22: 5.94 | H22: =IF(OR($F22="To Buy",$F22="In TCGPlayer Cart"),$E22*$G22,0) | I22: Creature | J22: R | L22: Tuned add for D6 | targeted on Master 2026-09-02
A23: D6 | B23: ADD | D23: Goblin Rabblemaster | E23: 1 | F23: In Raleigh Cart | G23: 0.66 | H23: =IF(OR($F23="To Buy",$F23="In TCGPlayer Cart"),$E23*$G23,0) | I23: Creature | J23: R | L23: Tuned add for D6
A24: D6 | B24: ADD | D24: Goblin Trashmaster | E24: 1 | F24: To Buy | G24: 7.78 | H24: =IF(OR($F24="To Buy",$F24="In TCGPlayer Cart"),$E24*$G24,0) | I24: Creature | J24: R | L24: Tuned add for D6 | targeted on Master 2026-09-02
A25: D6 | B25: ADD | D25: Molten Echoes | E25: 1 | F25: To Buy | G25: 9.51 | H25: =IF(OR($F25="To Buy",$F25="In TCGPlayer Cart"),$E25*$G25,0) | I25: Enchantment | J25: R | L25: Tuned add for D6 | targeted on Master 2026-09-02
A26: D6 | B26: ADD | D26: Purphoros's Intervention | E26: 1 | F26: In Raleigh Cart | G26: 0.28 | H26: =IF(OR($F26="To Buy",$F26="In TCGPlayer Cart"),$E26*$G26,0) | I26: Sorcery | J26: R | L26: Tuned add for D6
A27: D6 | B27: ADD | D27: Ruby Medallion | E27: 1 | F27: To Buy | G27: 14.81 | H27: =IF(OR($F27="To Buy",$F27="In TCGPlayer Cart"),$E27*$G27,0) | I27: Artifact | J27: C | L27: Tuned add for D6 | targeted on Master 2026-09-02
A28: D6 | B28: ADD | D28: Rundvelt Hordemaster | E28: 1 | F28: To Buy | G28: 4.87 | H28: =IF(OR($F28="To Buy",$F28="In TCGPlayer Cart"),$E28*$G28,0) | I28: Creature | J28: R | L28: Tuned add for D6 | targeted on Master 2026-09-02
A29: D6 | B29: ADD | D29: Shared Animosity | E29: 1 | F29: To Buy | G29: 4.47 | H29: =IF(OR($F29="To Buy",$F29="In TCGPlayer Cart"),$E29*$G29,0) | I29: Enchantment | J29: R | L29: Tuned add for D6 | targeted on Master 2026-09-02
A30: D6 | B30: CUT | D30: Burning Curiosity | E30: 1 | F30: -> Bench | I30: Sorcery | J30: R | K30: 3 | L30: Comes out at Tuned; move to Bench box
A31: D6 | B31: CUT | D31: Cinder Strike | E31: 1 | F31: -> Bench | I31: Sorcery | J31: R | K31: 1 | L31: Comes out at Tuned; move to Bench box
A32: D6 | B32: CUT | D32: Dwarven Mauler | E32: 1 | F32: -> Bench | I32: Creature | J32: R | K32: 1 | L32: Comes out at Tuned; move to Bench box
A33: D6 | B33: CUT | D33: Fire Diamond | E33: 1 | F33: -> Bench | G33: 0.36 | I33: Artifact | J33: R | K33: 2 | L33: Comes out at Tuned; move to Bench box
A34: D6 | B34: CUT | D34: Goblin Motivator | E34: 1 | F34: -> Bench | G34: 0.26 | I34: Creature | J34: R | K34: 1 | L34: Comes out at Tuned; move to Bench box
A35: D6 | B35: CUT | D35: Goblin Oriflamme | E35: 1 | F35: -> Bench | G35: 0.53 | I35: Enchantment | J35: R | K35: 2 | L35: Comes out at Tuned; move to Bench box
A36: D6 | B36: CUT | D36: Monastery Raid | E36: 1 | F36: -> Bench | I36: Sorcery | J36: R | K36: 3 | L36: Comes out at Tuned; move to Bench box
A37: D6 | B37: CUT | D37: Rummaging Goblin | E37: 1 | F37: -> Bench | G37: 0.2 | I37: Creature | J37: R | K37: 3 | L37: Comes out at Tuned; move to Bench box
A38: D6 | B38: CUT | D38: Tweeze | E38: 1 | F38: -> Bench | I38: Instant | J38: R | K38: 3 | L38: Comes out at Tuned; move to Bench box
A39: D6 | B39: CUT | D39: Voldaren Epicure | E39: 1 | F39: -> Bench | G39: 0.33 | I39: Creature | J39: R | K39: 1 | L39: Comes out at Tuned; move to Bench box
C51: 1
C103: 1
C128: 2
C175: 1
C177: 1
C206: 1
C213: 1
C217: 1
C233: 2
C238: 1
C276: 2
C306: 1
... C566: 2
A572: Enchanted River's Grasp | C572: 1
A573: Fearsome Goblin Pair | C573: 1
A574: Front Porch Sentries | C574: 1
A575: Getaway Barrel | C575: 1
A576: Mirkwood Nurturer | C576: 1
A577: Mirkwood Pathmaker | C577: 1
A578: Moment of Glory | C578: 1
A579: Old Fat Spider Can't See Me | C579: 1
A580: Ordinary Bear | C580: 1
A581: Rage into the Valley | C581: 1
A582: Stone by Sunlight | C582: 1
A583: Tidings of War | C583: 1

Sheet B3 Upgrades
A1: Deck | B1: B3 Add | C1: Status | D1: $ Each | E1: GC | F1: Color | G1: MV | H1: Type | I1: Replaces (-> Bench) | J1: Why It Makes B3
A2: D1 | B2: Inspiring Vantage | C2: To Buy | D2: 2.03 | F2: RW | G2: 0 | H2: Land | I2: Stone Quarry | J2: Enters untapped exactly when you need early plays - a strict upgrade over the tapped Quarry.
A3: D1 | B3: Anim Pakal, Thousandth Moon | C3: To Buy | D3: 4.21 | F3: RW | G3: 3 | H3: Legendary Creature | I3: Relic Retriever | J3: A widening Gnome army on every attack - a token stream Balefire Liege pumps, giving a second win angle beside Moonshaker Cavalry.
A4: D1 | B4: Sunbaked Canyon | C4: To Buy | D4: 4.58 | F4: RW | G4: 0 | H4: Land | I4: Fields of Strife | J4: Untapped R/W that cashes in for a card late - a mana base that never stumbles is the quietest B3 upgrade there is.
A5: D1 | B5: Farewell | C5: To Buy | D5: 6 | E5: GC | F5: W | G5: 6 | H5: Sorcery | I5: Ceaseless Conflict | J5: GAME CHANGER 2 of 2. The deck currently runs ZERO board wipes; modal exile-wipe answers your pod's token and enchantment engines and dodges all recursion.
A6: D2 | B6: Panharmonicon | C6: To Buy | D6: 6.92 | F6: C | G6: 4 | H6: Artifact | I6: Platypus-Bear | J6: Doubles every ETB trigger - each Roon blink, each Chulane replay now pays twice.
A7: D3 | B7: Nature's Lore | C7: To Buy | D7: 2.69 | F7: G | G7: 2 | H7: Sorcery | I7: Origin of Metalbending | J7: An untapped Forest at 2 mana - directly fixes the deck's biggest need: Atraxa reliably on turn 3-4.
A8: D3 | B8: Ichormoon Gauntlet | C8: To Buy | D8: 4.8 | F8: U | G8: 3 | H8: Artifact | I8: Rebellious Captives | J8: Proliferate on every noncreature spell (30 in the deck), plus planeswalker modes Atraxa's end step compounds.
A9: D3 | B9: Pir, Imaginative Rascal | C9: To Buy | D9: 5.32 | F9: G | G9: 3 | H9: Legendary Creature | I9: Stony Strength | J9: Every counter placed on your permanents gets +1 - quietly doubles proliferate output deck-wide.
A10: D4 | B10: Doran, the Siege Tower | C10: To Buy | D10: 8.48 | F10: WBG | G10: 3 | H10: Legendary Creature | I10: Meandering Towershell | J10: A second Betor effect in the 99 - every wall attacks and blocks with its toughness even when Betor is answered. Redundancy on the core mechanic is the #1 B3 fix.
A11: D5 | B11: Blood Artist | C11: To Buy | D11: 3.78 | F11: B | G11: 2 | H11: Creature | I11: Prideful Feastling | J11: The classic aristocrat: every creature death anywhere drains an opponent - turns board wipes (yours or theirs) into win attempts.
A12: D5 | B12: Pitiless Plunderer | C12: To Buy | D12: 4.21 | F12: B | G12: 4 | H12: Creature | I12: Zack Fair | J12: Every dying token pays you a Treasure - sacrifice loops go mana-positive.
A13: D5 | B13: Elenda, the Dusk Rose | C13: To Buy | D13: 5.75 | F13: BW | G13: 4 | H13: Legendary Creature | I13: Court Street Denizen | J13: Grows with every death and dies into a Vampire army - a token wincon that shrugs off board wipes.
A14: D6 | B14: Den of the Bugbear | C14: To Buy | D14: 1.91 | F14: R | G14: 0 | H14: Land | I14: Mountain | J14: Replaces 1 of 33 Mountains: a land that makes attacking Goblin tokens (more Purphoros triggers) when you flood - zero opportunity cost.
A15: D6 | B15: Idol of Oblivion | C15: To Buy | D15: 2.07 | F15: C | G15: 2 | H15: Artifact | I15: Gristle Glutton | J15: A guaranteed card every turn you made a token (i.e., every turn); cashes in for a 10/10 Eldrazi late.
A16: D6 | B16: Goblin Piledriver | C16: To Buy | D16: 2.56 | F16: R | G16: 2 | H16: Creature | I16: Ghor-Clan Wrecker | J16: Grows huge on every swarm attack and has protection from blue - real combat damage to back up the pings.
A17: D6 | B17: Pashalik Mons | C17: To Buy | D17: 3.9 | F17: R | G17: 3 | H17: Legendary Creature | I17: Bag of Holding | J17: Every dying Goblin pings a target - with Skirk Prospector and Goblin Bombardment your tokens deal damage twice.
... A22: D1 | B22: Fable of the Mirror-Breaker | C22: To Buy | D22: 6.23 | F22: R | G22: 3 | H22: Enchantment | I22: Primary Research | J22: Treasure ramp + repeatable looting that stocks the graveyard for Loremaster recursion; the flip side copies your best ETB creature every turn.
A23: D1 | B23: Smothering Tithe | C23: To Buy | D23: 61.67 | E23: GC | F23: W | G23: 4 | H23: Enchantment | I23: Millikin | J23: GAME CHANGER 1 of 2. Turns every opponent draw into a Treasure - jumps you 2-3 turns ahead on mana and funds double-spell turns. The single best B3 ramp engine in white.
A24: D2 | B24: Beast Whisperer | C24: To Buy | D24: 8.73 | F24: G | G24: 4 | H24: Creature | I24: Sun-Dappled Celebrant | J24: A card for every creature cast - alongside Chulane that's 2 cards + a land per creature.
A25: D2 | B25: Teleportation Circle | C25: To Buy | D25: 10.93 | F25: W | G25: 4 | H25: Enchantment | I25: Winnowing | J25: A free blink EVERY end step with no tap cost - blink-engine redundancy if Roon is answered.
A26: D2 | B26: Guardian Project | C26: To Buy | D26: 14.88 | F26: G | G26: 4 | H26: Enchantment | I26: Glamermite | J26: A second creature-based draw engine; engine redundancy is what separates a B3 deck from a B2 one.
A27: D2 | B27: Rhystic Study | C27: To Buy | D27: 70.58 | E27: GC | F27: U | G27: 3 | H27: Enchantment | I27: Shore Lurker | J27: GAME CHANGER 1 of 1, and THE Chulane staple - taxes all three opponents every single turn. The card-advantage backbone of a B3 Bant value deck.
A28: D3 | B28: Phyrexian Arena | C28: To Buy | D28: 4.65 | F28: B | G28: 3 | H28: Enchantment | I28: Mirrodin Avenged | J28: An extra card every upkeep - the raw, repeatable card advantage the current list lacks.
A29: D3 | B29: Night's Whisper | C29: To Buy | D29: 5.42 | F29: B | G29: 2 | H29: Sorcery | I29: Troll Negotiations | J29: Two cards for two mana; the life is paid back by Atraxa lifelink and Rhox Faithmender doubling.
A30: D3 | B30: Vorinclex, Monstrous Raider | C30: To Buy | D30: 55.18 | F30: G | G30: 6 | H30: Legendary Creature | I30: Nightmare Sower | J30: Marquee B3 payoff (NOT a Game Changer per Scryfall's official flag): doubles every counter you place and halves your opponents' - proliferate hits twice as hard while shutting down the pod's counter engines.
A31: D4 | B31: Guardian Project | C31: To Buy | D31: 14.88 | F31: G | G31: 4 | H31: Enchantment | I31: Crashing Drawbridge | J31: With 40+ creatures this draws on nearly every cast - converts the cheap wall curve into a card-advantage engine.
A32: D4 | B32: The Meathook Massacre | C32: To Buy | D32: 25.01 | F32: B | G32: 2 | H32: Legendary Enchantment | I32: Collective Effort | J32: Scalable wipe that drains for every death - clears the pod's token engines while stacking Betor lifegain triggers. Marquee removal and win engine in one card.
A33: D5 | B33: Brightclimb Pathway | C33: To Buy | D33: 4.74 | F33: BW | G33: 0 | H33: Land | I33: Scoured Barrens | J33: Untapped either side, your choice - cuts the tapped-land drag in a 2-color deck that should never stumble.
A34: D5 | B34: Ashnod's Altar | C34: To Buy | D34: 16.6 | F34: C | G34: 3 | H34: Artifact | I34: Dawn-Blessed Pennant | J34: Tokens become 2 mana each - with Procession and Plunderer it empties your whole hand in one turn.
A35: D5 | B35: Dictate of Erebos | C35: To Buy | D35: 19 | F35: B | G35: 5 | H35: Enchantment | I35: Chocobo Knights | J35: Flash edict engine: every token you sacrifice forces EACH opponent to sacrifice - repeatedly eats the pod's commanders and voltron threats.
A36: D5 | B36: Anointed Procession | C36: To Buy | D36: 59.34 | F36: W | G36: 4 | H36: Enchantment | I36: Aetheric Amplifier | J36: EVERY token doubled - Shadrix makes 4 fliers a combat, Lingering Souls makes 4, Spectral Procession 6. The defining B3 token payoff.
A37: D6 | B37: Underworld Breach | C37: To Buy | D37: 10.36 | E37: GC | F37: R | G37: 2 | H37: Enchantment | I37: Goblin Gathering | J37: GAME CHANGER 2 of 2: replays your token sorceries from the graveyard (Dragon Fodder, Krenko's Command, Empty the Warrens) for one extra mana each - on a Jeska's Will turn it converts the graveyard into 10+ Purphoros triggers at once.
A38: D6 | B38: Muxus, Goblin Grandee | C38: To Buy | D38: 12.87 | F38: R | G38: 6 | H38: Legendary Creature | I38: Boar-q-pine | J38: Dumps 3-4 Goblins into play at once - 6-8 Purphoros damage to EACH opponent plus a board out of nowhere.
A39: D6 | B39: Jeska's Will | C39: To Buy | D39: 40.09 | E39: GC | F39: R | G39: 3 | H39: Sorcery | I39: Combustion Technique | J39: GAME CHANGER 1 of 2: explosive mana AND a fresh grip in one card - powers out Purphoros plus a token spell in the same turn for lethal ping turns.

Sheet Read Me
A1: MtG Deck Master v2 - how this workbook works
A2: Built 2026-08-31. Prices are Scryfall/TCGplayer market USD as of that date. Replaces MtG Deck Master.xlsx (kept in the folder untouched).
A4: DECKS
A5: D1 = Quintorius, Loremaster (Quintorius)
A6: D2 = Chulane, Teller of Tales (Roon-Chulane)
A7: D3 = Atraxa, Praetors' Voice (Atraxa)
A8: D4 = Betor, Ancestor's Voice (Betor)
A9: D5 = Shadrix Silverquill (Shadrix)
A10: D6 = Purphoros, God of the Forge (Purphoros)
A12: SHEETS
A13: Master - every card in the six target v1 decks (600 cards; Tuned builds for D1-D4, v0/v1 builds for D5-D6), deduplicated by name with counts in the deck columns, PLUS the entire Bench (owned/inbound copies not assigned to any v1 slot). Qty = deck copies + bench copies.
A14: Upgrades (D5-D6) - the card swaps that take D5 and D6 from their v1 build to their Tuned build (cheap Max cards were already folded in per the <$1.50 rule). ADD rows are what goes in; CUT rows come out to the Bench.
... A31: Second-copy note: the deck columns count copies per deck, so a name used in several decks needs that many physical copies (see Qty vs Owned). Basics are priced at $0.10 nominal.

Sheet Temp Adds
A1: Temp Adds - bench cards to make D4 / D5 / D6 playable at 100 cards (rev. 2026-09-03 PM, after the Hobbit booster + Game Theory pickups)
A2: Box counts are as of your latest sheet (Game Theory pickups and the first TCG arrivals already in the boxes). Shared Animosity (on order) and the remaining TCGplayer orders are NOT assumed. NEW = from the Hobbit booster. Only physical bench copies (Master B-A) are used; nothing is pulled from the D1-D3 boxes. Each deck stays singleton and inside its color identity. MOVE = card already targeted for that deck, just not moved yet. ADD = temporary bench add (swap out when the TCG order lands). LAND = basic-land filler.
A4: Summary
A5: Deck | B5: Box now | C5: + Game Theory cards | D5: + Moves / adds (nonland) | E5: + Utility lands | F5: + Basics | G5: Total | H5: Lands after | I5: Nonland after
A6: D4 - Betor, Ancestor's Voice (W/B/G, toughness + counters) | B6: 70 | C6: 0 | D6: 18 | E6: 0 | F6: 12 | G6: 100 | H6: 47 | I6: 53
A7: D5 - Shadrix Silverquill (W/B, tokens + aristocrats) | B7: 67 | C7: 0 | D7: 18 | E7: 1 | F7: 14 | G7: 100 | H7: 53 | I7: 47
A8: D6 - Purphoros (mono-R goblins) | B8: 70 | C8: 0 | D8: 11 | E8: 1 | F8: 18 | G8: 100 | H8: 53 | I8: 47
A9: Reality check: the nonland bench pool still runs out before 100 (D4 88, D5 86, D6 82 without basics). Filling the rest with basics gets each deck to a legal 100 but lands run 47-53 of 100 - playable for a casual game, not tuned. The remaining TCG packages (D4 28 / D5 30 / D6 32 cards (D6 incl. Shared Animosity)) are the real fix; swap the LAND rows out first, then the ADD rows, NEW vanilla bodies (Ordinary Bear) first among those. D2 note: the box shows 101 - Hinterland Harbor arrived but its placeholder land (Simic Guildgate or Naya Panorama) is still in the box; pull one.
A11: D4 - Betor, Ancestor's Voice (W/B/G, toughness + counters)
A12: Start: 70 in box + 0 Game Theory card(s): (Painful Truths and the TCG arrivals are already in the box)
A13: Deck | B13: Step | C13: Card | D13: Copies | E13: Color ID | F13: Type | G13: MV | H13: Why it fits / note | I13: Running total
A14: D4 | B14: MOVE | C14: Spectacular Tactics | D14: 1 | E14: W | F14: Instant | G14: 2 | H14: Already a D4 target; +1/+1 counter or kill a 4-power creature | I14: 71
A15: D4 | B15: ADD | C15: Mirkwood Pathmaker | D15: 1 | E15: G | H15: NEW (Hobbit): P/T = lands you control - a toughness body Betor loves; stand-in for Tree of Perdition | I15: 72
A16: D4 | B16: ADD | C16: Moment of Glory | D16: 1 | E16: W | H16: NEW (Hobbit): +1/+1 counter, flashback puts a counter on every creature | I16: 73
A17: D4 | B17: ADD | C17: Wood Elves | D17: 1 | E17: G | F17: Creature | G17: 3 | H17: NEW: fetches a Forest onto the battlefield - ramp | I17: 74
A18: D4 | B18: ADD | C18: Stone by Sunlight | D18: 1 | E18: W | H18: NEW (Hobbit): kill a 4-power creature or make one indestructible | I18: 75
A19: D4 | B19: ADD | C19: Ordinary Bear | D19: 1 | E19: G | H19: NEW (Hobbit): vanilla body - last-in, first-out when the TCG order lands | I19: 76
A20: D4 | B20: ADD | C20: Blight Rot | D20: 1 | E20: B | F20: Instant | G20: 3 | H20: Cheap removal: four -1/-1 counters | I20: 77
A21: D4 | B21: ADD | C21: Origin of Metalbending | D21: 1 | E21: G | F21: Instant | G21: 2 | H21: Artifact/enchantment removal or +1/+1 counter + indestructible | I21: 78
A22: D4 | B22: ADD | C22: Midnight Tilling | D22: 1 | E22: G | F22: Instant | G22: 2 | H22: Instant-speed value: mill 4, return a permanent | I22: 79
A23: D4 | B23: ADD | C23: Dundoolin Weaver | D23: 1 | E23: G | F23: Creature | G23: 2 | H23: Recursion when you control 3+ creatures (2nd copy; D2 keeps its own) | I23: 80
A24: D4 | B24: ADD | C24: Lys Alana Dignitary | D24: 1 | E24: G | F24: Creature | G24: 2 | H24: Mana dork / ramp body | I24: 81
A25: D4 | B25: ADD | C25: Lys Alana Informant | D25: 1 | E25: G | F25: Creature | G25: 2 | H25: Cheap body, surveil on enter and on death | I25: 82
A26: D4 | B26: ADD | C26: Dawn's Light Archer | D26: 1 | E26: G | F26: Creature | G26: 3 | H26: Flash reach blocker, decent toughness | I26: 83
A27: D4 | B27: ADD | C27: Surly Farrier | D27: 1 | E27: G | F27: Creature | G27: 2 | H27: Repeatable +1/+1 pump (sorcery speed) | I27: 84
A28: D4 | B28: ADD | C28: Zendikar's Roil | D28: 1 | E28: G | F28: Enchantment | G28: 5 | H28: Landfall 2/2 tokens - board presence | I28: 85
A29: D4 | B29: ADD | C29: Kithkeeper | D29: 1 | E29: W | F29: Creature | G29: 7 | H29: Top-end token maker (2nd copy; 1st goes to D5) | I29: 86
A30: D4 | B30: ADD | C30: Ironsoul Enforcer | D30: 1 | E30: W | F30: Artifact Creature | G30: 5 | H30: Big body; returns artifacts when your commander attacks alone | I30: 87
A31: D4 | B31: ADD | C31: Venat, Heart of Hydaelyn | D31: 1 | E31: C | F31: Legendary Creature | G31: 3 | H31: Draws on legendary spells; late-game exile | I31: 88
... A34: D4 | B34: LAND | C34: Forest | D34: 4 | E34: G | F34: Basic Land | G34: 0 | H34: Basic filler | I34: 100
A36: D5 - Shadrix Silverquill (W/B, tokens + aristocrats)
A37: Start: 67 in box + 0 Game Theory card(s): (Pawn of Ulamog and Temple of Silence are already in the box)
A38: Deck | B38: Step | C38: Card | D38: Copies | E38: Color ID | F38: Type | G38: MV | H38: Why it fits / note | I38: Running total
A39: D5 | B39: MOVE | C39: Terror | D39: 1 | E39: B | F39: Instant | G39: 2 | H39: Already a D5 target; cheap removal | I39: 68
A40: D5 | B40: MOVE | C40: Pretending Poxbearers | D40: 1 | E40: BW | F40: Creature | G40: 2 | H40: Already a D5 target; dies -> 1/1 token | I40: 69
A41: D5 | B41: ADD | C41: Front Porch Sentries | D41: 1 | E41: B | H41: NEW (Hobbit): 2-drop that shrinks a blocker when it dies - aristocrats fodder | I41: 70
A42: D5 | B42: ADD | C42: Rage into the Valley | D42: 1 | E42: B | H42: NEW (Hobbit): draw a card + a growing Goblin Army token; stand-in for Night's Whisper | I42: 71
A43: D5 | B43: ADD | C43: Despark | D43: 1 | E43: BW | F43: Instant | G43: 2 | H43: NEW spare copy: exile a 4+ MV permanent (D4 keeps its own) | I43: 72
A44: D5 | B44: ADD | C44: Prideful Feastling | D44: 1 | E44: BW | F44: Creature | G44: 3 | H44: Changeling lifelink body | I44: 73
A45: D5 | B45: ADD | C45: Kithkeeper | D45: 1 | E45: W | F45: Creature | G45: 7 | H45: Makes X 1/1 Kithkin on enter - token fodder | I45: 74
A46: D5 | B46: ADD | C46: Lake-town Lookout | D46: 1 | E46: W | F46: Creature | G46: 1 | H46: 1-drop that loots and makes a token when it dies; stand-in for Ophiomancer | I46: 75
A47: D5 | B47: ADD | C47: Great Fierce Bee | D47: 1 | E47: B | F47: Creature | G47: 3 | H47: Flyer that scrys whenever creatures die | I47: 76
A48: D5 | B48: ADD | C48: Desmond Miles | D48: 1 | E48: B | F48: Legendary Creature | G48: 2 | H48: Cheap menace attacker | I48: 77
A49: D5 | B49: ADD | C49: Make Your Move | D49: 1 | E49: W | F49: Instant | G49: 3 | H49: Flexible removal (artifact, enchantment or 4-power creature) | I49: 78
A50: D5 | B50: ADD | C50: Destroy Evil | D50: 1 | E50: W | F50: Instant | G50: 2 | H50: Removal for big-toughness threats or an enchantment | I50: 79
A51: D5 | B51: ADD | C51: Spectacular Tactics | D51: 1 | E51: W | F51: Instant | G51: 2 | H51: Protection / removal (2nd bench copy; 1st is the D4 target) | I51: 80
A52: D5 | B52: ADD | C52: Hemlock Vial | D52: 1 | E52: B | F52: Artifact | G52: 2 | H52: Draw a card; sac for deathtouch | I52: 81
A53: D5 | B53: ADD | C53: Moonglove Extractor | D53: 1 | E53: B | F53: Creature | G53: 3 | H53: Card draw on attack | I53: 82
A54: D5 | B54: ADD | C54: Meanders Guide | D54: 1 | E54: W | F54: Creature | G54: 3 | H54: Attacker that recurs a small creature | I54: 83
... A59: D5 | B59: LAND | C59: Swamp | D59: 7 | E59: B | F59: Basic Land | G59: 0 | H59: Basic filler | I59: 100
A61: D6 - Purphoros (mono-R goblins)
A62: Start: 70 in box + 0 Game Theory card(s): (all 8 Game Theory cards are already in the box; Shared Animosity is on order from Wake Forest)
A63: Deck | B63: Step | C63: Card | D63: Copies | E63: Color ID | F63: Type | G63: MV | H63: Why it fits / note | I63: Running total
A64: D6 | B64: MOVE | C64: Raid Bombardment | D64: 1 | E64: R | F64: Enchantment | G64: 3 | H64: Already a D6 target; pings for each small attacker | I64: 71
A65: D6 | B65: MOVE | C65: Tempt with Vengeance | D65: 1 | E65: R | F65: Sorcery | G65: 1 | H65: Already a D6 target; X hasty 1/1s | I65: 72
A66: D6 | B66: ADD | C66: Tidings of War | D66: 1 | E66: R | H66: NEW (Hobbit): 1-mana Goblin Army token that grows; the Army IS a Goblin for your lords | I66: 73
A67: D6 | B67: ADD | C67: Getaway Barrel | D67: 1 | E67: R | H67: NEW (Hobbit): artifact that cheats a creature in when it dies - sac it to Goblin Trashmaster | I67: 74
A68: D6 | B68: ADD | C68: Endbringer | D68: 1 | E68: C | F68: Creature | G68: 6 | H68: Colorless utility: pinger, untaps each turn | I68: 75
A69: D6 | B69: ADD | C69: Ultima, Origin of Oblivion | D69: 1 | E69: C | F69: Legendary Creature | G69: 5 | H69: Colorless 5-mana flyer, disrupts lands | I69: 76
A70: D6 | B70: ADD | C70: Eldrazi Ravager | D70: 1 | E70: C | F70: Creature | G70: 6 | H70: Colorless 6-drop finisher (2nd of 2 copies) | I70: 77
A71: D6 | B71: ADD | C71: Weathered Sentinels | D71: 1 | E71: C | F71: Artifact Creature | G71: 3 | H71: Colorless artifact creature body (2nd copy; D4 keeps its own) | I71: 78
A72: D6 | B72: ADD | C72: Dwarven Mattock | D72: 1 | E72: C | F72: Artifact - Equipment | G72: 2 | H72: Equipment: +2/+2 and ward | I72: 79
A73: D6 | B73: ADD | C73: Perpetual Timepiece | D73: 1 | E73: C | F73: Artifact | G73: 2 | H73: Cheap artifact; mill / graveyard reset | I73: 80
A74: D6 | B74: ADD | C74: Explorer's Scope | D74: 1 | E74: C | F74: Artifact | G74: 1 | H74: Free lands off attacks (1 of 2 bench copies; D5 already holds a 3rd) | I74: 81
A75: D6 | B75: ADD | C75: Access Tunnel | D75: 1 | E75: C | F75: Land | G75: 0 | H75: Colorless utility land - makes a small goblin unblockable; counts as a land | I75: 82
A76: D6 | B76: LAND | C76: Mountain | D76: 18 | E76: R | F76: Basic Land | G76: 0 | H76: Basic filler | I76: 100
