Workbook

Sheet How to use
A1: MTG Deck Decision Matrix
A2: Six decks · 100 lineup slots each · eleven candidate builds per slot · every simulated column backed by its own Monte Carlo run.
A4: The column hierarchy
A5: Site ladder — as published | B5: Base → Tuned → Enhance → Max
A6: Simulation-improved (Monte Carlo) | B6: Tuned-2 → Enhance-2 → Max-2
A7: Fun-weighted engine v2.1 | B7: Fun Tuned → Fun Max
A8: Alternative commander | B8: Alt Tuned → Alt Max
A10: Site ladder — as published
A11: Base is the starting shell you already own. Tuned adds every required purchase. Enhance adds the site's cheap side-grade tier. Max is the site's curated Tier 3 ceiling. These are the catalog's own lists — Tuned is the only one of the four that was ever simulated in this exact form.
A13: Simulation-improved (Monte Carlo)
A14: Tuned-2, Enhance-2 and Max-2 are the improved sets of cards the Monte Carlo optimizer found: it measured where each build actually lost, proposed swaps, re-measured, and kept only what still held up on thousands of games the optimizer never saw. Enhance-2 and Max-2 were additionally re-simulated as assembled lists, because assembling a list from separate evidence is not the same as measuring that exact list.
A16: Fun-weighted engine v2.1
A17: The same six decks re-optimized after three engine corrections (toughness-as-damage creatures, planeswalker commanders, multicolour land parsing) and a scoring change: raw win rate was cut from 0.40 to 0.30 of the score and a fun/participation signal given 0.10. These builds are tuned for games you actually get to play in, not purely for winning.
A19: Alternative commander
A20: Decks 1, 3 and 5 only — Teneb, Hazel and Iroas, each measured on that deck's own 99 cards and then re-optimized around the new commander. Read the Summary tab's alternative-commander block before adopting one; the case is much stronger for some than for others.
A22: How to decide
A23: Work down a deck sheet. Each row is one lineup slot. Set FINAL PICK to the build whose card you want in that slot — the Final Card, its price and the reason it moved all resolve automatically. The Final List tab collects every choice into a flat table for the session updating the web app.
A25: A caution worth reading
A26: The engine is a model, not a rules engine. It cannot see proliferate, trigger doubling, devotion, or most commander-specific synergy text. Where that materially changes a recommendation, the Summary and Notes tabs say so explicitly rather than letting the number stand alone.

Sheet Summary
A1: Build metrics — what backs each column
A2: Every simulated column below reports the games behind it and whether its gain survived a holdout of seeds the optimizer never saw. Blank = a published list with no simulation of its own.
A3: DO NOT compare scores across engine generations. Tuned and Tuned-2 were measured on the v1 engine (three opponent archetypes, win rate weighted 0.40). Enhance-2 and Max-2 were re-verified on v1 as assembled lists. Fun and Alt columns ran on v2.1 (nine archetypes, win rate 0.30, fun 0.10, three combat fixes). v2.1 scores are systematically lower because the opponent field is harder — that is not the deck getting worse. Compare only within a generation.
A4: Deck | B4: Build | C4: Group | D4: Games | E4: Holdout games | F4: Score | G4: Win % | H4: Fun % | I4: Avg win turn | J4: Cmdr turn | K4: Screw % | L4: Interaction | M4: Verdict | N4: Swaps | O4: What this column is
A5: 1o · Ancestral Bulwark | B5: Base | C5: Site ladder — as published | O5: published
A6: 1o · Ancestral Bulwark | B6: Tuned | C6: Site ladder — as published | D6: 20000 | E6: 5000 | F6: 80.3 | G6: 0.4322 | I6: 11.855622 | J6: 5.1371183 | K6: 0.0552 | L6: 0.36832 | M6: confirmed | N6: 5 | O6: published + simulated (v1 engine)
A7: 1o · Ancestral Bulwark | B7: Enhance | C7: Site ladder — as published | O7: published
A8: 1o · Ancestral Bulwark | B8: Max | C8: Site ladder — as published | O8: published
A9: 1o · Ancestral Bulwark | B9: Tuned-2 | C9: Simulation-improved (Monte Carlo) | D9: 20000 | E9: 5000 | F9: 80.3 | G9: 0.4322 | I9: 11.855622 | J9: 5.1371183 | K9: 0.0552 | L9: 0.36832 | M9: confirmed | N9: 5 | O9: simulation-improved (v1 engine)
A10: 1o · Ancestral Bulwark | B10: Enhance-2 | C10: Simulation-improved (Monte Carlo) | D10: 13000 | E10: 5000 | F10: 77.9 | G10: 0.448 | I10: 11.791518 | J10: 5.2206641 | K10: 0.0572 | L10: 0.22744 | M10: no-change | N10: 0 | O10: simulation-improved, then independently re-verified as an assembled list
A11: 1o · Ancestral Bulwark | B11: Max-2 | C11: Simulation-improved (Monte Carlo) | D11: 16000 | E11: 5000 | F11: 77.7 | G11: 0.4466 | I11: 11.834304 | J11: 5.2291796 | K11: 0.0594 | L11: 0.24564 | M11: within-noise | N11: 2 | O11: simulation-improved, then independently re-verified as an assembled list
A12: 1o · Ancestral Bulwark | B12: Fun Tuned | C12: Fun-weighted engine v2.1 | D12: 20000 | E12: 5000 | F12: 85.8 | G12: 0.4728 | H12: 0.9994 | I12: 11.304569 | J12: 4.8862348 | K12: 0.0508 | L12: 0.4146 | M12: confirmed | N12: 4 | O12: fun-weighted engine v2.1 (9 opponent archetypes, fun blended into scoring, combat fixes)
A13: 1o · Ancestral Bulwark | B13: Fun Max | C13: Fun-weighted engine v2.1 | D13: 22000 | E13: 5000 | F13: 83.3 | G13: 0.4774 | H13: 0.9964 | I13: 11.410557 | J13: 5.271063 | K13: 0.1042 | L13: 0.43544 | M13: confirmed | N13: 10 | O13: fun-weighted engine v2.1 (9 opponent archetypes, fun blended into scoring, combat fixes)
A14: 1o · Ancestral Bulwark | B14: Alt Tuned | C14: Alternative commander | D14: 20000 | E14: 5000 | F14: 86.3 | G14: 0.4852 | H14: 0.999 | I14: 11.27906 | J14: 5.6097411 | K14: 0.0508 | L14: 0.40152 | M14: confirmed | N14: 4 | O14: alternative commander (Teneb, the Harvester) on the same 99, v2.1 engine
A15: 1o · Ancestral Bulwark | B15: Alt Max | C15: Alternative commander | D15: 24000 | E15: 5000 | F15: 84.6 | G15: 0.4746 | H15: 0.996 | I15: 11.340076 | J15: 5.9989243 | K15: 0.0844 | L15: 0.41532 | M15: confirmed | N15: 15 | O15: alternative commander (Teneb, the Harvester) on the same 99, v2.1 engine
A17: 2c · Proliferate Council | B17: Base | C17: Site ladder — as published | O17: published
A18: 2c · Proliferate Council | B18: Tuned | C18: Site ladder — as published | D18: 22000 | E18: 5000 | F18: 86.1 | G18: 0.505 | I18: 11.41505 | J18: 4.7921968 | K18: 0.0632 | L18: 0.37736 | M18: confirmed | N18: 10 | O18: published + simulated (v1 engine)
A19: 2c · Proliferate Council | B19: Enhance | C19: Site ladder — as published | O19: published
A20: 2c · Proliferate Council | B20: Max | C20: Site ladder — as published | O20: published
A21: 2c · Proliferate Council | B21: Tuned-2 | C21: Simulation-improved (Monte Carlo) | D21: 22000 | E21: 5000 | F21: 86.1 | G21: 0.505 | I21: 11.41505 | J21: 4.7921968 | K21: 0.0632 | L21: 0.37736 | M21: confirmed | N21: 10 | O21: simulation-improved (v1 engine)
A22: 2c · Proliferate Council | B22: Enhance-2 | C22: Simulation-improved (Monte Carlo) | D22: 20000 | E22: 5000 | F22: 84.6 | G22: 0.4816 | I22: 11.436462 | J22: 4.7976319 | K22: 0.0638 | L22: 0.38504 | M22: within-noise | N22: 5 | O22: simulation-improved, then independently re-verified as an assembled list
A23: 2c · Proliferate Council | B23: Max-2 | C23: Simulation-improved (Monte Carlo) | D23: 20000 | E23: 5000 | F23: 84.6 | G23: 0.4816 | I23: 11.436462 | J23: 4.7976319 | K23: 0.0638 | L23: 0.38504 | M23: within-noise | N23: 5 | O23: simulation-improved, then independently re-verified as an assembled list
A24: 2c · Proliferate Council | B24: Fun Tuned | C24: Fun-weighted engine v2.1 | D24: 20000 | E24: 5000 | F24: 75.3 | G24: 0.2934 | H24: 0.9991 | I24: 12.09816 | J24: 4.406838 | K24: 0.0436 | L24: 0.5392 | M24: confirmed | N24: 5 | O24: fun-weighted engine v2.1 (9 opponent archetypes, fun blended into scoring, combat fixes)
A25: 2c · Proliferate Council | B25: Fun Max | C25: Fun-weighted engine v2.1 | D25: 20000 | E25: 5000 | F25: 75.2 | G25: 0.3006 | H25: 0.9986 | I25: 12.220226 | J25: 4.3071169 | K25: 0.058 | L25: 0.56256 | M25: confirmed | N25: 5 | O25: fun-weighted engine v2.1 (9 opponent archetypes, fun blended into scoring, combat fixes)
A27: 3e · Golgari Land Engine | B27: Base | C27: Site ladder — as published | O27: published
A28: 3e · Golgari Land Engine | B28: Tuned | C28: Site ladder — as published | D28: 24000 | E28: 5000 | F28: 80.2 | G28: 0.4342 | I28: 12.062183 | J28: 4.7325629 | K28: 0.051 | L28: 0.3518 | M28: confirmed | N28: 13 | O28: published + simulated (v1 engine)
A29: 3e · Golgari Land Engine | B29: Enhance | C29: Site ladder — as published | O29: published
A30: 3e · Golgari Land Engine | B30: Max | C30: Site ladder — as published | O30: published
A31: 3e · Golgari Land Engine | B31: Tuned-2 | C31: Simulation-improved (Monte Carlo) | D31: 24000 | E31: 5000 | F31: 80.2 | G31: 0.4342 | I31: 12.062183 | J31: 4.7325629 | K31: 0.051 | L31: 0.3518 | M31: confirmed | N31: 13 | O31: simulation-improved (v1 engine)
A32: 3e · Golgari Land Engine | B32: Enhance-2 | C32: Simulation-improved (Monte Carlo) | D32: 7000 | E32: 5000 | F32: 70.6 | G32: 0.3996 | I32: 12.029029 | J32: 4.7151305 | K32: 0.054 | L32: 0.10452 | M32: no-change | N32: 0 | O32: simulation-improved, then independently re-verified as an assembled list
A33: 3e · Golgari Land Engine | B33: Max-2 | C33: Simulation-improved (Monte Carlo) | D33: 7000 | E33: 5000 | F33: 70.6 | G33: 0.3996 | I33: 12.029029 | J33: 4.7151305 | K33: 0.054 | L33: 0.10452 | M33: no-change | N33: 0 | O33: simulation-improved, then independently re-verified as an assembled list
A34: 3e · Golgari Land Engine | B34: Fun Tuned | C34: Fun-weighted engine v2.1 | D34: 22000 | E34: 5000 | F34: 74 | G34: 0.2766 | H34: 0.9989 | I34: 12.237889 | J34: 4.6077326 | K34: 0.0382 | L34: 0.39724 | M34: confirmed | N34: 10 | O34: fun-weighted engine v2.1 (9 opponent archetypes, fun blended into scoring, combat fixes)
A35: 3e · Golgari Land Engine | B35: Fun Max | C35: Fun-weighted engine v2.1 | D35: 22000 | E35: 5000 | F35: 72.2 | G35: 0.2668 | H35: 0.999 | I35: 12.17916 | J35: 4.4341444 | K35: 0.029 | L35: 0.35572 | M35: within-noise | N35: 10 | O35: fun-weighted engine v2.1 (9 opponent archetypes, fun blended into scoring, combat fixes)
A36: 3e · Golgari Land Engine | B36: Alt Tuned | C36: Alternative commander | D36: 22000 | E36: 5000 | F36: 79.1 | G36: 0.346 | H36: 0.9994 | I36: 11.93237 | J36: 4.0439054 | K36: 0.034 | L36: 0.4164 | M36: confirmed | N36: 10 | O36: alternative commander (Hazel of the Rootbloom) on the same 99, v2.1 engine
A37: 3e · Golgari Land Engine | B37: Alt Max | C37: Alternative commander | D37: 24000 | E37: 5000 | F37: 78.8 | G37: 0.351 | H37: 0.9991 | I37: 11.864387 | J37: 3.9857573 | K37: 0.031 | L37: 0.40448 | M37: confirmed | N37: 12 | O37: alternative commander (Hazel of the Rootbloom) on the same 99, v2.1 engine
A39: 4c · Bant Walls | B39: Base | C39: Site ladder — as published | O39: published
A40: 4c · Bant Walls | B40: Tuned | C40: Site ladder — as published | D40: 22000 | E40: 5000 | F40: 61.3 | G40: 0.2932 | I40: 12.966576 | J40: 4.8958378 | K40: 0.1072 | L40: 0.2632 | M40: confirmed | N40: 10 | O40: published + simulated (v1 engine)
A41: 4c · Bant Walls | B41: Enhance | C41: Site ladder — as published | O41: published
A42: 4c · Bant Walls | B42: Max | C42: Site ladder — as published | O42: published
A43: 4c · Bant Walls | B43: Tuned-2 | C43: Simulation-improved (Monte Carlo) | D43: 22000 | E43: 5000 | F43: 61.3 | G43: 0.2932 | I43: 12.966576 | J43: 4.8958378 | K43: 0.1072 | L43: 0.2632 | M43: confirmed | N43: 10 | O43: simulation-improved (v1 engine)
A44: 4c · Bant Walls | B44: Enhance-2 | C44: Simulation-improved (Monte Carlo) | D44: 13000 | E44: 5000 | F44: 55.7 | G44: 0.2456 | I44: 13.038274 | J44: 4.9427398 | K44: 0.113 | L44: 0.19712 | M44: no-change | N44: 0 | O44: simulation-improved, then independently re-verified as an assembled list
A45: 4c · Bant Walls | B45: Max-2 | C45: Simulation-improved (Monte Carlo) | D45: 13000 | E45: 5000 | F45: 55.7 | G45: 0.2456 | I45: 13.038274 | J45: 4.9427398 | K45: 0.113 | L45: 0.19712 | M45: no-change | N45: 0 | O45: simulation-improved, then independently re-verified as an assembled list
A46: 4c · Bant Walls | B46: Fun Tuned | C46: Fun-weighted engine v2.1 | D46: 20000 | E46: 5000 | F46: 81.4 | G46: 0.4688 | H46: 0.9988 | I46: 11.492321 | J46: 4.6407908 | K46: 0.1238 | L46: 0.4416 | M46: confirmed | N46: 5 | O46: fun-weighted engine v2.1 (9 opponent archetypes, fun blended into scoring, combat fixes)
A47: 4c · Bant Walls | B47: Fun Max | C47: Fun-weighted engine v2.1 | D47: 28000 | E47: 5000 | F47: 81 | G47: 0.4436 | H47: 0.9997 | I47: 11.490983 | J47: 4.4841141 | K47: 0.0912 | L47: 0.4282 | M47: within-noise | N47: 2 | O47: fun-weighted engine v2.1 (9 opponent archetypes, fun blended into scoring, combat fixes)
A49: 5o · Lorehold Spirit | B49: Base | C49: Site ladder — as published | O49: published
A50: 5o · Lorehold Spirit | B50: Tuned | C50: Site ladder — as published | D50: 20000 | E50: 5000 | F50: 74.8 | G50: 0.3822 | I50: 12.302459 | J50: 4.1357128 | K50: 0.0526 | L50: 0.27968 | M50: confirmed | N50: 5 | O50: published + simulated (v1 engine)
A51: 5o · Lorehold Spirit | B51: Enhance | C51: Site ladder — as published | O51: published
A52: 5o · Lorehold Spirit | B52: Max | C52: Site ladder — as published | O52: published
A53: 5o · Lorehold Spirit | B53: Tuned-2 | C53: Simulation-improved (Monte Carlo) | D53: 20000 | E53: 5000 | F53: 74.8 | G53: 0.3822 | I53: 12.302459 | J53: 4.1357128 | K53: 0.0526 | L53: 0.27968 | M53: confirmed | N53: 5 | O53: simulation-improved (v1 engine)
A54: 5o · Lorehold Spirit | B54: Enhance-2 | C54: Simulation-improved (Monte Carlo) | D54: 13000 | E54: 5000 | F54: 71.8 | G54: 0.3684 | I54: 12.179696 | J54: 4.0735146 | K54: 0.0536 | L54: 0.21864 | M54: no-change | N54: 0 | O54: simulation-improved, then independently re-verified as an assembled list
A55: 5o · Lorehold Spirit | B55: Max-2 | C55: Simulation-improved (Monte Carlo) | D55: 13000 | E55: 5000 | F55: 70.8 | G55: 0.3622 | I55: 12.185533 | J55: 4.1545272 | K55: 0.0566 | L55: 0.21136 | M55: no-change | N55: 0 | O55: simulation-improved, then independently re-verified as an assembled list
A56: 5o · Lorehold Spirit | B56: Fun Tuned | C56: Fun-weighted engine v2.1 | D56: 22000 | E56: 5000 | F56: 66.6 | G56: 0.1952 | H56: 0.9989 | I56: 12.485656 | J56: 4.0558457 | K56: 0.0496 | L56: 0.3286 | M56: confirmed | N56: 8 | O56: fun-weighted engine v2.1 (9 opponent archetypes, fun blended into scoring, combat fixes)
A57: 5o · Lorehold Spirit | B57: Fun Max | C57: Fun-weighted engine v2.1 | D57: 24000 | E57: 5000 | F57: 68 | G57: 0.2142 | H57: 0.9996 | I57: 12.223156 | J57: 4.071357 | K57: 0.0528 | L57: 0.3284 | M57: confirmed | N57: 7 | O57: fun-weighted engine v2.1 (9 opponent archetypes, fun blended into scoring, combat fixes)
A58: 5o · Lorehold Spirit | B58: Alt Tuned | C58: Alternative commander | D58: 22000 | E58: 5000 | F58: 82.7 | G58: 0.4288 | H58: 0.9989 | I58: 11.708955 | J58: 4.0538369 | K58: 0.0498 | L58: 0.36728 | M58: confirmed | N58: 7 | O58: alternative commander (Iroas, God of Victory) on the same 99, v2.1 engine
A59: 5o · Lorehold Spirit | B59: Alt Max | C59: Alternative commander | D59: 24000 | E59: 5000 | F59: 84.5 | G59: 0.4438 | H59: 0.9994 | I59: 11.707526 | J59: 4.0807615 | K59: 0.0516 | L59: 0.397 | M59: confirmed | N59: 7 | O59: alternative commander (Iroas, God of Victory) on the same 99, v2.1 engine
A61: 6f · Sultai ETB Doubling | B61: Base | C61: Site ladder — as published | O61: published
A62: 6f · Sultai ETB Doubling | B62: Tuned | C62: Site ladder — as published | D62: 14000 | E62: 5000 | F62: 82.9 | G62: 0.444 | I62: 12.157658 | J62: 5.0898302 | K62: 0.0512 | L62: 0.4028 | M62: confirmed | N62: 5 | O62: published + simulated (v1 engine)
A63: 6f · Sultai ETB Doubling | B63: Enhance | C63: Site ladder — as published | O63: published
A64: 6f · Sultai ETB Doubling | B64: Max | C64: Site ladder — as published | O64: published
A65: 6f · Sultai ETB Doubling | B65: Tuned-2 | C65: Simulation-improved (Monte Carlo) | D65: 14000 | E65: 5000 | F65: 82.9 | G65: 0.444 | I65: 12.157658 | J65: 5.0898302 | K65: 0.0512 | L65: 0.4028 | M65: confirmed | N65: 5 | O65: simulation-improved (v1 engine)
A66: 6f · Sultai ETB Doubling | B66: Enhance-2 | C66: Simulation-improved (Monte Carlo) | D66: 20000 | E66: 5000 | F66: 80.3 | G66: 0.4384 | I66: 12.223996 | J66: 5.1131417 | K66: 0.0592 | L66: 0.35488 | M66: within-noise | N66: 1 | O66: simulation-improved, then independently re-verified as an assembled list
A67: 6f · Sultai ETB Doubling | B67: Max-2 | C67: Simulation-improved (Monte Carlo) | D67: 20000 | E67: 5000 | F67: 80.4 | G67: 0.4382 | I67: 12.218622 | J67: 5.1420945 | K67: 0.0584 | L67: 0.36332 | M67: within-noise | N67: 1 | O67: simulation-improved, then independently re-verified as an assembled list
A68: 6f · Sultai ETB Doubling | B68: Fun Tuned | C68: Fun-weighted engine v2.1 | D68: 14000 | E68: 5000 | F68: 75.9 | G68: 0.3182 | H68: 0.9976 | I68: 12.316153 | J68: 5.0118223 | K68: 0.0496 | L68: 0.42932 | M68: within-noise | N68: 4 | O68: fun-weighted engine v2.1 (9 opponent archetypes, fun blended into scoring, combat fixes)
A69: 6f · Sultai ETB Doubling | B69: Fun Max | C69: Fun-weighted engine v2.1 | D69: 20000 | E69: 5000 | F69: 74.5 | G69: 0.319 | H69: 0.9965 | I69: 12.301567 | J69: 5.0273101 | K69: 0.0562 | L69: 0.379 | M69: within-noise | N69: 3 | O69: fun-weighted engine v2.1 (9 opponent archetypes, fun blended into scoring, combat fixes)
A72: Alternative commander — the case, and the caveat
A73: Deck | B73: Current commander | C73: Score | D73: Rank | E73: Alternative | F73: Score | G73: Rank | H73: Candidates measured | I73: Games each | J73: Price | K73: The honest read
A74: 1o · Ancestral Bulwark | B74: Betor, Ancestor's Voice | C74: 80.1 | D74: 4 | E74: Teneb, the Harvester | F74: 80.3 | G74: 3 | H74: 15 | I74: 4000 | J74: 0.98 | K74: Holds up. Teneb is a genuine reanimator, which is what this shell already wants, and it measures a hair above Betor (+0.2 — inside noise). Betor's end-step lifegain-to-counters engine is invisible to the model, so the true gap likely favours Betor. Swap only if you prefer the play pattern, not for the number.
A75: 3e · Golgari Land Engine | B75: The Gitrog Monster | C75: 63 | D75: 7 | E75: Hazel of the Rootbloom | F75: 67.5 | G75: 3 | H75: 15 | I75: 4000 | J75: 6.45 | K75: Real gain, real cost. Hazel measures +4.5 over Gitrog, but the optimizer's response to her is to strip TEN lands from a 48-land lands-matter deck — she pays off tokens, not landfall. That is not a minor tweak; it converts the Golgari Land Engine into a different deck. Adopt only if you want that rebuild.
A76: 5o · Lorehold Spirit | B76: Quintorius, History Chaser | C76: 59.6 | D76: 15 | E76: Iroas, God of Victory | F76: 72.8 | G76: 1 | H76: 15 | I76: 4000 | J76: 12.88 | K76: Treat the +13.2 as unreliable. Iroas only beats Quintorius in the model because the engine cannot see devotion and so treats it as a permanent 7/4 body. Forced to behave as the enchantment it usually is, Iroas scores 59.6 — identical to Quintorius. This deck's 50 nonland permanents average 1.22 red/white pips, so a typical board reaches roughly 5.5 devotion against the 7 Iroas needs. It will usually not be a creature.

Sheet 1o Ancestral Bulwark
A1: Ancestral Bulwark — Betor, Ancestor's Voice
A2: Deck slot 1 · variant 1o · 100 lineup slots · alternative commander tested: Teneb, the Harvester
B4: Site ladder — as published | F4: Simulation-improved (Monte Carlo) | I4: Fun-weighted engine v2.1 | K4: Alternative commander
A5: Slot | B5: Base | C5: Tuned | D5: Enhance | E5: Max | F5: Tuned-2 | G5: Enhance-2 | H5: Max-2 | I5: Fun Tuned | J5: Fun Max | K5: Alt Tuned | L5: Alt Max | M5: FINAL PICK | N5: Final card | O5: Price | P5: Why this card moved
A6: 1 | B6: Felothar the Steadfast | C6: Betor, Kin to All | D6: Betor, Kin to All | E6: Betor, Kin to All | F6: Phyrexian Arena | G6: Phyrexian Arena | H6: Phyrexian Arena | I6: Cloud's Limit Break | J6: Collective Resistance | K6: Teneb, the Harvester | L6: Teneb, the Harvester | M6: Fun Max | N6: =INDEX(B6:L6,MATCH(M6,$B$5:$L$5,0)) | O6: =IFERROR(VLOOKUP(N6,Prices!$A:$B,2,FALSE),0) | P6: =IFERROR(INDEX('_why_1o'!$B2:$L2,MATCH(M6,$B$5:$L$5,0)),"")
A7: 2 | B7: Betor, Ancestor's Voice | C7: Betor, Ancestor's Voice | D7: Betor, Ancestor's Voice | E7: Betor, Ancestor's Voice | F7: Betor, Ancestor's Voice | G7: Betor, Ancestor's Voice | H7: Betor, Ancestor's Voice | I7: Betor, Ancestor's Voice | J7: Betor, Ancestor's Voice | K7: Cloud's Limit Break | L7: Zombie Master | M7: Fun Max | N7: =INDEX(B7:L7,MATCH(M7,$B$5:$L$5,0)) | O7: =IFERROR(VLOOKUP(N7,Prices!$A:$B,2,FALSE),0) | P7: =IFERROR(INDEX('_why_1o'!$B3:$L3,MATCH(M7,$B$5:$L$5,0)),"")
A8: 3 | B8: Protector of the Wastes | C8: Protector of the Wastes | D8: Protector of the Wastes | E8: Protector of the Wastes | F8: Protector of the Wastes | G8: Protector of the Wastes | H8: Protector of the Wastes | I8: Protector of the Wastes | J8: Protector of the Wastes | K8: Protector of the Wastes | L8: Protector of the Wastes | M8: Fun Max | N8: =INDEX(B8:L8,MATCH(M8,$B$5:$L$5,0)) | O8: =IFERROR(VLOOKUP(N8,Prices!$A:$B,2,FALSE),0) | P8: =IFERROR(INDEX('_why_1o'!$B4:$L4,MATCH(M8,$B$5:$L$5,0)),"")
A9: 4 | B9: Reunion of the House | C9: Reunion of the House | D9: Reunion of the House | E9: Reunion of the House | F9: Reunion of the House | G9: Reunion of the House | H9: Reunion of the House | I9: Reunion of the House | J9: Golgari Charm | K9: Reunion of the House | L9: Cloud's Limit Break | M9: Fun Max | N9: =INDEX(B9:L9,MATCH(M9,$B$5:$L$5,0)) | O9: =IFERROR(VLOOKUP(N9,Prices!$A:$B,2,FALSE),0) | P9: =IFERROR(INDEX('_why_1o'!$B5:$L5,MATCH(M9,$B$5:$L$5,0)),"")
A10: 5 | B10: Jaws of Defeat | C10: Ozolith, the Shattered Spire | D10: Ozolith, the Shattered Spire | E10: Ozolith, the Shattered Spire | F10: Authority of the Consuls | G10: Authority of the Consuls | H10: Authority of the Consuls | I10: Valorous Stance | J10: Venat, Heart of Hydaelyn // Hydaelyn, the Mothercrystal | K10: Valorous Stance | L10: Giant's Boulder | M10: Fun Max | N10: =INDEX(B10:L10,MATCH(M10,$B$5:$L$5,0)) | O10: =IFERROR(VLOOKUP(N10,Prices!$A:$B,2,FALSE),0) | P10: =IFERROR(INDEX('_why_1o'!$B6:$L6,MATCH(M10,$B$5:$L$5,0)),"")
A11: 6 | B11: Tip the Scales | C11: Tip the Scales | D11: Hardened Scales | E11: Soul Warden | F11: Zodiark, Umbral God | G11: Zodiark, Umbral God | H11: Zodiark, Umbral God | I11: Golgari Charm | J11: Origin of Metalbending | K11: Golgari Charm | L11: Venat, Heart of Hydaelyn // Hydaelyn, the Mothercrystal | M11: Fun Max | N11: =INDEX(B11:L11,MATCH(M11,$B$5:$L$5,0)) | O11: =IFERROR(VLOOKUP(N11,Prices!$A:$B,2,FALSE),0) | P11: =IFERROR(INDEX('_why_1o'!$B7:$L7,MATCH(M11,$B$5:$L$5,0)),"")
A12: 7 | B12: Will of the Abzan | C12: Will of the Abzan | D12: Will of the Abzan | E12: Will of the Abzan | F12: Valorous Stance | G12: Valorous Stance | H12: Valorous Stance | I12: Golgari Grave-Troll | J12: Will of the Abzan | K12: Golgari Grave-Troll | L12: Will of the Abzan | M12: Fun Max | N12: =INDEX(B12:L12,MATCH(M12,$B$5:$L$5,0)) | O12: =IFERROR(VLOOKUP(N12,Prices!$A:$B,2,FALSE),0) | P12: =IFERROR(INDEX('_why_1o'!$B8:$L8,MATCH(M12,$B$5:$L$5,0)),"")
A13: 8 | B13: Arbor Adherent | C13: Arbor Adherent | D13: Well of Lost Dreams | E13: Arbor Adherent | F13: Blood Artist | G13: Blood Artist | H13: Blood Artist | I13: Arbor Adherent | J13: Snuff Out | K13: Arbor Adherent | L13: Abrupt Decay | M13: Fun Max | N13: =INDEX(B13:L13,MATCH(M13,$B$5:$L$5,0)) | O13: =IFERROR(VLOOKUP(N13,Prices!$A:$B,2,FALSE),0) | P13: =IFERROR(INDEX('_why_1o'!$B9:$L9,MATCH(M13,$B$5:$L$5,0)),"")
A14: 9 | B14: Canopy Gargantuan | C14: Canopy Gargantuan | D14: Canopy Gargantuan | E14: Canopy Gargantuan | F14: Canopy Gargantuan | G14: Canopy Gargantuan | H14: Canopy Gargantuan | I14: Canopy Gargantuan | J14: Canopy Gargantuan | K14: Canopy Gargantuan | L14: Canopy Gargantuan | M14: Fun Max | N14: =INDEX(B14:L14,MATCH(M14,$B$5:$L$5,0)) | O14: =IFERROR(VLOOKUP(N14,Prices!$A:$B,2,FALSE),0) | P14: =IFERROR(INDEX('_why_1o'!$B10:$L10,MATCH(M14,$B$5:$L$5,0)),"")
A15: 10 | B15: Rampart Architect | C15: Rampart Architect | D15: Rampart Architect | E15: Rampart Architect | F15: Rampart Architect | G15: Rampart Architect | H15: Rampart Architect | I15: Rampart Architect | J15: Rampart Architect | K15: Rampart Architect | L15: Rampart Architect | M15: Fun Max | N15: =INDEX(B15:L15,MATCH(M15,$B$5:$L$5,0)) | O15: =IFERROR(VLOOKUP(N15,Prices!$A:$B,2,FALSE),0) | P15: =IFERROR(INDEX('_why_1o'!$B11:$L11,MATCH(M15,$B$5:$L$5,0)),"")
A16: 11 | B16: Tree of Redemption | C16: Tree of Redemption | D16: Tree of Redemption | E16: Tree of Redemption | F16: Tree of Redemption | G16: Tree of Redemption | H16: Tree of Redemption | I16: Tree of Redemption | J16: Tree of Redemption | K16: Tree of Redemption | L16: Tree of Redemption | M16: Fun Max | N16: =INDEX(B16:L16,MATCH(M16,$B$5:$L$5,0)) | O16: =IFERROR(VLOOKUP(N16,Prices!$A:$B,2,FALSE),0) | P16: =IFERROR(INDEX('_why_1o'!$B12:$L12,MATCH(M16,$B$5:$L$5,0)),"")
A17: 12 | B17: Ikra Shidiqi, the Usurper | C17: Hardened Scales | D17: Inspiring Call | E17: Authority of the Consuls | F17: Soul Warden | G17: Soul Warden | H17: Soul Warden | I17: Origin of Metalbending | J17: Damn | K17: Origin of Metalbending | L17: Valorous Stance | M17: Fun Max | N17: =INDEX(B17:L17,MATCH(M17,$B$5:$L$5,0)) | O17: =IFERROR(VLOOKUP(N17,Prices!$A:$B,2,FALSE),0) | P17: =IFERROR(INDEX('_why_1o'!$B13:$L13,MATCH(M17,$B$5:$L$5,0)),"")
... A105: 100 | B105: Forest | C105: Forest | D105: Forest | E105: Forest | F105: Forest | G105: Forest | H105: Forest | I105: Forest | J105: Forest | K105: Forest | L105: Forest | M105: Fun Max | N105: =INDEX(B105:L105,MATCH(M105,$B$5:$L$5,0)) | O105: =IFERROR(VLOOKUP(N105,Prices!$A:$B,2,FALSE),0) | P105: =IFERROR(INDEX('_why_1o'!$B101:$L101,MATCH(M105,$B$5:$L$5,0)),"")
A106: TOTALS | B106: 81.46 | C106: 102.52 | D106: 107.46 | E106: 239.81 | F106: 92.25 | G106: 153.11 | H106: 217.82 | I106: 82.7 | J106: 255.46 | K106: 80.12 | L106: 177.34 | N106: Your selection → | O106: =SUM(O6:O105)
A108: Every row defaults to Fun Max — the newest engine, the full ceiling, and the same commander you already chose. It is a starting point, not a recommendation: change any row. Adopting an Alt column is a commander swap, so it is deliberately never the default; read the Summary tab's alternative-commander block first. Card totals are the full retail value of every card in that column, not what you still need to buy. Amber text marks a card that differs from Base.

Sheet _why_1o
B1: Base | C1: Tuned | D1: Enhance | E1: Max | F1: Tuned-2 | G1: Enhance-2 | H1: Max-2 | I1: Fun Tuned | J1: Fun Max | K1: Alt Tuned | L1: Alt Max
A2: 1 | I2: Replaces Tip the Scales (adds removal/wipe). Evidence: the card it replaces was cast in 56% of the games it was drawn; sat dead in hand 44% of the time; landed on turn 7.1 on average; the deck won 13% of games it was cast in. | J2: Replaces Reunion of the House (adds removal/protection). Evidence: the card it replaces was cast in 64% of the games it was drawn; sat dead in hand 36% of the time; landed on turn 9.1 on average; the deck won 50% of games it was cast in.
A3: 2 | K3: Replaces Tip the Scales (adds removal/wipe). Evidence: the card it replaces was cast in 58% of the games it was drawn; sat dead in hand 42% of the time; landed on turn 6.8 on average; the deck won 17% of games it was cast in. | L3: Replaces Reunion of the House (adds protection/threat). Evidence: the card it replaces was cast in 62% of the games it was drawn; sat dead in hand 38% of the time; landed on turn 9.0 on average; the deck won 54% of games it was cast in.
A4: 3
A5: 4 | J5: Replaces Expel the Interlopers (adds removal/wipe/protection). Evidence: the card it replaces was cast in 54% of the games it was drawn; sat dead in hand 46% of the time; landed on turn 7.9 on average; the deck won 16% of games it was cast in. | L5: Replaces Expel the Interlopers (adds removal/wipe). Evidence: the card it replaces was cast in 56% of the games it was drawn; sat dead in hand 44% of the time; landed on turn 7.5 on average; the deck won 16% of games it was cast in.
A6: 5 | I6: Replaces Will of the Abzan (adds removal/protection). Evidence: the card it replaces was cast in 81% of the games it was drawn; sat dead in hand 19% of the time; landed on turn 8.0 on average; the deck won 46% of games it was cast in. | J6: Replaces Exotic Orchard (adds draw/removal/protection/threat). Evidence: the land it replaces carried no spell effect the model could use; it was drawn in 19% of games; the deck stayed inside its land floor after the cut. | K6: Replaces Will of the Abzan (adds removal/protection). Evidence: the card it replaces was cast in 83% of the games it was drawn; sat dead in hand 17% of the time; landed on turn 7.9 on average; the deck won 47% of games it was cast in. | L6: Replaces Exotic Orchard (adds ramp/removal). Evidence: the land it replaces carried no spell effect the model could use; it was drawn in 19% of games; the deck stayed inside its land floor after the cut.
A7: 6 | F7: Replaces Tip the Scales (adds wipe/protection/finisher/threat). Evidence: the card it replaces was cast in 88% of the games it was drawn; sat dead in hand 12% of the time; landed on turn 6.6 on average; the deck won 14% of games it was cast in. | I7: Replaces Expel the Interlopers (adds removal/wipe/protection). Evidence: the card it replaces was cast in 54% of the games it was drawn; sat dead in hand 46% of the time; landed on turn 7.8 on average; the deck won 13% of games it was cast in. | J7: Replaces Temple of Plenty (adds removal/protection). Evidence: the land it replaces carried no spell effect the model could use; it was drawn in 19% of games; the deck stayed inside its land floor after the cut. | K7: Replaces Expel the Interlopers (adds removal/wipe/protection). Evidence: the card it replaces was cast in 53% of the games it was drawn; sat dead in hand 47% of the time; landed on turn 7.4 on average; the deck won 17% of games it was cast in. | L7: Replaces Wakestone Gargoyle (adds draw/removal/protection/threat). Evidence: the card it replaces was cast in 88% of the games it was drawn; sat dead in hand 12% of the time; landed on turn 7.5 on average; the deck won 51% of games it was cast in.
A8: 7 | F8: Replaces Will of the Abzan (adds removal/protection). Evidence: the card it replaces was cast in 86% of the games it was drawn; sat dead in hand 14% of the time; landed on turn 8.4 on average; the deck won 40% of games it was cast in. | I8: Mandatory legality fix — Tier 2 does not allow Seedborn Muse to stay in this list. | K8: Mandatory legality fix — Tier 2 does not allow Seedborn Muse to stay in this list.
A9: 8 | J9: Replaces Woodland Cemetery (adds removal/protection). Evidence: the land it replaces carried no spell effect the model could use; it was drawn in 19% of games; the deck stayed inside its land floor after the cut. | L9: Replaces Temple of Plenty (adds removal/protection). Evidence: the land it replaces carried no spell effect the model could use; it was drawn in 19% of games; the deck stayed inside its land floor after the cut.
A10: 9
A11: 10
A12: 11
A13: 12 | I13: Replaces Dragonlord Dromoka (adds removal/protection). Evidence: the card it replaces was cast in 89% of the games it was drawn; sat dead in hand 11% of the time; landed on turn 8.1 on average; the deck won 49% of games it was cast in. | J13: Replaces Command Tower (adds removal/protection). Evidence: the land it replaces carried no spell effect the model could use; it was drawn in 19% of games; the deck stayed inside its land floor after the cut. | K13: Replaces Dragonlord Dromoka (adds removal/protection). Evidence: the card it replaces was cast in 87% of the games it was drawn; sat dead in hand 13% of the time; landed on turn 8.3 on average; the deck won 49% of games it was cast in. | L13: Replaces Woodland Cemetery (adds removal/protection). Evidence: the land it replaces carried no spell effect the model could use; it was drawn in 19% of games; the deck stayed inside its land floor after the cut.
A14: 13
A15: 14 | F15: Replaces Expel the Interlopers (adds removal/wipe/protection). Evidence: the card it replaces was cast in 83% of the games it was drawn; sat dead in hand 17% of the time; landed on turn 8.0 on average; the deck won 14% of games it was cast in. | J15: Replaces Path of Ancestry (adds removal/protection). Evidence: the land it replaces carried no spell effect the model could use; it was drawn in 20% of games; the deck stayed inside its land floor after the cut. | L15: Replaces Evolving Wilds (adds removal/protection). Evidence: the land it replaces carried no spell effect the model could use; it was drawn in 19% of games; the deck stayed inside its land floor after the cut.
A16: 15
A17: 16
A18: 17
A19: 18 | F19: Replaces Wakestone Gargoyle (adds draw/removal/protection/threat). Evidence: the card it replaces was cast in 90% of the games it was drawn; sat dead in hand 10% of the time; landed on turn 8.0 on average; the deck won 41% of games it was cast in. | L19: Replaces Path of Ancestry (adds removal/protection/finisher/threat). Evidence: the land it replaces carried no spell effect the model could use; it was drawn in 20% of games; the deck stayed inside its land floor after the cut.
A20: 19
A21: 20
A22: 21 | F22: Replaces Zetalpa, Primal Dawn (adds removal/protection). Evidence: the card it replaces was cast in 79% of the games it was drawn; sat dead in hand 21% of the time; landed on turn 9.1 on average; the deck won 42% of games it was cast in.
A23: 22
A24: 23
A25: 24
A26: 25 | F26: Mandatory legality fix — Tier 2 does not allow Seedborn Muse to stay in this list.
A27: 26
A28: 27
A29: 28
A30: 29
A31: 30
A32: 31
A33: 32
A34: 33
A35: 34
A36: 35
A37: 36
A38: 37
... A47: 46
A48: 47 | J48: Replaces Felidar Retreat (adds removal/protection). Evidence: the card it replaces was cast in 81% of the games it was drawn; sat dead in hand 19% of the time; landed on turn 7.9 on average; the deck won 49% of games it was cast in. | L48: Replaces Felidar Retreat (adds removal/protection). Evidence: the card it replaces was cast in 81% of the games it was drawn; sat dead in hand 19% of the time; landed on turn 7.9 on average; the deck won 49% of games it was cast in.
A49: 48
A50: 49
A51: 50
A52: 51
A53: 52
A54: 53
A55: 54
A56: 55
A57: 56
A58: 57
A59: 58
A60: 59
... A64: 63
A65: 64 | L65: Replaces Smothering Tithe (adds protection). Evidence: the card it replaces was cast in 90% of the games it was drawn; sat dead in hand 10% of the time; landed on turn 5.7 on average; the deck won 47% of games it was cast in.
A66: 65
A67: 66
A68: 67
A69: 68
A70: 69
A71: 70
A72: 71
A73: 72
A74: 73
A75: 74
A76: 75
A77: 76
... A81: 80
A82: 81 | J82: Replaces Branching Evolution (adds removal/protection/finisher/threat). Evidence: the card it replaces was cast in 91% of the games it was drawn; sat dead in hand 9% of the time; landed on turn 7.1 on average; the deck won 43% of games it was cast in. | L82: Replaces Branching Evolution (adds removal). Evidence: the card it replaces was cast in 90% of the games it was drawn; sat dead in hand 10% of the time; landed on turn 7.0 on average; the deck won 43% of games it was cast in.
A83: 82
A84: 83
A85: 84
A86: 85
A87: 86
A88: 87
A89: 88
A90: 89
A91: 90
A92: 91
A93: 92
A94: 93
... A101: 100

Sheet 2c Proliferate Council
A1: Proliferate Council — Atraxa, Praetors' Voice
A2: Deck slot 2 · variant 2c · 100 lineup slots
B4: Site ladder — as published | F4: Simulation-improved (Monte Carlo) | I4: Fun-weighted engine v2.1
A5: Slot | B5: Base | C5: Tuned | D5: Enhance | E5: Max | F5: Tuned-2 | G5: Enhance-2 | H5: Max-2 | I5: Fun Tuned | J5: Fun Max | K5: FINAL PICK | L5: Final card | M5: Price | N5: Why this card moved
A6: 1 | B6: Thrummingbird | C6: Thrummingbird | D6: Thrummingbird | E6: Thrummingbird | F6: Thrummingbird | G6: Thrummingbird | H6: Thrummingbird | I6: Thrummingbird | J6: Thrummingbird | K6: Fun Max | L6: =INDEX(B6:J6,MATCH(K6,$B$5:$J$5,0)) | M6: =IFERROR(VLOOKUP(L6,Prices!$A:$B,2,FALSE),0) | N6: =IFERROR(INDEX('_why_2c'!$B2:$J2,MATCH(K6,$B$5:$J$5,0)),"")
A7: 2 | B7: Viral Drake | C7: Viral Drake | D7: Viral Drake | E7: Viral Drake | F7: Viral Drake | G7: Viral Drake | H7: Viral Drake | I7: Viral Drake | J7: Viral Drake | K7: Fun Max | L7: =INDEX(B7:J7,MATCH(K7,$B$5:$J$5,0)) | M7: =IFERROR(VLOOKUP(L7,Prices!$A:$B,2,FALSE),0) | N7: =IFERROR(INDEX('_why_2c'!$B3:$J3,MATCH(K7,$B$5:$J$5,0)),"")
A8: 3 | B8: Evolution Sage | C8: Evolution Sage | D8: Evolution Sage | E8: Evolution Sage | F8: Evolution Sage | G8: Evolution Sage | H8: Evolution Sage | I8: Evolution Sage | J8: Evolution Sage | K8: Fun Max | L8: =INDEX(B8:J8,MATCH(K8,$B$5:$J$5,0)) | M8: =IFERROR(VLOOKUP(L8,Prices!$A:$B,2,FALSE),0) | N8: =IFERROR(INDEX('_why_2c'!$B4:$J4,MATCH(K8,$B$5:$J$5,0)),"")
A9: 4 | B9: Contagion Clasp | C9: Contagion Clasp | D9: Contagion Clasp | E9: Contagion Clasp | F9: Contagion Clasp | G9: Contagion Clasp | H9: Contagion Clasp | I9: Contagion Clasp | J9: Contagion Clasp | K9: Fun Max | L9: =INDEX(B9:J9,MATCH(K9,$B$5:$J$5,0)) | M9: =IFERROR(VLOOKUP(L9,Prices!$A:$B,2,FALSE),0) | N9: =IFERROR(INDEX('_why_2c'!$B5:$J5,MATCH(K9,$B$5:$J$5,0)),"")
A10: 5 | B10: Steady Progress | C10: Steady Progress | D10: Steady Progress | E10: Steady Progress | F10: Steady Progress | G10: Steady Progress | H10: Steady Progress | I10: Steady Progress | J10: Steady Progress | K10: Fun Max | L10: =INDEX(B10:J10,MATCH(K10,$B$5:$J$5,0)) | M10: =IFERROR(VLOOKUP(L10,Prices!$A:$B,2,FALSE),0) | N10: =IFERROR(INDEX('_why_2c'!$B6:$J6,MATCH(K10,$B$5:$J$5,0)),"")
A11: 6 | B11: Tezzeret's Gambit | C11: Tezzeret's Gambit | D11: Tezzeret's Gambit | E11: Tezzeret's Gambit | F11: Tezzeret's Gambit | G11: Tezzeret's Gambit | H11: Tezzeret's Gambit | I11: Tezzeret's Gambit | J11: Tezzeret's Gambit | K11: Fun Max | L11: =INDEX(B11:J11,MATCH(K11,$B$5:$J$5,0)) | M11: =IFERROR(VLOOKUP(L11,Prices!$A:$B,2,FALSE),0) | N11: =IFERROR(INDEX('_why_2c'!$B7:$J7,MATCH(K11,$B$5:$J$5,0)),"")
A12: 7 | B12: Grim Affliction | C12: Grim Affliction | D12: Grim Affliction | E12: Grim Affliction | F12: Grim Affliction | G12: Grim Affliction | H12: Grim Affliction | I12: Grim Affliction | J12: Grim Affliction | K12: Fun Max | L12: =INDEX(B12:J12,MATCH(K12,$B$5:$J$5,0)) | M12: =IFERROR(VLOOKUP(L12,Prices!$A:$B,2,FALSE),0) | N12: =IFERROR(INDEX('_why_2c'!$B8:$J8,MATCH(K12,$B$5:$J$5,0)),"")
A13: 8 | B13: Throne of Geth | C13: Throne of Geth | D13: Throne of Geth | E13: Throne of Geth | F13: Throne of Geth | G13: Throne of Geth | H13: Throne of Geth | I13: Throne of Geth | J13: Throne of Geth | K13: Fun Max | L13: =INDEX(B13:J13,MATCH(K13,$B$5:$J$5,0)) | M13: =IFERROR(VLOOKUP(L13,Prices!$A:$B,2,FALSE),0) | N13: =IFERROR(INDEX('_why_2c'!$B9:$J9,MATCH(K13,$B$5:$J$5,0)),"")
A14: 9 | B14: Conclave Mentor | C14: Conclave Mentor | D14: Conclave Mentor | E14: Teferi's Protection | F14: Conclave Mentor | G14: Doubling Season | H14: Doubling Season | I14: Conclave Mentor | J14: Portcullis Vine | K14: Fun Max | L14: =INDEX(B14:J14,MATCH(K14,$B$5:$J$5,0)) | M14: =IFERROR(VLOOKUP(L14,Prices!$A:$B,2,FALSE),0) | N14: =IFERROR(INDEX('_why_2c'!$B10:$J10,MATCH(K14,$B$5:$J$5,0)),"")
A15: 10 | B15: Corpsejack Menace | C15: Corpsejack Menace | D15: Corpsejack Menace | E15: Corpsejack Menace | F15: Corpsejack Menace | G15: Corpsejack Menace | H15: Corpsejack Menace | I15: Corpsejack Menace | J15: Corpsejack Menace | K15: Fun Max | L15: =INDEX(B15:J15,MATCH(K15,$B$5:$J$5,0)) | M15: =IFERROR(VLOOKUP(L15,Prices!$A:$B,2,FALSE),0) | N15: =IFERROR(INDEX('_why_2c'!$B11:$J11,MATCH(K15,$B$5:$J$5,0)),"")
A16: 11 | B16: Vorel of the Hull Clade | C16: Vorel of the Hull Clade | D16: Vorel of the Hull Clade | E16: Vorel of the Hull Clade | F16: Vorel of the Hull Clade | G16: Vorel of the Hull Clade | H16: Vorel of the Hull Clade | I16: Vorel of the Hull Clade | J16: Vorel of the Hull Clade | K16: Fun Max | L16: =INDEX(B16:J16,MATCH(K16,$B$5:$J$5,0)) | M16: =IFERROR(VLOOKUP(L16,Prices!$A:$B,2,FALSE),0) | N16: =IFERROR(INDEX('_why_2c'!$B12:$J12,MATCH(K16,$B$5:$J$5,0)),"")
A17: 12 | B17: Forgotten Ancient | C17: Forgotten Ancient | D17: Forgotten Ancient | E17: Forgotten Ancient | F17: Forgotten Ancient | G17: Forgotten Ancient | H17: Forgotten Ancient | I17: Forgotten Ancient | J17: Forgotten Ancient | K17: Fun Max | L17: =INDEX(B17:J17,MATCH(K17,$B$5:$J$5,0)) | M17: =IFERROR(VLOOKUP(L17,Prices!$A:$B,2,FALSE),0) | N17: =IFERROR(INDEX('_why_2c'!$B13:$J13,MATCH(K17,$B$5:$J$5,0)),"")
... A105: 100 | B105: The Ozolith | C105: The Ozolith | D105: The Ozolith | E105: The Ozolith | F105: The Ozolith | G105: The Ozolith | H105: The Ozolith | I105: The Ozolith | J105: The Ozolith | K105: Fun Max | L105: =INDEX(B105:J105,MATCH(K105,$B$5:$J$5,0)) | M105: =IFERROR(VLOOKUP(L105,Prices!$A:$B,2,FALSE),0) | N105: =IFERROR(INDEX('_why_2c'!$B101:$J101,MATCH(K105,$B$5:$J$5,0)),"")
A106: TOTALS | B106: 158.43 | C106: 167.25 | D106: 166.24 | E106: 401.89 | F106: 181.97 | G106: 346.92 | H106: 346.92 | I106: 168.86 | J106: 403.57 | L106: Your selection → | M106: =SUM(M6:M105)
A108: Every row defaults to Fun Max — the newest engine, the full ceiling, and the same commander you already chose. It is a starting point, not a recommendation: change any row. Adopting an Alt column is a commander swap, so it is deliberately never the default; read the Summary tab's alternative-commander block first. Card totals are the full retail value of every card in that column, not what you still need to buy. Amber text marks a card that differs from Base.

Sheet _why_2c
B1: Base | C1: Tuned | D1: Enhance | E1: Max | F1: Tuned-2 | G1: Enhance-2 | H1: Max-2 | I1: Fun Tuned | J1: Fun Max
A2: 1
A3: 2
A4: 3
A5: 4
A6: 5
A7: 6
A8: 7
A9: 8
A10: 9 | J10: Replaces Esper Panorama (adds draw/threat). Evidence: the land it replaces carried no spell effect the model could use; it was drawn in 21% of games; the deck stayed inside its land floor after the cut.
A11: 10
A12: 11
A13: 12
A14: 13
A15: 14
A16: 15
A17: 16
A18: 17
A19: 18
A20: 19 | I20: Replaces Command Tower (adds draw/finisher/threat). Evidence: the land it replaces carried no spell effect the model could use; it was drawn in 21% of games; the deck stayed inside its land floor after the cut. | J20: Replaces Terramorphic Expanse (adds draw/threat). Evidence: the land it replaces carried no spell effect the model could use; it was drawn in 20% of games; the deck stayed inside its land floor after the cut.
A21: 20
A22: 21
A23: 22
A24: 23 | J24: Replaces Scoured Barrens (adds draw/finisher/threat). Evidence: the land it replaces carried no spell effect the model could use; it was drawn in 21% of games; the deck stayed inside its land floor after the cut.
A25: 24
A26: 25
A27: 26
A28: 27
A29: 28
A30: 29
A31: 30 | F31: Replaces Putrefy (adds removal/finisher/threat). Evidence: the card it replaces was cast in 89% of the games it was drawn; sat dead in hand 11% of the time; landed on turn 8.2 on average; the deck won 28% of games it was cast in.
A32: 31
A33: 32 | F33: Replaces Utter End (adds finisher/threat). Evidence: the card it replaces was cast in 92% of the games it was drawn; sat dead in hand 8% of the time; landed on turn 8.7 on average; the deck won 26% of games it was cast in.
A34: 33 | J34: Replaces Orzhov Basilica (adds draw/threat). Evidence: the land it replaces carried no spell effect the model could use; it was drawn in 22% of games; the deck stayed inside its land floor after the cut.
A35: 34
A36: 35
A37: 36 | I37: Replaces Sandsteppe Citadel (adds draw/threat). Evidence: the land it replaces carried no spell effect the model could use; it was drawn in 21% of games; the deck stayed inside its land floor after the cut. | J37: Replaces Sunpetal Grove (adds draw/threat). Evidence: the land it replaces carried no spell effect the model could use; it was drawn in 22% of games; the deck stayed inside its land floor after the cut.
A38: 37
A39: 38 | F39: Replaces Fact or Fiction (adds threat). Evidence: the card it replaces was cast in 92% of the games it was drawn; sat dead in hand 8% of the time; landed on turn 8.3 on average; the deck won 25% of games it was cast in.
A40: 39
A41: 40
A42: 41 | F42: Replaces Inexorable Tide (adds finisher/threat). Evidence: the card it replaces was cast in 76% of the games it was drawn; sat dead in hand 24% of the time; landed on turn 8.8 on average; the deck won 27% of games it was cast in. | I42: Replaces Seaside Citadel (adds draw/threat). Evidence: the land it replaces carried no spell effect the model could use; it was drawn in 22% of games; the deck stayed inside its land floor after the cut.
A43: 42
A44: 43
A45: 44
A46: 45
A47: 46 | F47: Replaces Fuel for the Cause (adds finisher/threat). Evidence: the card it replaces was cast in 78% of the games it was drawn; sat dead in hand 22% of the time; landed on turn 9.3 on average; the deck won 32% of games it was cast in.
A48: 47
A49: 48
A50: 49
A51: 50
A52: 51
A53: 52 | F53: Replaces Karn's Bastion (adds draw/finisher/threat). Evidence: the land it replaces carried no spell effect the model could use; it was drawn in 20% of games; the deck stayed inside its land floor after the cut. | I53: Replaces Esper Panorama (adds draw/threat). Evidence: the land it replaces carried no spell effect the model could use; it was drawn in 22% of games; the deck stayed inside its land floor after the cut.
A54: 53
A55: 54
A56: 55
A57: 56
A58: 57
A59: 58
A60: 59
A61: 60
A62: 61
A63: 62
A64: 63
A65: 64 | I65: Replaces Naya Panorama (adds draw/threat). Evidence: the land it replaces carried no spell effect the model could use; it was drawn in 21% of games; the deck stayed inside its land floor after the cut.
A66: 65
A67: 66
A68: 67
A69: 68
A70: 69
A71: 70
A72: 71
A73: 72
A74: 73
A75: 74 | F75: Replaces Esper Panorama (adds draw/finisher/threat). Evidence: the land it replaces carried no spell effect the model could use; it was drawn in 23% of games; the deck stayed inside its land floor after the cut.
A76: 75 | F76: Replaces Naya Panorama (adds draw/finisher/threat). Evidence: the land it replaces carried no spell effect the model could use; it was drawn in 21% of games; the deck stayed inside its land floor after the cut.
A77: 76
A78: 77
A79: 78
A80: 79
A81: 80
A82: 81
A83: 82
A84: 83
A85: 84
A86: 85 | F86: Replaces Simic Growth Chamber (adds draw/finisher/threat). Evidence: the land it replaces carried no spell effect the model could use; it was drawn in 22% of games; the deck stayed inside its land floor after the cut.
A87: 86
A88: 87
A89: 88
A90: 89 | F90: Replaces Woodland Cemetery (adds draw/finisher/threat). Evidence: the land it replaces carried no spell effect the model could use; it was drawn in 20% of games; the deck stayed inside its land floor after the cut.
A91: 90
A92: 91
A93: 92
A94: 93
A95: 94
A96: 95
A97: 96
A98: 97
A99: 98
A100: 99
...

Sheet 3e Golgari Land Engine
A1: Golgari Land Engine — The Gitrog Monster
A2: Deck slot 3 · variant 3e · 100 lineup slots · alternative commander tested: Hazel of the Rootbloom
B4: Site ladder — as published | F4: Simulation-improved (Monte Carlo) | I4: Fun-weighted engine v2.1 | K4: Alternative commander
A5: Slot | B5: Base | C5: Tuned | D5: Enhance | E5: Max | F5: Tuned-2 | G5: Enhance-2 | H5: Max-2 | I5: Fun Tuned | J5: Fun Max | K5: Alt Tuned | L5: Alt Max | M5: FINAL PICK | N5: Final card | O5: Price | P5: Why this card moved
A6: 1 | B6: Sakura-Tribe Elder | C6: Sakura-Tribe Elder | D6: Sakura-Tribe Elder | E6: Sakura-Tribe Elder | F6: Sakura-Tribe Elder | G6: Sakura-Tribe Elder | H6: Sakura-Tribe Elder | I6: Sakura-Tribe Elder | J6: Sakura-Tribe Elder | K6: Sakura-Tribe Elder | L6: Sakura-Tribe Elder | M6: Fun Max | N6: =INDEX(B6:L6,MATCH(M6,$B$5:$L$5,0)) | O6: =IFERROR(VLOOKUP(N6,Prices!$A:$B,2,FALSE),0) | P6: =IFERROR(INDEX('_why_3e'!$B2:$L2,MATCH(M6,$B$5:$L$5,0)),"")
A7: 2 | B7: Wood Elves | C7: Wood Elves | D7: Wood Elves | E7: Wood Elves | F7: Wood Elves | G7: Wood Elves | H7: Wood Elves | I7: Wood Elves | J7: Wood Elves | K7: Wood Elves | L7: Wood Elves | M7: Fun Max | N7: =INDEX(B7:L7,MATCH(M7,$B$5:$L$5,0)) | O7: =IFERROR(VLOOKUP(N7,Prices!$A:$B,2,FALSE),0) | P7: =IFERROR(INDEX('_why_3e'!$B3:$L3,MATCH(M7,$B$5:$L$5,0)),"")
A8: 3 | B8: Yavimaya Elder | C8: Yavimaya Elder | D8: Yavimaya Elder | E8: Yavimaya Elder | F8: Yavimaya Elder | G8: Yavimaya Elder | H8: Yavimaya Elder | I8: Yavimaya Elder | J8: Yavimaya Elder | K8: Yavimaya Elder | L8: Yavimaya Elder | M8: Fun Max | N8: =INDEX(B8:L8,MATCH(M8,$B$5:$L$5,0)) | O8: =IFERROR(VLOOKUP(N8,Prices!$A:$B,2,FALSE),0) | P8: =IFERROR(INDEX('_why_3e'!$B4:$L4,MATCH(M8,$B$5:$L$5,0)),"")
A9: 4 | B9: Solemn Simulacrum | C9: Solemn Simulacrum | D9: Solemn Simulacrum | E9: Solemn Simulacrum | F9: Solemn Simulacrum | G9: Solemn Simulacrum | H9: Solemn Simulacrum | I9: Solemn Simulacrum | J9: Solemn Simulacrum | K9: Solemn Simulacrum | L9: Solemn Simulacrum | M9: Fun Max | N9: =INDEX(B9:L9,MATCH(M9,$B$5:$L$5,0)) | O9: =IFERROR(VLOOKUP(N9,Prices!$A:$B,2,FALSE),0) | P9: =IFERROR(INDEX('_why_3e'!$B5:$L5,MATCH(M9,$B$5:$L$5,0)),"")
A10: 5 | B10: Sylvan Ranger | C10: Sylvan Ranger | D10: Sylvan Ranger | E10: Sylvan Ranger | F10: Sylvan Ranger | G10: Sylvan Ranger | H10: Sylvan Ranger | I10: Sylvan Ranger | J10: Sylvan Ranger | K10: Sylvan Ranger | L10: Sylvan Ranger | M10: Fun Max | N10: =INDEX(B10:L10,MATCH(M10,$B$5:$L$5,0)) | O10: =IFERROR(VLOOKUP(N10,Prices!$A:$B,2,FALSE),0) | P10: =IFERROR(INDEX('_why_3e'!$B6:$L6,MATCH(M10,$B$5:$L$5,0)),"")
A11: 6 | B11: Tireless Tracker | C11: Tireless Tracker | D11: Tireless Tracker | E11: Tireless Tracker | F11: Tireless Tracker | G11: Tireless Tracker | H11: Tireless Tracker | I11: Tireless Tracker | J11: Tireless Tracker | K11: Tireless Tracker | L11: Tireless Tracker | M11: Fun Max | N11: =INDEX(B11:L11,MATCH(M11,$B$5:$L$5,0)) | O11: =IFERROR(VLOOKUP(N11,Prices!$A:$B,2,FALSE),0) | P11: =IFERROR(INDEX('_why_3e'!$B7:$L7,MATCH(M11,$B$5:$L$5,0)),"")
A12: 7 | B12: Perpetual Timepiece | C12: Perpetual Timepiece | D12: Perpetual Timepiece | E12: Perpetual Timepiece | F12: Perpetual Timepiece | G12: Perpetual Timepiece | H12: Perpetual Timepiece | I12: Perpetual Timepiece | J12: Perpetual Timepiece | K12: Perpetual Timepiece | L12: Perpetual Timepiece | M12: Fun Max | N12: =INDEX(B12:L12,MATCH(M12,$B$5:$L$5,0)) | O12: =IFERROR(VLOOKUP(N12,Prices!$A:$B,2,FALSE),0) | P12: =IFERROR(INDEX('_why_3e'!$B8:$L8,MATCH(M12,$B$5:$L$5,0)),"")
A13: 8 | B13: Sol Ring | C13: Sol Ring | D13: Sol Ring | E13: Sol Ring | F13: Sol Ring | G13: Sol Ring | H13: Sol Ring | I13: Sol Ring | J13: Sol Ring | K13: Sol Ring | L13: Sol Ring | M13: Fun Max | N13: =INDEX(B13:L13,MATCH(M13,$B$5:$L$5,0)) | O13: =IFERROR(VLOOKUP(N13,Prices!$A:$B,2,FALSE),0) | P13: =IFERROR(INDEX('_why_3e'!$B9:$L9,MATCH(M13,$B$5:$L$5,0)),"")
A14: 9 | B14: Arcane Signet | C14: Ramunap Excavator | D14: Ramunap Excavator | E14: Field of the Dead | F14: Ramunap Excavator | G14: Crucible of Worlds | H14: Crucible of Worlds | I14: Inspiring Call | J14: Heritage Reclamation | K14: Heritage Reclamation | L14: Snuff Out | M14: Fun Max | N14: =INDEX(B14:L14,MATCH(M14,$B$5:$L$5,0)) | O14: =IFERROR(VLOOKUP(N14,Prices!$A:$B,2,FALSE),0) | P14: =IFERROR(INDEX('_why_3e'!$B10:$L10,MATCH(M14,$B$5:$L$5,0)),"")
A15: 10 | B15: Golgari Signet | C15: Golgari Signet | D15: Golgari Signet | E15: Golgari Signet | F15: Golgari Signet | G15: Golgari Signet | H15: Golgari Signet | I15: Golgari Signet | J15: Golgari Signet | K15: Golgari Signet | L15: Golgari Signet | M15: Fun Max | N15: =INDEX(B15:L15,MATCH(M15,$B$5:$L$5,0)) | O15: =IFERROR(VLOOKUP(N15,Prices!$A:$B,2,FALSE),0) | P15: =IFERROR(INDEX('_why_3e'!$B11:$L11,MATCH(M15,$B$5:$L$5,0)),"")
A16: 11 | B16: Harrow | C16: Harrow | D16: Harrow | E16: Harrow | F16: Harrow | G16: Harrow | H16: Harrow | I16: Harrow | J16: Harrow | K16: Harrow | L16: Harrow | M16: Fun Max | N16: =INDEX(B16:L16,MATCH(M16,$B$5:$L$5,0)) | O16: =IFERROR(VLOOKUP(N16,Prices!$A:$B,2,FALSE),0) | P16: =IFERROR(INDEX('_why_3e'!$B12:$L12,MATCH(M16,$B$5:$L$5,0)),"")
A17: 12 | B17: Cultivate | C17: Cultivate | D17: Cultivate | E17: Cultivate | F17: Cultivate | G17: Cultivate | H17: Cultivate | I17: Cultivate | J17: Cultivate | K17: Cultivate | L17: Cultivate | M17: Fun Max | N17: =INDEX(B17:L17,MATCH(M17,$B$5:$L$5,0)) | O17: =IFERROR(VLOOKUP(N17,Prices!$A:$B,2,FALSE),0) | P17: =IFERROR(INDEX('_why_3e'!$B13:$L13,MATCH(M17,$B$5:$L$5,0)),"")
... A105: 100 | B105: Currency Converter | C105: Currency Converter | D105: Currency Converter | E105: Currency Converter | F105: Currency Converter | G105: Currency Converter | H105: Currency Converter | I105: Currency Converter | J105: Currency Converter | K105: Currency Converter | L105: Currency Converter | M105: Fun Max | N105: =INDEX(B105:L105,MATCH(M105,$B$5:$L$5,0)) | O105: =IFERROR(VLOOKUP(N105,Prices!$A:$B,2,FALSE),0) | P105: =IFERROR(INDEX('_why_3e'!$B101:$L101,MATCH(M105,$B$5:$L$5,0)),"")
A106: TOTALS | B106: 54.81 | C106: 64.41 | D106: 64.3 | E106: 154.99 | F106: 230.36 | G106: 290.78 | H106: 290.78 | I106: 118.97 | J106: 179.51 | K106: 122.96 | L106: 194.4 | N106: Your selection → | O106: =SUM(O6:O105)
A108: Every row defaults to Fun Max — the newest engine, the full ceiling, and the same commander you already chose. It is a starting point, not a recommendation: change any row. Adopting an Alt column is a commander swap, so it is deliberately never the default; read the Summary tab's alternative-commander block first. Card totals are the full retail value of every card in that column, not what you still need to buy. Amber text marks a card that differs from Base.

Sheet _why_3e
B1: Base | C1: Tuned | D1: Enhance | E1: Max | F1: Tuned-2 | G1: Enhance-2 | H1: Max-2 | I1: Fun Tuned | J1: Fun Max | K1: Alt Tuned | L1: Alt Max
A2: 1
A3: 2
A4: 3
A5: 4
A6: 5
A7: 6
A8: 7
A9: 8
A10: 9 | I10: Replaces Blighted Woodland (adds draw/protection). Evidence: the land it replaces carried no spell effect the model could use; it was drawn in 18% of games; the deck stayed inside its land floor after the cut. | J10: Replaces Command Tower (adds draw/removal). Evidence: the land it replaces carried no spell effect the model could use; it was drawn in 18% of games; the deck stayed inside its land floor after the cut. | K10: Replaces Llanowar Wastes (adds draw/removal). Evidence: the land it replaces carried no spell effect the model could use; it was drawn in 19% of games; the deck stayed inside its land floor after the cut. | L10: Replaces Casualties of War (adds removal/protection). Evidence: the card it replaces was cast in 96% of the games it was drawn; sat dead in hand 4% of the time; landed on turn 7.5 on average; the deck won 35% of games it was cast in.
A11: 10
A12: 11
A13: 12
A14: 13
A15: 14
A16: 15
A17: 16
A18: 17
A19: 18
A20: 19
A21: 20
A22: 21
A23: 22 | I23: Replaces Llanowar Wastes (adds draw/removal/threat). Evidence: the land it replaces carried no spell effect the model could use; it was drawn in 19% of games; the deck stayed inside its land floor after the cut. | J23: Replaces Woodland Cemetery (adds draw/protection). Evidence: the land it replaces carried no spell effect the model could use; it was drawn in 17% of games; the deck stayed inside its land floor after the cut. | K23: Replaces Golgari Rot Farm (adds draw/protection). Evidence: the land it replaces carried no spell effect the model could use; it was drawn in 19% of games; the deck stayed inside its land floor after the cut. | L23: Replaces Command Tower (adds draw/removal). Evidence: the land it replaces carried no spell effect the model could use; it was drawn in 18% of games; the deck stayed inside its land floor after the cut.
A24: 23 | I24: Replaces Golgari Rot Farm (adds removal/protection). Evidence: the land it replaces carried no spell effect the model could use; it was drawn in 20% of games; the deck stayed inside its land floor after the cut. | J24: Replaces Bojuka Bog (adds draw/removal). Evidence: the land it replaces carried no spell effect the model could use; it was drawn in 19% of games; the deck stayed inside its land floor after the cut. | K24: Replaces Bojuka Bog (adds removal/protection). Evidence: the land it replaces carried no spell effect the model could use; it was drawn in 20% of games; the deck stayed inside its land floor after the cut. | L24: Replaces Woodland Cemetery (adds removal/protection). Evidence: the land it replaces carried no spell effect the model could use; it was drawn in 17% of games; the deck stayed inside its land floor after the cut.
A25: 24
A26: 25 | F26: Replaces Casualties of War (adds removal/protection). Evidence: the card it replaces was cast in 93% of the games it was drawn; sat dead in hand 7% of the time; landed on turn 8.0 on average; the deck won 37% of games it was cast in. | L26: Replaces Bojuka Bog (adds draw/removal). Evidence: the land it replaces carried no spell effect the model could use; it was drawn in 19% of games; the deck stayed inside its land floor after the cut.
A27: 26
A28: 27
A29: 28
A30: 29
A31: 30
A32: 31
A33: 32
A34: 33
A35: 34
A36: 35
A37: 36
A38: 37 | I38: Replaces Bojuka Bog (adds removal/protection). Evidence: the land it replaces carried no spell effect the model could use; it was drawn in 20% of games; the deck stayed inside its land floor after the cut.
A39: 38
A40: 39
A41: 40
A42: 41
A43: 42
A44: 43
A45: 44
A46: 45
A47: 46 | J47: Replaces Ghost Quarter (adds removal/protection). Evidence: the land it replaces carried no spell effect the model could use; it was drawn in 19% of games; the deck stayed inside its land floor after the cut. | L47: Replaces Blast Zone (adds removal/protection). Evidence: the land it replaces carried no spell effect the model could use; it was drawn in 18% of games; the deck stayed inside its land floor after the cut.
A48: 47
A49: 48
A50: 49 | J50: Replaces Myriad Landscape (adds draw/removal/protection). Evidence: the land it replaces carried no spell effect the model could use; it was drawn in 18% of games; the deck stayed inside its land floor after the cut. | L50: Replaces Myriad Landscape (adds removal/protection). Evidence: the land it replaces carried no spell effect the model could use; it was drawn in 17% of games; the deck stayed inside its land floor after the cut.
A51: 50
A52: 51
A53: 52
A54: 53
A55: 54
A56: 55
A57: 56
A58: 57
A59: 58
A60: 59
A61: 60
A62: 61
... A76: 75
A77: 76 | F77: Replaces Command Tower (adds finisher/threat). Evidence: the land it replaces carried no spell effect the model could use; it was drawn in 20% of games; the deck stayed inside its land floor after the cut. | J77: Replaces Barren Moor (adds draw/removal/threat). Evidence: the land it replaces carried no spell effect the model could use; it was drawn in 19% of games; the deck stayed inside its land floor after the cut. | L77: Replaces Barren Moor (adds draw/protection). Evidence: the land it replaces carried no spell effect the model could use; it was drawn in 19% of games; the deck stayed inside its land floor after the cut.
A78: 77 | F78: Replaces Woodland Cemetery (adds removal/protection/finisher/threat). Evidence: the land it replaces carried no spell effect the model could use; it was drawn in 20% of games; the deck stayed inside its land floor after the cut. | J78: Replaces Grim Backwoods (adds draw/removal/threat). Evidence: the land it replaces carried no spell effect the model could use; it was drawn in 19% of games; the deck stayed inside its land floor after the cut. | L78: Replaces Grim Backwoods (adds draw/removal/threat). Evidence: the land it replaces carried no spell effect the model could use; it was drawn in 19% of games; the deck stayed inside its land floor after the cut.
A79: 78 | F79: Replaces Llanowar Wastes (adds removal/protection). Evidence: the land it replaces carried no spell effect the model could use; it was drawn in 20% of games; the deck stayed inside its land floor after the cut. | I79: Replaces Evolving Wilds (adds removal/wipe/protection). Evidence: the land it replaces carried no spell effect the model could use; it was drawn in 18% of games; the deck stayed inside its land floor after the cut. | K79: Replaces Dakmor Salvage (adds draw/removal). Evidence: the land it replaces carried no spell effect the model could use; it was drawn in 18% of games; the deck stayed inside its land floor after the cut.
A80: 79 | F80: Replaces Golgari Rot Farm (adds wipe/protection/finisher/threat). Evidence: the land it replaces carried no spell effect the model could use; it was drawn in 20% of games; the deck stayed inside its land floor after the cut. | I80: Replaces Dakmor Salvage (adds draw/removal/protection). Evidence: the land it replaces carried no spell effect the model could use; it was drawn in 18% of games; the deck stayed inside its land floor after the cut. | K80: Replaces Evolving Wilds (adds draw/removal/protection). Evidence: the land it replaces carried no spell effect the model could use; it was drawn in 18% of games; the deck stayed inside its land floor after the cut.
A81: 80
A82: 81 | I82: Replaces Golgari Guildgate (adds removal/protection). Evidence: the land it replaces carried no spell effect the model could use; it was drawn in 20% of games; the deck stayed inside its land floor after the cut. | J82: Replaces Fabled Passage (adds removal/protection). Evidence: the land it replaces carried no spell effect the model could use; it was drawn in 19% of games; the deck stayed inside its land floor after the cut. | K82: Replaces Terramorphic Expanse (adds draw/removal/threat). Evidence: the land it replaces carried no spell effect the model could use; it was drawn in 19% of games; the deck stayed inside its land floor after the cut.
A83: 82 | F83: Replaces Dakmor Salvage (adds draw/removal/protection). Evidence: the land it replaces carried no spell effect the model could use; it was drawn in 19% of games; the deck stayed inside its land floor after the cut. | I83: Replaces Barren Moor (adds draw/removal). Evidence: the land it replaces carried no spell effect the model could use; it was drawn in 19% of games; the deck stayed inside its land floor after the cut. | K83: Replaces Foul Orchard (adds removal/protection). Evidence: the land it replaces carried no spell effect the model could use; it was drawn in 19% of games; the deck stayed inside its land floor after the cut.
A84: 83
A85: 84 | L85: Replaces Fabled Passage (adds draw/removal/protection). Evidence: the land it replaces carried no spell effect the model could use; it was drawn in 18% of games; the deck stayed inside its land floor after the cut.
A86: 85 | F86: Replaces Evolving Wilds (adds removal/protection). Evidence: the land it replaces carried no spell effect the model could use; it was drawn in 19% of games; the deck stayed inside its land floor after the cut. | I86: Replaces Tranquil Thicket (adds draw/protection/threat). Evidence: the land it replaces carried no spell effect the model could use; it was drawn in 17% of games; the deck stayed inside its land floor after the cut. | K86: Replaces Slippery Karst (adds removal/protection). Evidence: the land it replaces carried no spell effect the model could use; it was drawn in 19% of games; the deck stayed inside its land floor after the cut.
A87: 86 | K87: Replaces Fabled Passage (adds removal/wipe/protection). Evidence: the land it replaces carried no spell effect the model could use; it was drawn in 18% of games; the deck stayed inside its land floor after the cut.
A88: 87 | F88: Replaces Myriad Landscape (adds removal/finisher/threat). Evidence: the land it replaces carried no spell effect the model could use; it was drawn in 19% of games; the deck stayed inside its land floor after the cut. | J88: Replaces Mirkwood (adds removal/wipe/protection). Evidence: the land it replaces carried no spell effect the model could use; it was drawn in 18% of games; the deck stayed inside its land floor after the cut.
A89: 88 | I89: Replaces Foul Orchard (adds draw/removal/threat). Evidence: the land it replaces carried no spell effect the model could use; it was drawn in 20% of games; the deck stayed inside its land floor after the cut. | J89: Replaces Field of the Dead (adds removal/protection). Evidence: the land it replaces carried no spell effect the model could use; it was drawn in 19% of games; the deck stayed inside its land floor after the cut. | L89: Replaces Mirkwood (adds removal/wipe). Evidence: the land it replaces carried no spell effect the model could use; it was drawn in 18% of games; the deck stayed inside its land floor after the cut.
A90: 89
A91: 90 | L91: Replaces Field of the Dead (adds removal/protection). Evidence: the land it replaces carried no spell effect the model could use; it was drawn in 19% of games; the deck stayed inside its land floor after the cut.
A92: 91
A93: 92
A94: 93 | F94: Replaces Foul Orchard (adds removal/protection). Evidence: the land it replaces carried no spell effect the model could use; it was drawn in 20% of games; the deck stayed inside its land floor after the cut. | K94: Replaces Barren Moor (adds draw/removal/threat). Evidence: the land it replaces carried no spell effect the model could use; it was drawn in 19% of games; the deck stayed inside its land floor after the cut.
A95: 94 | F95: Replaces Slippery Karst (adds removal/protection). Evidence: the land it replaces carried no spell effect the model could use; it was drawn in 20% of games; the deck stayed inside its land floor after the cut.
A96: 95
A97: 96
A98: 97 | F98: Replaces Fabled Passage (adds removal/protection/finisher/threat). Evidence: the land it replaces carried no spell effect the model could use; it was drawn in 19% of games; the deck stayed inside its land floor after the cut.
A99: 98
A100: 99
A101: 100

Sheet 4c Bant Walls
A1: Bant Walls — Arcades, the Strategist
A2: Deck slot 4 · variant 4c · 100 lineup slots
B4: Site ladder — as published | F4: Simulation-improved (Monte Carlo) | I4: Fun-weighted engine v2.1
A5: Slot | B5: Base | C5: Tuned | D5: Enhance | E5: Max | F5: Tuned-2 | G5: Enhance-2 | H5: Max-2 | I5: Fun Tuned | J5: Fun Max | K5: FINAL PICK | L5: Final card | M5: Price | N5: Why this card moved
A6: 1 | B6: Wall of Denial | C6: Wall of Denial | D6: Wall of Denial | E6: Wall of Denial | F6: Wall of Denial | G6: Wall of Denial | H6: Wall of Denial | I6: Wall of Denial | J6: Wall of Denial | K6: Fun Max | L6: =INDEX(B6:J6,MATCH(K6,$B$5:$J$5,0)) | M6: =IFERROR(VLOOKUP(L6,Prices!$A:$B,2,FALSE),0) | N6: =IFERROR(INDEX('_why_4c'!$B2:$J2,MATCH(K6,$B$5:$J$5,0)),"")
A7: 2 | B7: Fog Bank | C7: Fog Bank | D7: Fog Bank | E7: Fog Bank | F7: Fog Bank | G7: Fog Bank | H7: Fog Bank | I7: Fog Bank | J7: Fog Bank | K7: Fun Max | L7: =INDEX(B7:J7,MATCH(K7,$B$5:$J$5,0)) | M7: =IFERROR(VLOOKUP(L7,Prices!$A:$B,2,FALSE),0) | N7: =IFERROR(INDEX('_why_4c'!$B3:$J3,MATCH(K7,$B$5:$J$5,0)),"")
A8: 3 | B8: Wall of Junk | C8: Wall of Junk | D8: Wall of Junk | E8: Wall of Junk | F8: Wall of Junk | G8: Wall of Junk | H8: Wall of Junk | I8: Wall of Junk | J8: Wall of Junk | K8: Fun Max | L8: =INDEX(B8:J8,MATCH(K8,$B$5:$J$5,0)) | M8: =IFERROR(VLOOKUP(L8,Prices!$A:$B,2,FALSE),0) | N8: =IFERROR(INDEX('_why_4c'!$B4:$J4,MATCH(K8,$B$5:$J$5,0)),"")
A9: 4 | B9: Perimeter Captain | C9: Perimeter Captain | D9: Perimeter Captain | E9: Perimeter Captain | F9: Perimeter Captain | G9: Perimeter Captain | H9: Perimeter Captain | I9: Perimeter Captain | J9: Perimeter Captain | K9: Fun Max | L9: =INDEX(B9:J9,MATCH(K9,$B$5:$J$5,0)) | M9: =IFERROR(VLOOKUP(L9,Prices!$A:$B,2,FALSE),0) | N9: =IFERROR(INDEX('_why_4c'!$B5:$J5,MATCH(K9,$B$5:$J$5,0)),"")
A10: 5 | B10: Shield Sphere | C10: Shield Sphere | D10: Shield Sphere | E10: Shield Sphere | F10: Shield Sphere | G10: Shield Sphere | H10: Shield Sphere | I10: Shield Sphere | J10: Shield Sphere | K10: Fun Max | L10: =INDEX(B10:J10,MATCH(K10,$B$5:$J$5,0)) | M10: =IFERROR(VLOOKUP(L10,Prices!$A:$B,2,FALSE),0) | N10: =IFERROR(INDEX('_why_4c'!$B6:$J6,MATCH(K10,$B$5:$J$5,0)),"")
A11: 6 | B11: Steel Wall | C11: Steel Wall | D11: Steel Wall | E11: Steel Wall | F11: Steel Wall | G11: Steel Wall | H11: Steel Wall | I11: Steel Wall | J11: Steel Wall | K11: Fun Max | L11: =INDEX(B11:J11,MATCH(K11,$B$5:$J$5,0)) | M11: =IFERROR(VLOOKUP(L11,Prices!$A:$B,2,FALSE),0) | N11: =IFERROR(INDEX('_why_4c'!$B7:$J7,MATCH(K11,$B$5:$J$5,0)),"")
A12: 7 | B12: Wall of Frost | C12: Wall of Frost | D12: Wall of Frost | E12: Wall of Frost | F12: Aesi, Tyrant of Gyre Strait | G12: Aesi, Tyrant of Gyre Strait | H12: Aesi, Tyrant of Gyre Strait | I12: Wall of Frost | J12: Wall of Frost | K12: Fun Max | L12: =INDEX(B12:J12,MATCH(K12,$B$5:$J$5,0)) | M12: =IFERROR(VLOOKUP(L12,Prices!$A:$B,2,FALSE),0) | N12: =IFERROR(INDEX('_why_4c'!$B8:$J8,MATCH(K12,$B$5:$J$5,0)),"")
A13: 8 | B13: Glacial Wall | C13: Glacial Wall | D13: Glacial Wall | E13: Glacial Wall | F13: Kruphix, God of Horizons | G13: Kruphix, God of Horizons | H13: Kruphix, God of Horizons | I13: Glacial Wall | J13: Glacial Wall | K13: Fun Max | L13: =INDEX(B13:J13,MATCH(K13,$B$5:$J$5,0)) | M13: =IFERROR(VLOOKUP(L13,Prices!$A:$B,2,FALSE),0) | N13: =IFERROR(INDEX('_why_4c'!$B9:$J9,MATCH(K13,$B$5:$J$5,0)),"")
A14: 9 | B14: Overgrown Battlement | C14: Overgrown Battlement | D14: Overgrown Battlement | E14: Overgrown Battlement | F14: Overgrown Battlement | G14: Overgrown Battlement | H14: Overgrown Battlement | I14: Overgrown Battlement | J14: Overgrown Battlement | K14: Fun Max | L14: =INDEX(B14:J14,MATCH(K14,$B$5:$J$5,0)) | M14: =IFERROR(VLOOKUP(L14,Prices!$A:$B,2,FALSE),0) | N14: =IFERROR(INDEX('_why_4c'!$B10:$J10,MATCH(K14,$B$5:$J$5,0)),"")
A15: 10 | B15: Vine Trellis | C15: Vine Trellis | D15: Vine Trellis | E15: Vine Trellis | F15: Vine Trellis | G15: Vine Trellis | H15: Vine Trellis | I15: Vine Trellis | J15: Vine Trellis | K15: Fun Max | L15: =INDEX(B15:J15,MATCH(K15,$B$5:$J$5,0)) | M15: =IFERROR(VLOOKUP(L15,Prices!$A:$B,2,FALSE),0) | N15: =IFERROR(INDEX('_why_4c'!$B11:$J11,MATCH(K15,$B$5:$J$5,0)),"")
A16: 11 | B16: Wall of Tanglecord | C16: Wall of Tanglecord | D16: Wall of Tanglecord | E16: Wall of Tanglecord | F16: Wall of Tanglecord | G16: Wall of Tanglecord | H16: Wall of Tanglecord | I16: Wall of Tanglecord | J16: Wall of Tanglecord | K16: Fun Max | L16: =INDEX(B16:J16,MATCH(K16,$B$5:$J$5,0)) | M16: =IFERROR(VLOOKUP(L16,Prices!$A:$B,2,FALSE),0) | N16: =IFERROR(INDEX('_why_4c'!$B12:$J12,MATCH(K16,$B$5:$J$5,0)),"")
A17: 12 | B17: Wall of Kelp | C17: Wall of Kelp | D17: Wall of Kelp | E17: Wall of Kelp | F17: Wall of Kelp | G17: Wall of Kelp | H17: Wall of Kelp | I17: Wall of Kelp | J17: Wall of Kelp | K17: Fun Max | L17: =INDEX(B17:J17,MATCH(K17,$B$5:$J$5,0)) | M17: =IFERROR(VLOOKUP(L17,Prices!$A:$B,2,FALSE),0) | N17: =IFERROR(INDEX('_why_4c'!$B13:$J13,MATCH(K17,$B$5:$J$5,0)),"")
... A105: 100 | B105: Bedrock Tortoise | C105: Bedrock Tortoise | D105: Bedrock Tortoise | E105: Bedrock Tortoise | F105: Bedrock Tortoise | G105: Bedrock Tortoise | H105: Bedrock Tortoise | I105: Bedrock Tortoise | J105: Bedrock Tortoise | K105: Fun Max | L105: =INDEX(B105:J105,MATCH(K105,$B$5:$J$5,0)) | M105: =IFERROR(VLOOKUP(L105,Prices!$A:$B,2,FALSE),0) | N105: =IFERROR(INDEX('_why_4c'!$B101:$J101,MATCH(K105,$B$5:$J$5,0)),"")
A106: TOTALS | B106: 57.94 | C106: 56.28 | D106: 57.29 | E106: 126.51 | F106: 124.43 | G106: 185.34 | H106: 185.34 | I106: 65.66 | J106: 131.47 | L106: Your selection → | M106: =SUM(M6:M105)
A108: Every row defaults to Fun Max — the newest engine, the full ceiling, and the same commander you already chose. It is a starting point, not a recommendation: change any row. Adopting an Alt column is a commander swap, so it is deliberately never the default; read the Summary tab's alternative-commander block first. Card totals are the full retail value of every card in that column, not what you still need to buy. Amber text marks a card that differs from Base.

Sheet _why_4c
B1: Base | C1: Tuned | D1: Enhance | E1: Max | F1: Tuned-2 | G1: Enhance-2 | H1: Max-2 | I1: Fun Tuned | J1: Fun Max
A2: 1
A3: 2
A4: 3
A5: 4
A6: 5
A7: 6
A8: 7
A9: 8 | F9: Replaces Glacial Wall (adds protection/finisher/threat). Evidence: the card it replaces was cast in 90% of the games it was drawn; sat dead in hand 10% of the time; landed on turn 7.5 on average; the deck won 22% of games it was cast in.
A10: 9
A11: 10
A12: 11
A13: 12
A14: 13 | F14: Replaces High Alert (adds protection/finisher/threat). Evidence: the card it replaces was cast in 89% of the games it was drawn; sat dead in hand 11% of the time; landed on turn 8.2 on average; the deck won 24% of games it was cast in. | I14: Replaces Seaside Citadel (adds draw/removal/protection/threat). Evidence: the land it replaces carried no spell effect the model could use; it was drawn in 19% of games; the deck stayed inside its land floor after the cut. | J14: Replaces Evolving Wilds (adds removal/protection). Evidence: the land it replaces carried no spell effect the model could use; it was drawn in 18% of games; the deck stayed inside its land floor after the cut.
A15: 14
A16: 15
A17: 16
A18: 17
A19: 18
A20: 19
A21: 20
A22: 21 | I22: Replaces Selesnya Sanctuary (adds draw/removal/protection). Evidence: the land it replaces carried no spell effect the model could use; it was drawn in 19% of games; the deck stayed inside its land floor after the cut. | J22: Replaces Krosan Verge (adds removal/protection). Evidence: the land it replaces carried no spell effect the model could use; it was drawn in 19% of games; the deck stayed inside its land floor after the cut.
A23: 22
A24: 23
A25: 24
A26: 25
A27: 26
A28: 27
A29: 28
A30: 29
A31: 30
A32: 31
A33: 32 | F33: Replaces Return to Dust (adds removal/finisher/threat). Evidence: the card it replaces was cast in 85% of the games it was drawn; sat dead in hand 15% of the time; landed on turn 8.6 on average; the deck won 22% of games it was cast in.
A34: 33
A35: 34
A36: 35 | I36: Replaces Sunpetal Grove (adds removal/protection). Evidence: the land it replaces carried no spell effect the model could use; it was drawn in 18% of games; the deck stayed inside its land floor after the cut.
A37: 36 | F37: Replaces Mystic Confluence (adds draw/protection/finisher/threat). Evidence: the card it replaces was cast in 78% of the games it was drawn; sat dead in hand 22% of the time; landed on turn 8.1 on average; the deck won 23% of games it was cast in.
A38: 37
A39: 38
A40: 39
A41: 40
A42: 41
A43: 42
A44: 43
A45: 44
A46: 45
A47: 46 | I47: Replaces Terramorphic Expanse (adds removal/protection). Evidence: the land it replaces carried no spell effect the model could use; it was drawn in 18% of games; the deck stayed inside its land floor after the cut.
A48: 47
A49: 48
A50: 49
A51: 50
A52: 51 | F52: Replaces Rewind (adds removal/protection/finisher/threat). Evidence: the card it replaces was cast in 76% of the games it was drawn; sat dead in hand 24% of the time; landed on turn 9.4 on average; the deck won 23% of games it was cast in.
A53: 52 | F53: Replaces Whirlwind Denial (adds protection/finisher/threat). Evidence: the card it replaces was cast in 90% of the games it was drawn; sat dead in hand 10% of the time; landed on turn 7.7 on average; the deck won 21% of games it was cast in.
A54: 53
A55: 54
A56: 55
A57: 56
A58: 57
A59: 58
A60: 59
A61: 60
A62: 61
A63: 62
A64: 63
A65: 64
... A75: 74
A76: 75 | F76: Replaces Seaside Citadel (adds removal/protection/finisher/threat). Evidence: the land it replaces carried no spell effect the model could use; it was drawn in 20% of games; the deck stayed inside its land floor after the cut. | I76: Replaces Krosan Verge (adds removal/protection). Evidence: the land it replaces carried no spell effect the model could use; it was drawn in 20% of games; the deck stayed inside its land floor after the cut.
A77: 76
A78: 77
A79: 78 | F79: Replaces Bant Panorama (adds removal/protection). Evidence: the land it replaces carried no spell effect the model could use; it was drawn in 20% of games; the deck stayed inside its land floor after the cut.
A80: 79
A81: 80
A82: 81
A83: 82
A84: 83
A85: 84
A86: 85
A87: 86
A88: 87
A89: 88
A90: 89 | F90: Replaces Terramorphic Expanse (adds removal/protection/finisher/threat). Evidence: the land it replaces carried no spell effect the model could use; it was drawn in 19% of games; the deck stayed inside its land floor after the cut.
A91: 90 | F91: Replaces Myriad Landscape (adds draw/removal/protection/threat). Evidence: the land it replaces carried no spell effect the model could use; it was drawn in 19% of games; the deck stayed inside its land floor after the cut.
A92: 91
A93: 92
A94: 93
A95: 94
A96: 95
A97: 96
A98: 97
A99: 98
A100: 99
A101: 100

Sheet 5o Lorehold Spirit
A1: Lorehold Spirit — Quintorius, History Chaser
A2: Deck slot 5 · variant 5o · 100 lineup slots · alternative commander tested: Iroas, God of Victory
B4: Site ladder — as published | F4: Simulation-improved (Monte Carlo) | I4: Fun-weighted engine v2.1 | K4: Alternative commander
A5: Slot | B5: Base | C5: Tuned | D5: Enhance | E5: Max | F5: Tuned-2 | G5: Enhance-2 | H5: Max-2 | I5: Fun Tuned | J5: Fun Max | K5: Alt Tuned | L5: Alt Max | M5: FINAL PICK | N5: Final card | O5: Price | P5: Why this card moved
A6: 1 | B6: Quintorius, History Chaser | C6: Quintorius, History Chaser | D6: Quintorius, History Chaser | E6: Quintorius, History Chaser | F6: Quintorius, History Chaser | G6: Quintorius, History Chaser | H6: Quintorius, History Chaser | I6: Quintorius, History Chaser | J6: Quintorius, History Chaser | K6: Iroas, God of Victory | L6: Iroas, God of Victory | M6: Fun Max | N6: =INDEX(B6:L6,MATCH(M6,$B$5:$L$5,0)) | O6: =IFERROR(VLOOKUP(N6,Prices!$A:$B,2,FALSE),0) | P6: =IFERROR(INDEX('_why_5o'!$B2:$L2,MATCH(M6,$B$5:$L$5,0)),"")
A7: 2 | B7: Excava, the Risen Past | C7: Cast Out | D7: Cast Out | E7: Cast Out | F7: Darksteel Plate | G7: Darksteel Plate | H7: Darksteel Plate | I7: Cloud's Limit Break | J7: Venat, Heart of Hydaelyn // Hydaelyn, the Mothercrystal | K7: Cloud's Limit Break | L7: Cloud's Limit Break | M7: Fun Max | N7: =INDEX(B7:L7,MATCH(M7,$B$5:$L$5,0)) | O7: =IFERROR(VLOOKUP(N7,Prices!$A:$B,2,FALSE),0) | P7: =IFERROR(INDEX('_why_5o'!$B3:$L3,MATCH(M7,$B$5:$L$5,0)),"")
A8: 3 | B8: Lorehold Archivist // Restore Relic | C8: Lorehold Archivist // Restore Relic | D8: Lorehold Archivist // Restore Relic | E8: Lorehold Archivist // Restore Relic | F8: Lorehold Archivist // Restore Relic | G8: Lorehold Archivist // Restore Relic | H8: Lorehold Archivist // Restore Relic | I8: Lorehold Archivist // Restore Relic | J8: Lorehold Archivist // Restore Relic | K8: Lorehold Archivist // Restore Relic | L8: Lorehold Archivist // Restore Relic | M8: Fun Max | N8: =INDEX(B8:L8,MATCH(M8,$B$5:$L$5,0)) | O8: =IFERROR(VLOOKUP(N8,Prices!$A:$B,2,FALSE),0) | P8: =IFERROR(INDEX('_why_5o'!$B4:$L4,MATCH(M8,$B$5:$L$5,0)),"")
A9: 4 | B9: Augusta, Order Returned | C9: Augusta, Order Returned | D9: Augusta, Order Returned | E9: Augusta, Order Returned | F9: Augusta, Order Returned | G9: Augusta, Order Returned | H9: Augusta, Order Returned | I9: Augusta, Order Returned | J9: Augusta, Order Returned | K9: Augusta, Order Returned | L9: Augusta, Order Returned | M9: Fun Max | N9: =INDEX(B9:L9,MATCH(M9,$B$5:$L$5,0)) | O9: =IFERROR(VLOOKUP(N9,Prices!$A:$B,2,FALSE),0) | P9: =IFERROR(INDEX('_why_5o'!$B5:$L5,MATCH(M9,$B$5:$L$5,0)),"")
A10: 5 | B10: Ceaseless Conflict | C10: Ceaseless Conflict | D10: Ceaseless Conflict | E10: Ceaseless Conflict | F10: Cloud's Limit Break | G10: Cloud's Limit Break | H10: Cloud's Limit Break | I10: Season of the Burrow | J10: Ceaseless Conflict | K10: Venat, Heart of Hydaelyn // Hydaelyn, the Mothercrystal | L10: Venat, Heart of Hydaelyn // Hydaelyn, the Mothercrystal | M10: Fun Max | N10: =INDEX(B10:L10,MATCH(M10,$B$5:$L$5,0)) | O10: =IFERROR(VLOOKUP(N10,Prices!$A:$B,2,FALSE),0) | P10: =IFERROR(INDEX('_why_5o'!$B6:$L6,MATCH(M10,$B$5:$L$5,0)),"")
A11: 6 | B11: Vanguard of the Restless | C11: Vanguard of the Restless | D11: Vanguard of the Restless | E11: Vanguard of the Restless | F11: Vanguard of the Restless | G11: Vanguard of the Restless | H11: Vanguard of the Restless | I11: Vanguard of the Restless | J11: Vanguard of the Restless | K11: Vanguard of the Restless | L11: Vanguard of the Restless | M11: Fun Max | N11: =INDEX(B11:L11,MATCH(M11,$B$5:$L$5,0)) | O11: =IFERROR(VLOOKUP(N11,Prices!$A:$B,2,FALSE),0) | P11: =IFERROR(INDEX('_why_5o'!$B7:$L7,MATCH(M11,$B$5:$L$5,0)),"")
A12: 7 | B12: Advanced Reconstruction | C12: Portable Hole | D12: Portable Hole | E12: Portable Hole | F12: Cast Out | G12: Cast Out | H12: Cast Out | I12: Venat, Heart of Hydaelyn // Hydaelyn, the Mothercrystal | J12: Pyroblast | K12: Pyroblast | L12: Pyroblast | M12: Fun Max | N12: =INDEX(B12:L12,MATCH(M12,$B$5:$L$5,0)) | O12: =IFERROR(VLOOKUP(N12,Prices!$A:$B,2,FALSE),0) | P12: =IFERROR(INDEX('_why_5o'!$B8:$L8,MATCH(M12,$B$5:$L$5,0)),"")
A13: 8 | B13: Fateful Tempest | C13: Knight of the White Orchid | D13: Bag of Holding | E13: Knight of the White Orchid | F13: Sunforger | G13: Sunforger | H13: Sunforger | I13: Pyroblast | J13: Cathar Commando | K13: Boros Charm | L13: Éowyn, Fearless Knight | M13: Fun Max | N13: =INDEX(B13:L13,MATCH(M13,$B$5:$L$5,0)) | O13: =IFERROR(VLOOKUP(N13,Prices!$A:$B,2,FALSE),0) | P13: =IFERROR(INDEX('_why_5o'!$B9:$L9,MATCH(M13,$B$5:$L$5,0)),"")
A14: 9 | B14: Naktamun Lorespinner // Wheel of Fortune | C14: Naktamun Lorespinner // Wheel of Fortune | D14: Naktamun Lorespinner // Wheel of Fortune | E14: Naktamun Lorespinner // Wheel of Fortune | F14: Naktamun Lorespinner // Wheel of Fortune | G14: Naktamun Lorespinner // Wheel of Fortune | H14: Naktamun Lorespinner // Wheel of Fortune | I14: Boros Charm | J14: Naktamun Lorespinner // Wheel of Fortune | K14: Naktamun Lorespinner // Wheel of Fortune | L14: Naktamun Lorespinner // Wheel of Fortune | M14: Fun Max | N14: =INDEX(B14:L14,MATCH(M14,$B$5:$L$5,0)) | O14: =IFERROR(VLOOKUP(N14,Prices!$A:$B,2,FALSE),0) | P14: =IFERROR(INDEX('_why_5o'!$B10:$L10,MATCH(M14,$B$5:$L$5,0)),"")
A15: 10 | B15: Relic Retriever | C15: Relic Retriever | D15: Relic Retriever | E15: Relic Retriever | F15: Relic Retriever | G15: Relic Retriever | H15: Relic Retriever | I15: Relic Retriever | J15: Relic Retriever | K15: Relic Retriever | L15: Relic Retriever | M15: Fun Max | N15: =INDEX(B15:L15,MATCH(M15,$B$5:$L$5,0)) | O15: =IFERROR(VLOOKUP(N15,Prices!$A:$B,2,FALSE),0) | P15: =IFERROR(INDEX('_why_5o'!$B11:$L11,MATCH(M15,$B$5:$L$5,0)),"")
A16: 11 | B16: Spirit of Resilience | C16: Spirit of Resilience | D16: Spirit of Resilience | E16: Spirit of Resilience | F16: Spirit of Resilience | G16: Spirit of Resilience | H16: Spirit of Resilience | I16: Spirit of Resilience | J16: Spirit of Resilience | K16: Spirit of Resilience | L16: Spirit of Resilience | M16: Fun Max | N16: =INDEX(B16:L16,MATCH(M16,$B$5:$L$5,0)) | O16: =IFERROR(VLOOKUP(N16,Prices!$A:$B,2,FALSE),0) | P16: =IFERROR(INDEX('_why_5o'!$B12:$L12,MATCH(M16,$B$5:$L$5,0)),"")
A17: 12 | B17: Turbulent Steppe | C17: Turbulent Steppe | D17: Turbulent Steppe | E17: Turbulent Steppe | F17: Turbulent Steppe | G17: Turbulent Steppe | H17: Turbulent Steppe | I17: Turbulent Steppe | J17: Turbulent Steppe | K17: Turbulent Steppe | L17: Turbulent Steppe | M17: Fun Max | N17: =INDEX(B17:L17,MATCH(M17,$B$5:$L$5,0)) | O17: =IFERROR(VLOOKUP(N17,Prices!$A:$B,2,FALSE),0) | P17: =IFERROR(INDEX('_why_5o'!$B13:$L13,MATCH(M17,$B$5:$L$5,0)),"")
... A105: 100 | B105: Mountain | C105: Mountain | D105: Mountain | E105: Mountain | F105: Mountain | G105: Mountain | H105: Mountain | I105: Mountain | J105: Mountain | K105: Mountain | L105: Mountain | M105: Fun Max | N105: =INDEX(B105:L105,MATCH(M105,$B$5:$L$5,0)) | O105: =IFERROR(VLOOKUP(N105,Prices!$A:$B,2,FALSE),0) | P105: =IFERROR(INDEX('_why_5o'!$B101:$L101,MATCH(M105,$B$5:$L$5,0)),"")
A106: TOTALS | B106: 66.21 | C106: 79.05 | D106: 87.93 | E106: 163.87 | F106: 112.44 | G106: 112.44 | H106: 173.36 | I106: 93.19 | J106: 157.37 | K106: 104.6 | L106: 227.72 | N106: Your selection → | O106: =SUM(O6:O105)
A108: Every row defaults to Fun Max — the newest engine, the full ceiling, and the same commander you already chose. It is a starting point, not a recommendation: change any row. Adopting an Alt column is a commander swap, so it is deliberately never the default; read the Summary tab's alternative-commander block first. Card totals are the full retail value of every card in that column, not what you still need to buy. Amber text marks a card that differs from Base.

Sheet _why_5o
B1: Base | C1: Tuned | D1: Enhance | E1: Max | F1: Tuned-2 | G1: Enhance-2 | H1: Max-2 | I1: Fun Tuned | J1: Fun Max | K1: Alt Tuned | L1: Alt Max
A2: 1
A3: 2 | I3: Replaces Ceaseless Conflict (adds removal/wipe). Evidence: the card it replaces was cast in 81% of the games it was drawn; sat dead in hand 19% of the time; landed on turn 6.9 on average; the deck won 4% of games it was cast in. | J3: Replaces Wave of Reckoning (adds draw/removal/protection/threat). Evidence: the card it replaces was cast in 76% of the games it was drawn; sat dead in hand 24% of the time; landed on turn 8.8 on average; the deck won 18% of games it was cast in. | K3: Replaces Ceaseless Conflict (adds removal/wipe). Evidence: the card it replaces was cast in 47% of the games it was drawn; sat dead in hand 53% of the time; landed on turn 7.9 on average; the deck won 6% of games it was cast in. | L3: Replaces Ceaseless Conflict (adds removal/wipe). Evidence: the card it replaces was cast in 48% of the games it was drawn; sat dead in hand 52% of the time; landed on turn 7.9 on average; the deck won 8% of games it was cast in.
A4: 3
A5: 4
A6: 5 | F6: Replaces Ceaseless Conflict (adds removal/wipe). Evidence: the card it replaces was cast in 82% of the games it was drawn; sat dead in hand 18% of the time; landed on turn 7.2 on average; the deck won 6% of games it was cast in. | I6: Replaces Wave of Reckoning (adds removal/protection). Evidence: the card it replaces was cast in 76% of the games it was drawn; sat dead in hand 24% of the time; landed on turn 8.8 on average; the deck won 20% of games it was cast in. | K6: Replaces Wave of Reckoning (adds draw/removal/protection/threat). Evidence: the card it replaces was cast in 70% of the games it was drawn; sat dead in hand 30% of the time; landed on turn 9.1 on average; the deck won 39% of games it was cast in. | L6: Replaces Wave of Reckoning (adds draw/removal/protection/threat). Evidence: the card it replaces was cast in 70% of the games it was drawn; sat dead in hand 30% of the time; landed on turn 9.0 on average; the deck won 40% of games it was cast in.
A7: 6
A8: 7 | I8: Replaces Naktamun Lorespinner // Wheel of Fortune (adds draw/removal/protection/threat). Evidence: the card it replaces was cast in 85% of the games it was drawn; sat dead in hand 15% of the time; landed on turn 7.9 on average; the deck won 23% of games it was cast in. | J8: Replaces Archaeomancer's Map (adds removal/protection). Evidence: the card it replaces was cast in 86% of the games it was drawn; sat dead in hand 14% of the time; landed on turn 8.0 on average; the deck won 15% of games it was cast in. | K8: Replaces Archaeomancer's Map (adds removal/protection). Evidence: the card it replaces was cast in 84% of the games it was drawn; sat dead in hand 16% of the time; landed on turn 8.0 on average; the deck won 39% of games it was cast in. | L8: Replaces Archaeomancer's Map (adds removal/protection). Evidence: the card it replaces was cast in 82% of the games it was drawn; sat dead in hand 18% of the time; landed on turn 8.1 on average; the deck won 40% of games it was cast in.
A9: 8 | I9: Replaces Archaeomancer's Map (adds removal/protection). Evidence: the card it replaces was cast in 87% of the games it was drawn; sat dead in hand 13% of the time; landed on turn 7.9 on average; the deck won 17% of games it was cast in. | J9: Replaces Sevinne's Reclamation (adds removal/threat). Evidence: the card it replaces was cast in 87% of the games it was drawn; sat dead in hand 13% of the time; landed on turn 7.8 on average; the deck won 18% of games it was cast in. | K9: Replaces Sevinne's Reclamation (adds removal/protection). Evidence: the card it replaces was cast in 80% of the games it was drawn; sat dead in hand 20% of the time; landed on turn 8.1 on average; the deck won 38% of games it was cast in. | L9: Replaces Sevinne's Reclamation (adds removal/protection/threat). Evidence: the card it replaces was cast in 84% of the games it was drawn; sat dead in hand 16% of the time; landed on turn 7.9 on average; the deck won 39% of games it was cast in.
A10: 9 | I10: Replaces Sevinne's Reclamation (adds removal/protection). Evidence: the card it replaces was cast in 84% of the games it was drawn; sat dead in hand 16% of the time; landed on turn 7.8 on average; the deck won 17% of games it was cast in.
A11: 10
A12: 11
A13: 12
A14: 13
A15: 14
A16: 15 | F16: Replaces Wave of Reckoning (adds removal/protection/threat). Evidence: the card it replaces was cast in 82% of the games it was drawn; sat dead in hand 18% of the time; landed on turn 9.3 on average; the deck won 37% of games it was cast in. | I16: Replaces Sun Titan (adds removal/protection/threat). Evidence: the card it replaces was cast in 84% of the games it was drawn; sat dead in hand 16% of the time; landed on turn 7.8 on average; the deck won 21% of games it was cast in. | K16: Replaces Skyclave Apparition (adds removal/protection/threat). Evidence: the card it replaces was cast in 88% of the games it was drawn; sat dead in hand 12% of the time; landed on turn 6.9 on average; the deck won 38% of games it was cast in. | L16: Replaces Tragic Arrogance (adds wipe/protection). Evidence: the card it replaces was cast in 49% of the games it was drawn; sat dead in hand 51% of the time; landed on turn 7.7 on average; the deck won 7% of games it was cast in.
A17: 16
A18: 17
A19: 18 | I19: Replaces Elspeth, Sun's Champion (adds removal/protection). Evidence: the card it replaces was cast in 94% of the games it was drawn; sat dead in hand 6% of the time; landed on turn 7.4 on average; the deck won 13% of games it was cast in. | K19: Replaces Elspeth, Sun's Champion (adds removal/protection). Evidence: the card it replaces was cast in 93% of the games it was drawn; sat dead in hand 7% of the time; landed on turn 7.5 on average; the deck won 34% of games it was cast in.
A20: 19
A21: 20
A22: 21
A23: 22
A24: 23
A25: 24
A26: 25 | F26: Replaces Elspeth, Sun's Champion (adds removal/protection). Evidence: the card it replaces was cast in 97% of the games it was drawn; sat dead in hand 3% of the time; landed on turn 7.8 on average; the deck won 28% of games it was cast in.
A27: 26
A28: 27
A29: 28
A30: 29 | F30: Replaces Sevinne's Reclamation (adds draw/removal/protection/threat). Evidence: the card it replaces was cast in 89% of the games it was drawn; sat dead in hand 11% of the time; landed on turn 8.3 on average; the deck won 34% of games it was cast in. | J30: Replaces Darksteel Plate (adds protection/threat). Evidence: the card it replaces was cast in 90% of the games it was drawn; sat dead in hand 10% of the time; landed on turn 7.7 on average; the deck won 16% of games it was cast in.
A31: 30
A32: 31
A33: 32
A34: 33 | F34: Replaces Tragic Arrogance (adds draw/removal/wipe). Evidence: the card it replaces was cast in 83% of the games it was drawn; sat dead in hand 17% of the time; landed on turn 7.3 on average; the deck won 7% of games it was cast in. | L34: Replaces Darksteel Plate (adds draw/removal/protection). Evidence: the card it replaces was cast in 84% of the games it was drawn; sat dead in hand 16% of the time; landed on turn 7.7 on average; the deck won 42% of games it was cast in.
A35: 34
A36: 35
A37: 36
A38: 37
A39: 38
A40: 39
A41: 40
A42: 41
A43: 42
A44: 43
A45: 44
A46: 45
... A69: 68
A70: 69 | I70: Replaces Tragic Arrogance (adds draw/removal/wipe). Evidence: the card it replaces was cast in 80% of the games it was drawn; sat dead in hand 20% of the time; landed on turn 7.0 on average; the deck won 3% of games it was cast in. | J70: Replaces Farewell (adds removal/protection). Evidence: the card it replaces was cast in 75% of the games it was drawn; sat dead in hand 25% of the time; landed on turn 7.3 on average; the deck won 4% of games it was cast in. | K70: Replaces Tragic Arrogance (adds draw/removal/wipe). Evidence: the card it replaces was cast in 46% of the games it was drawn; sat dead in hand 54% of the time; landed on turn 8.1 on average; the deck won 7% of games it was cast in. | L70: Replaces Farewell (adds removal/protection). Evidence: the card it replaces was cast in 45% of the games it was drawn; sat dead in hand 55% of the time; landed on turn 8.3 on average; the deck won 6% of games it was cast in.
A71: 70
A72: 71
A73: 72
A74: 73
A75: 74
A76: 75
A77: 76
A78: 77
A79: 78
A80: 79 | J80: Replaces Sunforger (adds removal/protection/threat). Evidence: the card it replaces was cast in 88% of the games it was drawn; sat dead in hand 12% of the time; landed on turn 8.1 on average; the deck won 17% of games it was cast in.
A81: 80
A82: 81
A83: 82
A84: 83
A85: 84
A86: 85
A87: 86
A88: 87
A89: 88
A90: 89
A91: 90
A92: 91
... A101: 100

Sheet 6f Sultai ETB Doubling
A1: Sultai ETB Doubling — Yarok, the Desecrated
A2: Deck slot 6 · variant 6f · 100 lineup slots
B4: Site ladder — as published | F4: Simulation-improved (Monte Carlo) | I4: Fun-weighted engine v2.1
A5: Slot | B5: Base | C5: Tuned | D5: Enhance | E5: Max | F5: Tuned-2 | G5: Enhance-2 | H5: Max-2 | I5: Fun Tuned | J5: Fun Max | K5: FINAL PICK | L5: Final card | M5: Price | N5: Why this card moved
A6: 1 | B6: Yarok, the Desecrated | C6: Yarok, the Desecrated | D6: Yarok, the Desecrated | E6: Yarok, the Desecrated | F6: Yarok, the Desecrated | G6: Yarok, the Desecrated | H6: Yarok, the Desecrated | I6: Yarok, the Desecrated | J6: Yarok, the Desecrated | K6: Fun Max | L6: =INDEX(B6:J6,MATCH(K6,$B$5:$J$5,0)) | M6: =IFERROR(VLOOKUP(L6,Prices!$A:$B,2,FALSE),0) | N6: =IFERROR(INDEX('_why_6f'!$B2:$J2,MATCH(K6,$B$5:$J$5,0)),"")
A7: 2 | B7: Island | C7: Island | D7: Island | E7: Island | F7: Island | G7: Island | H7: Island | I7: Island | J7: Island | K7: Fun Max | L7: =INDEX(B7:J7,MATCH(K7,$B$5:$J$5,0)) | M7: =IFERROR(VLOOKUP(L7,Prices!$A:$B,2,FALSE),0) | N7: =IFERROR(INDEX('_why_6f'!$B3:$J3,MATCH(K7,$B$5:$J$5,0)),"")
A8: 3 | B8: Island | C8: Island | D8: Island | E8: Island | F8: Island | G8: Island | H8: Island | I8: Island | J8: Island | K8: Fun Max | L8: =INDEX(B8:J8,MATCH(K8,$B$5:$J$5,0)) | M8: =IFERROR(VLOOKUP(L8,Prices!$A:$B,2,FALSE),0) | N8: =IFERROR(INDEX('_why_6f'!$B4:$J4,MATCH(K8,$B$5:$J$5,0)),"")
A9: 4 | B9: Island | C9: Island | D9: Island | E9: Island | F9: Island | G9: Island | H9: Island | I9: Island | J9: Island | K9: Fun Max | L9: =INDEX(B9:J9,MATCH(K9,$B$5:$J$5,0)) | M9: =IFERROR(VLOOKUP(L9,Prices!$A:$B,2,FALSE),0) | N9: =IFERROR(INDEX('_why_6f'!$B5:$J5,MATCH(K9,$B$5:$J$5,0)),"")
A10: 5 | B10: Island | C10: Island | D10: Island | E10: Island | F10: Island | G10: Island | H10: Island | I10: Island | J10: Island | K10: Fun Max | L10: =INDEX(B10:J10,MATCH(K10,$B$5:$J$5,0)) | M10: =IFERROR(VLOOKUP(L10,Prices!$A:$B,2,FALSE),0) | N10: =IFERROR(INDEX('_why_6f'!$B6:$J6,MATCH(K10,$B$5:$J$5,0)),"")
A11: 6 | B11: Island | C11: Island | D11: Island | E11: Island | F11: Island | G11: Island | H11: Island | I11: Island | J11: Island | K11: Fun Max | L11: =INDEX(B11:J11,MATCH(K11,$B$5:$J$5,0)) | M11: =IFERROR(VLOOKUP(L11,Prices!$A:$B,2,FALSE),0) | N11: =IFERROR(INDEX('_why_6f'!$B7:$J7,MATCH(K11,$B$5:$J$5,0)),"")
A12: 7 | B12: Island | C12: Island | D12: Island | E12: Island | F12: Island | G12: Island | H12: Island | I12: Island | J12: Island | K12: Fun Max | L12: =INDEX(B12:J12,MATCH(K12,$B$5:$J$5,0)) | M12: =IFERROR(VLOOKUP(L12,Prices!$A:$B,2,FALSE),0) | N12: =IFERROR(INDEX('_why_6f'!$B8:$J8,MATCH(K12,$B$5:$J$5,0)),"")
A13: 8 | B13: Island | C13: Island | D13: Island | E13: Island | F13: Island | G13: Island | H13: Island | I13: Island | J13: Island | K13: Fun Max | L13: =INDEX(B13:J13,MATCH(K13,$B$5:$J$5,0)) | M13: =IFERROR(VLOOKUP(L13,Prices!$A:$B,2,FALSE),0) | N13: =IFERROR(INDEX('_why_6f'!$B9:$J9,MATCH(K13,$B$5:$J$5,0)),"")
A14: 9 | B14: Island | C14: Island | D14: Island | E14: Island | F14: Island | G14: Island | H14: Island | I14: Island | J14: Island | K14: Fun Max | L14: =INDEX(B14:J14,MATCH(K14,$B$5:$J$5,0)) | M14: =IFERROR(VLOOKUP(L14,Prices!$A:$B,2,FALSE),0) | N14: =IFERROR(INDEX('_why_6f'!$B10:$J10,MATCH(K14,$B$5:$J$5,0)),"")
A15: 10 | B15: Island | C15: Island | D15: Island | E15: Island | F15: Island | G15: Island | H15: Island | I15: Island | J15: Island | K15: Fun Max | L15: =INDEX(B15:J15,MATCH(K15,$B$5:$J$5,0)) | M15: =IFERROR(VLOOKUP(L15,Prices!$A:$B,2,FALSE),0) | N15: =IFERROR(INDEX('_why_6f'!$B11:$J11,MATCH(K15,$B$5:$J$5,0)),"")
A16: 11 | B16: Island | C16: Island | D16: Island | E16: Island | F16: Island | G16: Island | H16: Island | I16: Island | J16: Island | K16: Fun Max | L16: =INDEX(B16:J16,MATCH(K16,$B$5:$J$5,0)) | M16: =IFERROR(VLOOKUP(L16,Prices!$A:$B,2,FALSE),0) | N16: =IFERROR(INDEX('_why_6f'!$B12:$J12,MATCH(K16,$B$5:$J$5,0)),"")
A17: 12 | B17: Island | C17: Island | D17: Island | E17: Island | F17: Island | G17: Island | H17: Island | I17: Island | J17: Island | K17: Fun Max | L17: =INDEX(B17:J17,MATCH(K17,$B$5:$J$5,0)) | M17: =IFERROR(VLOOKUP(L17,Prices!$A:$B,2,FALSE),0) | N17: =IFERROR(INDEX('_why_6f'!$B13:$J13,MATCH(K17,$B$5:$J$5,0)),"")
... A105: 100 | B105: Deadly Dispute | C105: Deadly Dispute | D105: Deadly Dispute | E105: Deadly Dispute | F105: Deadly Dispute | G105: Deadly Dispute | H105: Deadly Dispute | I105: Deadly Dispute | J105: Deadly Dispute | K105: Fun Max | L105: =INDEX(B105:J105,MATCH(K105,$B$5:$J$5,0)) | M105: =IFERROR(VLOOKUP(L105,Prices!$A:$B,2,FALSE),0) | N105: =IFERROR(INDEX('_why_6f'!$B101:$J101,MATCH(K105,$B$5:$J$5,0)),"")
A106: TOTALS | B106: 91.01 | C106: 179.1 | D106: 179.1 | E106: 328.51 | F106: 240 | G106: 262.04 | H106: 331.37 | I106: 181.21 | J106: 322.98 | L106: Your selection → | M106: =SUM(M6:M105)
A108: Every row defaults to Fun Max — the newest engine, the full ceiling, and the same commander you already chose. It is a starting point, not a recommendation: change any row. Adopting an Alt column is a commander swap, so it is deliberately never the default; read the Summary tab's alternative-commander block first. Card totals are the full retail value of every card in that column, not what you still need to buy. Amber text marks a card that differs from Base.

Sheet _why_6f
B1: Base | C1: Tuned | D1: Enhance | E1: Max | F1: Tuned-2 | G1: Enhance-2 | H1: Max-2 | I1: Fun Tuned | J1: Fun Max
A2: 1
A3: 2
A4: 3
A5: 4
A6: 5
A7: 6
A8: 7
A9: 8
A10: 9
A11: 10
A12: 11
A13: 12
... A38: 37
A39: 38 | F39: Replaces Panharmonicon (adds removal/protection). Evidence: the card it replaces was cast in 86% of the games it was drawn; sat dead in hand 14% of the time; landed on turn 8.7 on average; the deck won 45% of games it was cast in. | I39: Replaces Zendikar's Roil (adds removal/protection). Evidence: the card it replaces was cast in 74% of the games it was drawn; sat dead in hand 26% of the time; landed on turn 9.2 on average; the deck won 35% of games it was cast in. | J39: Replaces Harrow (adds removal/protection). Evidence: the card it replaces was cast in 89% of the games it was drawn; sat dead in hand 11% of the time; landed on turn 6.0 on average; the deck won 36% of games it was cast in.
A40: 39 | I40: Replaces Maelstrom Pulse (adds removal/protection). Evidence: the card it replaces was cast in 85% of the games it was drawn; sat dead in hand 15% of the time; landed on turn 7.7 on average; the deck won 30% of games it was cast in. | J40: Replaces Kodama's Reach (adds removal/protection). Evidence: the card it replaces was cast in 88% of the games it was drawn; sat dead in hand 12% of the time; landed on turn 7.8 on average; the deck won 35% of games it was cast in.
A41: 40 | I41: Replaces Cultivate (adds removal/protection). Evidence: the card it replaces was cast in 87% of the games it was drawn; sat dead in hand 13% of the time; landed on turn 7.9 on average; the deck won 33% of games it was cast in. | J41: Replaces Panharmonicon (adds removal/protection). Evidence: the card it replaces was cast in 83% of the games it was drawn; sat dead in hand 17% of the time; landed on turn 8.3 on average; the deck won 35% of games it was cast in.
A42: 41 | I42: Replaces Kodama's Reach (adds removal/protection). Evidence: the card it replaces was cast in 86% of the games it was drawn; sat dead in hand 14% of the time; landed on turn 7.7 on average; the deck won 34% of games it was cast in.
A43: 42
A44: 43
A45: 44
A46: 45
A47: 46
A48: 47
A49: 48
A50: 49
A51: 50
A52: 51
A53: 52
A54: 53
... A66: 65
A67: 66 | F67: Replaces Putrefy (adds removal/protection/finisher/threat). Evidence: the card it replaces was cast in 86% of the games it was drawn; sat dead in hand 14% of the time; landed on turn 8.7 on average; the deck won 44% of games it was cast in.
A68: 67
A69: 68
A70: 69
A71: 70
A72: 71
A73: 72
A74: 73
A75: 74
A76: 75
A77: 76
A78: 77
A79: 78
... A84: 83
A85: 84 | F85: Replaces Casualties of War (adds removal/protection/finisher/threat). Evidence: the card it replaces was cast in 80% of the games it was drawn; sat dead in hand 20% of the time; landed on turn 9.4 on average; the deck won 47% of games it was cast in.
A86: 85
A87: 86
A88: 87 | F88: Replaces Cultivate (adds removal/protection). Evidence: the card it replaces was cast in 89% of the games it was drawn; sat dead in hand 11% of the time; landed on turn 8.2 on average; the deck won 44% of games it was cast in.
A89: 88
A90: 89
A91: 90
A92: 91
A93: 92 | F93: Replaces Kodama's Reach (adds removal/protection). Evidence: the card it replaces was cast in 88% of the games it was drawn; sat dead in hand 12% of the time; landed on turn 8.0 on average; the deck won 44% of games it was cast in.
A94: 93
A95: 94
A96: 95
A97: 96
A98: 97
A99: 98
A100: 99
A101: 100

Sheet Prices
A1: Card | B1: Price (USD)
A2: Abrupt Decay | B2: 2.43
A3: Access Tunnel | B3: 0.41
A4: Acidic Slime | B4: 0.27
A5: Advanced Reconstruction | B5: 0.35
A6: Aesi, Tyrant of Gyre Strait | B6: 11.26
A7: Aetherflux Reservoir | B7: 19.8
A8: Agent of Treachery | B8: 5.27
A9: Alhammarret's Archive | B9: 10.54
A10: Altar of the Wretched // Wretched Bonemass | B10: 1.49
A11: Ancient Greenwarden | B11: 12.43
A12: Angel of Despair | B12: 1.92
A13: Angel of Indemnity | B13: 0.38
... A667: Éowyn, Fearless Knight | B667: 1.2

Sheet Card Data
A1: Card data for every card referenced in this workbook — resolved across the catalog, the candidate pools and every simulation result.
A2: Card | B2: Type line | C2: Mana cost | D2: Colour identity | E2: Price (USD) | F2: Game Changer | G2: Oracle text
A3: Abrupt Decay | B3: Instant | C3: {B}{G} | D3: BG | E3: 2.43 | G3: This spell can't be countered. / Destroy target nonland permanent with mana value 3 or less.
A4: Access Tunnel | B4: Land | E4: 0.41 | G4: {T}: Add {C}. / {3}, {T}: Target creature with power 3 or less can't be blocked this turn.
A5: Acidic Slime | B5: Creature — Ooze | C5: {3}{G}{G} | D5: G | E5: 0.27 | G5: Deathtouch (Any amount of damage this deals to a creature is enough to destroy it.) / When this creature enters, destroy target artifact, enchantment, or land.
A6: Advanced Reconstruction | B6: Enchantment — Class | C6: {3}{R} | D6: R | E6: 0.35 | G6: (Gain the next level as a sorcery to add its ability.) / At the beginning of your first main phase, mill a card, then exile a card from your graveyard at random. You may play the exiled card this turn. / {1}{R}: Level 2 / Whenever one or more cards leave your graveyard, this Class deals 2 damage to each opponent. / {1}{R}: Level 3 / Spells you cast from anywhere other than your hand cost {2} less to cast.
A7: Aesi, Tyrant of Gyre Strait | B7: Legendary Creature — Serpent | C7: {4}{G}{U} | D7: GU | E7: 11.26 | G7: You may play an additional land on each of your turns. / Landfall — Whenever a land you control enters, you may draw a card.
A8: Agent of Treachery | B8: Creature — Human Rogue | C8: {5}{U}{U} | D8: U | E8: 5.27 | G8: When this creature enters, gain control of target permanent. / At the beginning of your end step, if you control three or more permanents you don't own, draw three cards.
A9: Altar of the Wretched // Wretched Bonemass | B9: Artifact // Creature — Skeleton Horror | C9: {2}{B} | D9: B | E9: 1.49 | G9: When this artifact enters, you may sacrifice a nontoken creature. If you do, draw X cards, then mill X cards, where X is that creature's power. / Craft with one or more creatures {2}{B}{B} / {2}{B}: Return this card from your graveyard to your hand. // Wretched Bonemass's power and toughness are each equal to the total power of the exiled cards used to craft it. / This creature has flying as long as an exiled card used to craft it has flying. The same is true for first strike, double strike, deathtouch, haste, hexproof, indestructible, lifelink, menace, protection, reach, trample, and vigilance.
A10: Angel of Indemnity | B10: Creature — Angel Warrior | C10: {5}{W} | D10: W | E10: 0.38 | G10: Flying, lifelink / When this creature enters, return target permanent card with mana value 4 or less from your graveyard to the battlefield. / Encore {6}{W}{W} ({6}{W}{W}, Exile this card from your graveyard: For each opponent, create a token copy that attacks that opponent this turn if able. They gain haste. Sacrifice them at the beginning of the next end step. Activate only as a sorcery.)
A11: Angelic Wall | B11: Creature — Wall | C11: {1}{W} | D11: W | E11: 0.18 | G11: Defender (This creature can't attack.) / Flying
A12: Anger | B12: Creature — Incarnation | C12: {3}{R} | D12: R | E12: 0.6 | G12: Haste / As long as this card is in your graveyard and you control a Mountain, creatures you control have haste.
A13: Anguished Unmaking | B13: Instant | C13: {1}{W}{B} | D13: BW | E13: 1.41 | G13: Exile target nonland permanent. You lose 3 life.
A14: Ao, the Dawn Sky | B14: Legendary Creature — Dragon Spirit | C14: {3}{W}{W} | D14: W | E14: 0.31 | G14: Flying, vigilance / When Ao dies, choose one — / • Look at the top seven cards of your library. Put any number of nonland permanent cards with total mana value 4 or less from among them onto the battlefield. Put the rest on the bottom of your library in a random order. / • Put two +1/+1 counters on each permanent you control that's a creature or Vehicle.
A15: Arasta of the Endless Web | B15: Legendary Enchantment Creature — Spider | C15: {2}{G}{G} | D15: G | E15: 0.38 | G15: Reach / Whenever an opponent casts an instant or sorcery spell, create a 1/2 green Spider creature token with reach.
A16: Arbor Adherent | B16: Creature — Dog Druid | C16: {3}{G} | D16: G | E16: 1.55 | G16: {T}: Add one mana of any color. / {T}: Add X mana of any one color, where X is the greatest toughness among other creatures you control.
... A18: Arcades, the Strategist | B18: Legendary Creature — Elder Dragon | C18: {1}{G}{W}{U} | D18: GUW | E18: 4.81 | G18: Flying, vigilance / Whenever a creature you control with defender enters, draw a card. / Each creature you control with defender assigns combat damage equal to its toughness rather than its power and can attack as though it didn't have defender.
A19: Arcane Sanctum | B19: Land | D19: BUW | E19: 0.48 | G19: This land enters tapped. / {T}: Add {W}, {U}, or {B}.
A20: Arcane Signet | B20: Artifact | C20: {2} | E20: 0.52 | G20: {T}: Add one mana of any color in your commander's color identity.
A21: Archaeomancer's Map | B21: Artifact | C21: {2}{W} | D21: W | E21: 1.2 | G21: When this artifact enters, search your library for up to two basic Plains cards, reveal them, put them into your hand, then shuffle. / Whenever a land an opponent controls enters, if that player controls more lands than you, you may put a land card from your hand onto the battlefield.
A22: Archfiend of Ifnir | B22: Creature — Demon | C22: {3}{B}{B} | D22: B | E22: 0.38 | G22: Flying / Whenever you cycle or discard another card, put a -1/-1 counter on each creature your opponents control. / Cycling {2} ({2}, Discard this card: Draw a card.)
A23: Assassin's Trophy | B23: Instant | C23: {B}{G} | D23: BG | E23: 0.99 | G23: Destroy target permanent an opponent controls. Its controller may search their library for a basic land card, put it onto the battlefield, then shuffle.
A24: Assault Formation | B24: Enchantment | C24: {1}{G} | D24: G | E24: 0.35 | G24: Each creature you control assigns combat damage equal to its toughness rather than its power. / {G}: Target creature with defender can attack this turn as though it didn't have defender. / {2}{G}: Creatures you control get +0/+1 until end of turn.
A25: Astral Cornucopia | B25: Artifact | C25: {X}{X}{X} | E25: 0.29 | G25: This artifact enters with X charge counters on it. / {T}: Choose a color. Add one mana of that color for each charge counter on this artifact.
A26: Atraxa, Praetors' Voice | B26: Legendary Creature — Phyrexian Angel Horror | C26: {G}{W}{U}{B} | D26: BGUW | E26: 30.12 | G26: Flying, vigilance, deathtouch, lifelink / At the beginning of your end step, proliferate. (Choose any number of permanents and/or players, then give each another counter of each kind already there.)
A27: Atsushi, the Blazing Sky | B27: Legendary Creature — Dragon Spirit | C27: {2}{R}{R} | D27: R | E27: 0.38 | G27: Flying, trample / When Atsushi dies, choose one — / • Exile the top two cards of your library. Until the end of your next turn, you may play those cards. / • Create three Treasure tokens.
A28: Augusta, Order Returned | B28: Legendary Creature — Spirit Advisor | C28: {2}{W} | D28: W | E28: 0.2 | G28: Flying, vigilance / Whenever Augusta attacks, each player exiles a card from their graveyard. When one or more nonland cards are exiled this way, put that many +1/+1 counters on target attacking creature.
A29: Austere Command | B29: Sorcery | C29: {4}{W}{W} | D29: W | E29: 0.4 | G29: Choose two — / • Destroy all artifacts. / • Destroy all enchantments. / • Destroy all creatures with mana value 3 or less. / • Destroy all creatures with mana value 4 or greater.
A30: Authority of the Consuls | B30: Enchantment | C30: {W} | D30: W | E30: 4.41 | G30: Creatures your opponents control enter tapped. / Whenever a creature an opponent controls enters, you gain 1 life.
A31: Avenger of Zendikar | B31: Creature — Elemental | C31: {5}{G}{G} | D31: G | E31: 0.39 | G31: When this creature enters, create a 0/1 green Plant creature token for each land you control. / Landfall — Whenever a land you control enters, you may put a +1/+1 counter on each Plant creature you control.
A32: Axebane Guardian | B32: Creature — Human Druid | C32: {2}{G} | D32: G | E32: 0.28 | G32: Defender / {T}: Add X mana in any combination of colors, where X is the number of creatures you control with defender.
A33: Azorius Chancery | B33: Land | D33: UW | E33: 0.35 | G33: This land enters tapped. / When this land enters, return a land you control to its owner's hand. / {T}: Add {W}{U}.
A34: Bag of Holding | B34: Artifact | C34: {1} | E34: 0.34 | G34: Whenever you discard a card, exile that card from your graveyard. / {2}, {T}: Draw a card, then discard a card. / {4}, {T}, Sacrifice this artifact: Return all cards exiled with this artifact to their owner's hand.
A35: Baldin, Century Herdmaster | B35: Legendary Creature — Human Warrior | C35: {4}{W}{W} | D35: W | E35: 0.38 | G35: During your turn, each creature assigns combat damage equal to its toughness rather than its power. / Whenever Baldin attacks, up to one hundred target creatures each get +0/+X until end of turn, where X is the number of cards in your hand.
A36: Balefire Liege | B36: Creature — Spirit Horror | C36: {2}{R/W}{R/W}{R/W} | D36: RW | E36: 0.33 | G36: Other red creatures you control get +1/+1. / Other white creatures you control get +1/+1. / Whenever you cast a red spell, this creature deals 3 damage to target player or planeswalker. / Whenever you cast a white spell, you gain 3 life.
A37: Bant Charm | B37: Instant | C37: {G}{W}{U} | D37: GUW | E37: 0.32 | G37: Choose one — / • Destroy target artifact. / • Put target creature on the bottom of its owner's library. / • Counter target instant spell.
A38: Bant Panorama | B38: Land | E38: 0.33 | G38: {T}: Add {C}. / {1}, {T}, Sacrifice this land: Search your library for a basic Forest, Plains, or Island card, put it onto the battlefield tapped, then shuffle.
A39: Barren Moor | B39: Land | D39: B | E39: 0.27 | G39: This land enters tapped. / {T}: Add {B}. / Cycling {B} ({B}, Discard this card: Draw a card.)
A40: Battlefield Forge | B40: Land | D40: RW | E40: 0.39 | G40: {T}: Add {C}. / {T}: Add {R} or {W}. This land deals 1 damage to you.
A41: Bedrock Tortoise | B41: Creature — Turtle | C41: {3}{G} | D41: G | E41: 2.02 | G41: During your turn, creatures you control have hexproof. / Each creature you control with toughness greater than its power assigns combat damage equal to its toughness rather than its power.
A42: Behind the Scenes | B42: Enchantment | C42: {2}{B} | D42: BW | E42: 0.23 | G42: Creatures you control have skulk. (They can't be blocked by creatures with greater power.) / {4}{W}: Creatures you control get +1/+1 until end of turn.
A43: Betor, Ancestor's Voice | B43: Legendary Creature — Spirit Dragon | C43: {2}{W}{B}{G} | D43: BGW | E43: 3.56 | G43: Flying, lifelink / At the beginning of your end step, put a number of +1/+1 counters on up to one other target creature you control equal to the amount of life you gained this turn. Return up to one target creature card with mana value less than or equal to the amount of life you lost this turn from your graveyard to the battlefield.
A44: Betor, Kin to All | B44: Legendary Creature — Spirit Dragon | C44: {2}{W}{B}{G} | D44: BGW | E44: 5.23 | G44: Flying / At the beginning of your end step, if creatures you control have total toughness 10 or greater, draw a card. Then if creatures you control have total toughness 20 or greater, untap each creature you control. Then if creatures you control have total toughness 40 or greater, each opponent loses half their life, rounded up.
A45: Bitterthorn, Nissa's Animus | B45: Legendary Artifact — Equipment | C45: {3} | E45: 5.78 | G45: Living weapon (When this Equipment enters, create a 0/0 black Phyrexian Germ creature token, then attach this to it.) / Equipped creature gets +1/+1. / Whenever equipped creature attacks, you may search your library for a basic land card, put it onto the battlefield tapped, then shuffle. / Equip {3}
A46: Blast Zone | B46: Land | E46: 0.38 | G46: This land enters with a charge counter on it. / {T}: Add {C}. / {X}{X}, {T}: Put X charge counters on this land. / {3}, {T}, Sacrifice this land: Destroy each nonland permanent with mana value equal to the number of charge counters on this land.
A47: Blight Pile | B47: Creature — Phyrexian | C47: {1}{B} | D47: B | E47: 0.24 | G47: Defender / {2}{B}, {T}: Each opponent loses X life, where X is the number of creatures with defender you control.
A48: Blighted Woodland | B48: Land | D48: G | E48: 0.39 | G48: {T}: Add {C}. / {3}{G}, {T}, Sacrifice this land: Search your library for up to two basic land cards, put them onto the battlefield tapped, then shuffle.
A49: Blood Artist | B49: Creature — Vampire | C49: {1}{B} | D49: B | E49: 3.37 | G49: Whenever this creature or another creature dies, target player loses 1 life and you gain 1 life.
A50: Bloodchief's Thirst | B50: Sorcery | C50: {B} | D50: B | E50: 0.23 | G50: Kicker {2}{B} (You may pay an additional {2}{B} as you cast this spell.) / Destroy target creature or planeswalker with mana value 2 or less. If this spell was kicked, instead destroy target creature or planeswalker.
A51: Blossoming Sands | B51: Land | D51: GW | E51: 0.19 | G51: This land enters tapped. / When this land enters, you gain 1 life. / {T}: Add {G} or {W}.
A52: Bojuka Bog | B52: Land | D52: B | E52: 1.4 | G52: This land enters tapped. / When this land enters, exile target player's graveyard. / {T}: Add {B}.
A53: Bone Shards | B53: Sorcery | C53: {B} | D53: B | E53: 0.3 | G53: As an additional cost to cast this spell, sacrifice a creature or discard a card. / Destroy target creature or planeswalker.
A54: Boros Charm | B54: Instant | C54: {R}{W} | D54: RW | E54: 4.4 | G54: Choose one — / • Boros Charm deals 4 damage to target player or planeswalker. / • Permanents you control gain indestructible until end of turn. / • Target creature gains double strike until end of turn.
A55: Branching Evolution | B55: Enchantment | C55: {2}{G} | D55: G | E55: 7.44 | G55: If one or more +1/+1 counters would be put on a creature you control, twice that many +1/+1 counters are put on that creature instead.
A56: Burnished Hart | B56: Artifact Creature — Elk | C56: {3} | E56: 0.27 | G56: {3}, Sacrifice this creature: Search your library for up to two basic land cards, put them onto the battlefield tapped, then shuffle.
A57: Canopy Gargantuan | B57: Creature — Dragon | C57: {5}{G}{G} | D57: G | E57: 3.25 | G57: Flying, ward {2} / At the beginning of your upkeep, put a number of +1/+1 counters on each other creature you control equal to that creature's toughness.
A58: Canopy Vista | B58: Land — Forest Plains | D58: GW | E58: 0.34 | G58: ({T}: Add {G} or {W}.) / This land enters tapped unless you control two or more basic lands.
A59: Carven Caryatid | B59: Creature — Spirit | C59: {1}{G}{G} | D59: G | E59: 0.25 | G59: Defender (This creature can't attack.) / When this creature enters, draw a card.
A60: Cast Down | B60: Instant | C60: {1}{B} | D60: B | E60: 0.35 | G60: Destroy target nonlegendary creature.
A61: Cast Out | B61: Enchantment | C61: {3}{W} | D61: W | E61: 0.28 | G61: Flash / When this enchantment enters, exile target nonland permanent an opponent controls until this enchantment leaves the battlefield. / Cycling {W} ({W}, Discard this card: Draw a card.)
A62: Casualties of War | B62: Sorcery | C62: {2}{B}{B}{G}{G} | D62: BG | E62: 0.33 | G62: Choose one or more — / • Destroy target artifact. / • Destroy target creature. / • Destroy target enchantment. / • Destroy target land. / • Destroy target planeswalker.
A63: Cathar Commando | B63: Creature — Human Soldier | C63: {1}{W} | D63: W | E63: 0.19 | G63: Flash / {1}, Sacrifice this creature: Destroy target artifact or enchantment.
A64: Ceaseless Conflict | B64: Sorcery | C64: {3}{W}{W} | D64: W | E64: 0.24 | G64: Destroy all creatures. Then create a 3/2 red and white Spirit creature token for each nontoken creature you controlled that was destroyed this way.
A65: Charming Prince | B65: Creature — Human Noble | C65: {1}{W} | D65: W | E65: 0.38 | G65: When this creature enters, choose one — / • Scry 2. / • You gain 3 life. / • Exile another target creature you own. Return it to the battlefield under your control at the beginning of the next end step.
A66: Chromatic Lantern | B66: Artifact | C66: {3} | E66: 0.9 | G66: Lands you control have "{T}: Add one mana of any color." / {T}: Add one mana of any color.
A67: Claim Jumper | B67: Creature — Rabbit Mercenary | C67: {2}{W} | D67: W | E67: 0.37 | G67: Vigilance / When this creature enters, if an opponent controls more lands than you, you may search your library for a Plains card and put it onto the battlefield tapped. Then if an opponent controls more lands than you, repeat this process once. If you search your library this way, shuffle.
A68: Clifftop Retreat | B68: Land | D68: RW | E68: 0.33 | G68: This land enters tapped unless you control a Mountain or a Plains. / {T}: Add {R} or {W}.
A69: Cloud's Limit Break | B69: Instant | C69: {1}{W} | D69: W | E69: 0.28 | G69: Tiered (Choose one additional cost.) / • Cross-Slash — {0} — Destroy target tapped creature. / • Blade Beam — {1} — Destroy any number of target tapped creatures with different controllers. / • Omnislash — {3}{W} — Destroy all tapped creatures.
A70: Cloudblazer | B70: Creature — Human Scout | C70: {3}{W}{U} | D70: UW | E70: 0.11 | G70: Flying / When this creature enters, you gain 2 life and draw two cards.
A71: Cloudstone Curio | B71: Artifact | C71: {3} | E71: 16.92 | G71: Whenever a nonartifact permanent you control enters, you may return another permanent you control that shares a permanent type with it to its owner's hand.
A72: Coldsteel Heart | B72: Snow Artifact | C72: {2} | E72: 1.72 | G72: This artifact enters tapped. / As this artifact enters, choose a color. / {T}: Add one mana of the chosen color.
A73: Colfenor's Urn | B73: Artifact | C73: {3} | E73: 0.29 | G73: Whenever a creature with toughness 4 or greater is put into your graveyard from the battlefield, you may exile it. / At the beginning of the end step, if three or more cards have been exiled with this artifact, sacrifice it. If you do, return those cards to the battlefield under their owner's control.
A74: Collective Resistance | B74: Instant | C74: {1}{G} | D74: G | E74: 2.04 | G74: Escalate {G} (Pay this cost for each mode chosen beyond the first.) / Choose one or more — / • Destroy target artifact. / • Destroy target enchantment. / • Target creature gains hexproof and indestructible until end of turn.
A75: Colossus of Akros | B75: Artifact Creature — Golem | C75: {8} | E75: 1.78 | G75: Defender, indestructible / {10}: Monstrosity 10. (If this creature isn't monstrous, put ten +1/+1 counters on it and it becomes monstrous.) / As long as this creature is monstrous, it has trample and can attack as though it didn't have defender.
A76: Command Tower | B76: Land | E76: 0.39 | G76: {T}: Add one mana of any color in your commander's color identity.
A77: Conclave Mentor | B77: Creature — Centaur Cleric | C77: {G}{W} | D77: GW | E77: 0.72 | G77: If one or more +1/+1 counters would be put on a creature you control, that many plus one +1/+1 counters are put on that creature instead. / When this creature dies, you gain life equal to its power.
A78: Consecrated Sphinx | B78: Creature — Sphinx | C78: {4}{U}{U} | D78: U | E78: 30.55 | G78: Flying / Whenever an opponent draws a card, you may draw two cards.
A79: Conspiracy Theorist | B79: Creature — Human Shaman | C79: {1}{R} | D79: R | E79: 0.32 | G79: Whenever this creature attacks, you may pay {1} and discard a card. If you do, draw a card. / Whenever you discard one or more nonland cards, you may exile one of them from your graveyard. If you do, you may cast it this turn.
A80: Contagion Clasp | B80: Artifact | C80: {2} | E80: 0.37 | G80: When this artifact enters, put a -1/-1 counter on target creature. / {4}, {T}: Proliferate. (Choose any number of permanents and/or players, then give each another counter of each kind already there.)
A81: Containment Construct | B81: Artifact Creature — Construct | C81: {2} | E81: 0.26 | G81: Whenever you discard a card, you may exile that card from your graveyard. If you do, you may play that card this turn.
A82: Contentious Plan | B82: Sorcery | C82: {1}{U} | D82: U | E82: 0.34 | G82: Proliferate. (Choose any number of permanents and/or players, then give each another counter of each kind already there.) / Draw a card.
A83: Corpsejack Menace | B83: Creature — Fungus | C83: {2}{B}{G} | D83: BG | E83: 0.91 | G83: If one or more +1/+1 counters would be put on a creature you control, twice that many +1/+1 counters are put on it instead.
A84: Crashing Drawbridge | B84: Artifact Creature — Wall | C84: {2} | E84: 0.77 | G84: Defender / {T}: Creatures you control gain haste until end of turn.
A85: Craterhoof Behemoth | B85: Creature — Beast | C85: {5}{G}{G}{G} | D85: G | E85: 23.51 | G85: Haste / When this creature enters, creatures you control gain trample and get +X/+X until end of turn, where X is the number of creatures you control.
A86: Crop Rotation | B86: Instant | C86: {G} | D86: G | E86: 3.46 | G86: As an additional cost to cast this spell, sacrifice a land. / Search your library for a land card, put that card onto the battlefield, then shuffle.
A87: Crucible of Worlds | B87: Artifact | C87: {3} | E87: 34.97 | G87: You may play lands from your graveyard.
A88: Cryptic Command | B88: Instant | E88: 7.44
A89: Cultivate | B89: Sorcery | C89: {2}{G} | D89: G | E89: 0.42 | G89: Search your library for up to two basic land cards, reveal those cards, put one onto the battlefield tapped and the other into your hand, then shuffle.
A90: Currency Converter | B90: Artifact | C90: {1} | E90: 0.51 | G90: Whenever you discard a card, you may exile that card from your graveyard. / {2}, {T}: Draw a card, then discard a card. / {T}: Put a card exiled with this artifact into its owner's graveyard. If it's a land card, create a Treasure token. If it's a nonland card, create a 2/2 black Rogue creature token.
A91: Dakmor Salvage | B91: Land | D91: B | E91: 0.35 | G91: This land enters tapped. / {T}: Add {B}. / Dredge 2 (If you would draw a card, you may mill two cards instead. If you do, return this card from your graveyard to your hand.)
A92: Damn | B92: Sorcery | C92: {B}{B} | D92: BW | E92: 1.96 | G92: Destroy target creature. A creature destroyed this way can't be regenerated. / Overload {2}{W}{W} (You may cast this spell for its overload cost. If you do, change "target" in its text to "each.")
A93: Darksteel Plate | B93: Artifact — Equipment | C93: {3} | E93: 6.52 | G93: Indestructible / Equipped creature has indestructible. / Equip {2}
A94: Dawn of Hope | B94: Enchantment | C94: {1}{W} | D94: W | E94: 0.48 | G94: Whenever you gain life, you may pay {2}. If you do, draw a card. / {3}{W}: Create a 1/1 white Soldier creature token with lifelink.
A95: Deadeye Navigator | B95: Creature — Spirit | C95: {4}{U}{U} | D95: U | E95: 3.02 | G95: Soulbond (You may pair this creature with another unpaired creature when either enters. They remain paired for as long as you control both of them.) / As long as Deadeye Navigator is paired with another creature, each of those creatures has "{1}{U}: Exile this creature, then return it to the battlefield under your control."
A96: Deadly Dispute | B96: Instant | C96: {1}{B} | D96: B | E96: 0.32 | G96: As an additional cost to cast this spell, sacrifice an artifact or creature. / Draw two cards and create a Treasure token. (It's an artifact with "{T}, Sacrifice this token: Add one mana of any color.")
A97: Deathrite Shaman | B97: Creature — Elf Shaman | C97: {B/G} | D97: BG | E97: 8.33 | G97: {T}: Exile target land card from a graveyard. Add one mana of any color. (Activate only as an instant.) / {B}, {T}: Exile target instant or sorcery card from a graveyard. Each opponent loses 2 life. / {G}, {T}: Exile target creature card from a graveyard. You gain 2 life.
A98: Deceptive Landscape | B98: Land | D98: BGW | E98: 0.2 | G98: {T}: Add {C}. / {T}, Sacrifice this land: Search your library for a basic Plains, Swamp, or Forest card, put it onto the battlefield tapped, then shuffle. / Cycling {W}{B}{G} ({W}{B}{G}, Discard this card: Draw a card.)
A99: Deepglow Skate | B99: Creature — Fish | C99: {4}{U} | D99: U | E99: 0.29 | G99: When this creature enters, double the number of each kind of counter on any number of target permanents.
A100: Despark | B100: Instant | C100: {W}{B} | D100: BW | E100: 0.4 | G100: Exile target permanent with mana value 4 or greater.
A101: Disenchant | B101: Instant | C101: {1}{W} | D101: W | E101: 0.1 | G101: Destroy target artifact or enchantment.
...

Sheet Final List
A1: Final List — hand this tab to the session updating the web app
A2: Live formulas: every row follows the FINAL PICK you set on that deck's sheet. Values update as you choose.
A4: Deck | B4: Variant | C4: Slot | D4: Chosen build | E4: Card | F4: Price
A5: Ancestral Bulwark | B5: 1o | C5: 1 | D5: ='1o Ancestral Bulwark'!M6 | E5: ='1o Ancestral Bulwark'!N6 | F5: ='1o Ancestral Bulwark'!O6
A6: Ancestral Bulwark | B6: 1o | C6: 2 | D6: ='1o Ancestral Bulwark'!M7 | E6: ='1o Ancestral Bulwark'!N7 | F6: ='1o Ancestral Bulwark'!O7
A7: Ancestral Bulwark | B7: 1o | C7: 3 | D7: ='1o Ancestral Bulwark'!M8 | E7: ='1o Ancestral Bulwark'!N8 | F7: ='1o Ancestral Bulwark'!O8
A8: Ancestral Bulwark | B8: 1o | C8: 4 | D8: ='1o Ancestral Bulwark'!M9 | E8: ='1o Ancestral Bulwark'!N9 | F8: ='1o Ancestral Bulwark'!O9
A9: Ancestral Bulwark | B9: 1o | C9: 5 | D9: ='1o Ancestral Bulwark'!M10 | E9: ='1o Ancestral Bulwark'!N10 | F9: ='1o Ancestral Bulwark'!O10
A10: Ancestral Bulwark | B10: 1o | C10: 6 | D10: ='1o Ancestral Bulwark'!M11 | E10: ='1o Ancestral Bulwark'!N11 | F10: ='1o Ancestral Bulwark'!O11
A11: Ancestral Bulwark | B11: 1o | C11: 7 | D11: ='1o Ancestral Bulwark'!M12 | E11: ='1o Ancestral Bulwark'!N12 | F11: ='1o Ancestral Bulwark'!O12
A12: Ancestral Bulwark | B12: 1o | C12: 8 | D12: ='1o Ancestral Bulwark'!M13 | E12: ='1o Ancestral Bulwark'!N13 | F12: ='1o Ancestral Bulwark'!O13
A13: Ancestral Bulwark | B13: 1o | C13: 9 | D13: ='1o Ancestral Bulwark'!M14 | E13: ='1o Ancestral Bulwark'!N14 | F13: ='1o Ancestral Bulwark'!O14
A14: Ancestral Bulwark | B14: 1o | C14: 10 | D14: ='1o Ancestral Bulwark'!M15 | E14: ='1o Ancestral Bulwark'!N15 | F14: ='1o Ancestral Bulwark'!O15
A15: Ancestral Bulwark | B15: 1o | C15: 11 | D15: ='1o Ancestral Bulwark'!M16 | E15: ='1o Ancestral Bulwark'!N16 | F15: ='1o Ancestral Bulwark'!O16
A16: Ancestral Bulwark | B16: 1o | C16: 12 | D16: ='1o Ancestral Bulwark'!M17 | E16: ='1o Ancestral Bulwark'!N17 | F16: ='1o Ancestral Bulwark'!O17
... A104: Ancestral Bulwark | B104: 1o | C104: 100 | D104: ='1o Ancestral Bulwark'!M105 | E104: ='1o Ancestral Bulwark'!N105 | F104: ='1o Ancestral Bulwark'!O105
A105: Proliferate Council | B105: 2c | C105: 1 | D105: ='2c Proliferate Council'!K6 | E105: ='2c Proliferate Council'!L6 | F105: ='2c Proliferate Council'!M6
A106: Proliferate Council | B106: 2c | C106: 2 | D106: ='2c Proliferate Council'!K7 | E106: ='2c Proliferate Council'!L7 | F106: ='2c Proliferate Council'!M7
A107: Proliferate Council | B107: 2c | C107: 3 | D107: ='2c Proliferate Council'!K8 | E107: ='2c Proliferate Council'!L8 | F107: ='2c Proliferate Council'!M8
A108: Proliferate Council | B108: 2c | C108: 4 | D108: ='2c Proliferate Council'!K9 | E108: ='2c Proliferate Council'!L9 | F108: ='2c Proliferate Council'!M9
A109: Proliferate Council | B109: 2c | C109: 5 | D109: ='2c Proliferate Council'!K10 | E109: ='2c Proliferate Council'!L10 | F109: ='2c Proliferate Council'!M10
A110: Proliferate Council | B110: 2c | C110: 6 | D110: ='2c Proliferate Council'!K11 | E110: ='2c Proliferate Council'!L11 | F110: ='2c Proliferate Council'!M11
A111: Proliferate Council | B111: 2c | C111: 7 | D111: ='2c Proliferate Council'!K12 | E111: ='2c Proliferate Council'!L12 | F111: ='2c Proliferate Council'!M12
A112: Proliferate Council | B112: 2c | C112: 8 | D112: ='2c Proliferate Council'!K13 | E112: ='2c Proliferate Council'!L13 | F112: ='2c Proliferate Council'!M13
A113: Proliferate Council | B113: 2c | C113: 9 | D113: ='2c Proliferate Council'!K14 | E113: ='2c Proliferate Council'!L14 | F113: ='2c Proliferate Council'!M14
A114: Proliferate Council | B114: 2c | C114: 10 | D114: ='2c Proliferate Council'!K15 | E114: ='2c Proliferate Council'!L15 | F114: ='2c Proliferate Council'!M15
A115: Proliferate Council | B115: 2c | C115: 11 | D115: ='2c Proliferate Council'!K16 | E115: ='2c Proliferate Council'!L16 | F115: ='2c Proliferate Council'!M16
A116: Proliferate Council | B116: 2c | C116: 12 | D116: ='2c Proliferate Council'!K17 | E116: ='2c Proliferate Council'!L17 | F116: ='2c Proliferate Council'!M17
... A204: Proliferate Council | B204: 2c | C204: 100 | D204: ='2c Proliferate Council'!K105 | E204: ='2c Proliferate Council'!L105 | F204: ='2c Proliferate Council'!M105
A205: Golgari Land Engine | B205: 3e | C205: 1 | D205: ='3e Golgari Land Engine'!M6 | E205: ='3e Golgari Land Engine'!N6 | F205: ='3e Golgari Land Engine'!O6
A206: Golgari Land Engine | B206: 3e | C206: 2 | D206: ='3e Golgari Land Engine'!M7 | E206: ='3e Golgari Land Engine'!N7 | F206: ='3e Golgari Land Engine'!O7
A207: Golgari Land Engine | B207: 3e | C207: 3 | D207: ='3e Golgari Land Engine'!M8 | E207: ='3e Golgari Land Engine'!N8 | F207: ='3e Golgari Land Engine'!O8
A208: Golgari Land Engine | B208: 3e | C208: 4 | D208: ='3e Golgari Land Engine'!M9 | E208: ='3e Golgari Land Engine'!N9 | F208: ='3e Golgari Land Engine'!O9
A209: Golgari Land Engine | B209: 3e | C209: 5 | D209: ='3e Golgari Land Engine'!M10 | E209: ='3e Golgari Land Engine'!N10 | F209: ='3e Golgari Land Engine'!O10
A210: Golgari Land Engine | B210: 3e | C210: 6 | D210: ='3e Golgari Land Engine'!M11 | E210: ='3e Golgari Land Engine'!N11 | F210: ='3e Golgari Land Engine'!O11
A211: Golgari Land Engine | B211: 3e | C211: 7 | D211: ='3e Golgari Land Engine'!M12 | E211: ='3e Golgari Land Engine'!N12 | F211: ='3e Golgari Land Engine'!O12
A212: Golgari Land Engine | B212: 3e | C212: 8 | D212: ='3e Golgari Land Engine'!M13 | E212: ='3e Golgari Land Engine'!N13 | F212: ='3e Golgari Land Engine'!O13
A213: Golgari Land Engine | B213: 3e | C213: 9 | D213: ='3e Golgari Land Engine'!M14 | E213: ='3e Golgari Land Engine'!N14 | F213: ='3e Golgari Land Engine'!O14
A214: Golgari Land Engine | B214: 3e | C214: 10 | D214: ='3e Golgari Land Engine'!M15 | E214: ='3e Golgari Land Engine'!N15 | F214: ='3e Golgari Land Engine'!O15
A215: Golgari Land Engine | B215: 3e | C215: 11 | D215: ='3e Golgari Land Engine'!M16 | E215: ='3e Golgari Land Engine'!N16 | F215: ='3e Golgari Land Engine'!O16
A216: Golgari Land Engine | B216: 3e | C216: 12 | D216: ='3e Golgari Land Engine'!M17 | E216: ='3e Golgari Land Engine'!N17 | F216: ='3e Golgari Land Engine'!O17
... A304: Golgari Land Engine | B304: 3e | C304: 100 | D304: ='3e Golgari Land Engine'!M105 | E304: ='3e Golgari Land Engine'!N105 | F304: ='3e Golgari Land Engine'!O105
A305: Bant Walls | B305: 4c | C305: 1 | D305: ='4c Bant Walls'!K6 | E305: ='4c Bant Walls'!L6 | F305: ='4c Bant Walls'!M6
A306: Bant Walls | B306: 4c | C306: 2 | D306: ='4c Bant Walls'!K7 | E306: ='4c Bant Walls'!L7 | F306: ='4c Bant Walls'!M7
A307: Bant Walls | B307: 4c | C307: 3 | D307: ='4c Bant Walls'!K8 | E307: ='4c Bant Walls'!L8 | F307: ='4c Bant Walls'!M8
A308: Bant Walls | B308: 4c | C308: 4 | D308: ='4c Bant Walls'!K9 | E308: ='4c Bant Walls'!L9 | F308: ='4c Bant Walls'!M9
A309: Bant Walls | B309: 4c | C309: 5 | D309: ='4c Bant Walls'!K10 | E309: ='4c Bant Walls'!L10 | F309: ='4c Bant Walls'!M10
A310: Bant Walls | B310: 4c | C310: 6 | D310: ='4c Bant Walls'!K11 | E310: ='4c Bant Walls'!L11 | F310: ='4c Bant Walls'!M11
A311: Bant Walls | B311: 4c | C311: 7 | D311: ='4c Bant Walls'!K12 | E311: ='4c Bant Walls'!L12 | F311: ='4c Bant Walls'!M12
A312: Bant Walls | B312: 4c | C312: 8 | D312: ='4c Bant Walls'!K13 | E312: ='4c Bant Walls'!L13 | F312: ='4c Bant Walls'!M13
A313: Bant Walls | B313: 4c | C313: 9 | D313: ='4c Bant Walls'!K14 | E313: ='4c Bant Walls'!L14 | F313: ='4c Bant Walls'!M14
A314: Bant Walls | B314: 4c | C314: 10 | D314: ='4c Bant Walls'!K15 | E314: ='4c Bant Walls'!L15 | F314: ='4c Bant Walls'!M15
A315: Bant Walls | B315: 4c | C315: 11 | D315: ='4c Bant Walls'!K16 | E315: ='4c Bant Walls'!L16 | F315: ='4c Bant Walls'!M16
A316: Bant Walls | B316: 4c | C316: 12 | D316: ='4c Bant Walls'!K17 | E316: ='4c Bant Walls'!L17 | F316: ='4c Bant Walls'!M17
... A404: Bant Walls | B404: 4c | C404: 100 | D404: ='4c Bant Walls'!K105 | E404: ='4c Bant Walls'!L105 | F404: ='4c Bant Walls'!M105
A405: Lorehold Spirit | B405: 5o | C405: 1 | D405: ='5o Lorehold Spirit'!M6 | E405: ='5o Lorehold Spirit'!N6 | F405: ='5o Lorehold Spirit'!O6
A406: Lorehold Spirit | B406: 5o | C406: 2 | D406: ='5o Lorehold Spirit'!M7 | E406: ='5o Lorehold Spirit'!N7 | F406: ='5o Lorehold Spirit'!O7
A407: Lorehold Spirit | B407: 5o | C407: 3 | D407: ='5o Lorehold Spirit'!M8 | E407: ='5o Lorehold Spirit'!N8 | F407: ='5o Lorehold Spirit'!O8
A408: Lorehold Spirit | B408: 5o | C408: 4 | D408: ='5o Lorehold Spirit'!M9 | E408: ='5o Lorehold Spirit'!N9 | F408: ='5o Lorehold Spirit'!O9
A409: Lorehold Spirit | B409: 5o | C409: 5 | D409: ='5o Lorehold Spirit'!M10 | E409: ='5o Lorehold Spirit'!N10 | F409: ='5o Lorehold Spirit'!O10
A410: Lorehold Spirit | B410: 5o | C410: 6 | D410: ='5o Lorehold Spirit'!M11 | E410: ='5o Lorehold Spirit'!N11 | F410: ='5o Lorehold Spirit'!O11
A411: Lorehold Spirit | B411: 5o | C411: 7 | D411: ='5o Lorehold Spirit'!M12 | E411: ='5o Lorehold Spirit'!N12 | F411: ='5o Lorehold Spirit'!O12
A412: Lorehold Spirit | B412: 5o | C412: 8 | D412: ='5o Lorehold Spirit'!M13 | E412: ='5o Lorehold Spirit'!N13 | F412: ='5o Lorehold Spirit'!O13
A413: Lorehold Spirit | B413: 5o | C413: 9 | D413: ='5o Lorehold Spirit'!M14 | E413: ='5o Lorehold Spirit'!N14 | F413: ='5o Lorehold Spirit'!O14
A414: Lorehold Spirit | B414: 5o | C414: 10 | D414: ='5o Lorehold Spirit'!M15 | E414: ='5o Lorehold Spirit'!N15 | F414: ='5o Lorehold Spirit'!O15
A415: Lorehold Spirit | B415: 5o | C415: 11 | D415: ='5o Lorehold Spirit'!M16 | E415: ='5o Lorehold Spirit'!N16 | F415: ='5o Lorehold Spirit'!O16
A416: Lorehold Spirit | B416: 5o | C416: 12 | D416: ='5o Lorehold Spirit'!M17 | E416: ='5o Lorehold Spirit'!N17 | F416: ='5o Lorehold Spirit'!O17
... A504: Lorehold Spirit | B504: 5o | C504: 100 | D504: ='5o Lorehold Spirit'!M105 | E504: ='5o Lorehold Spirit'!N105 | F504: ='5o Lorehold Spirit'!O105
A505: Sultai ETB Doubling | B505: 6f | C505: 1 | D505: ='6f Sultai ETB Doubling'!K6 | E505: ='6f Sultai ETB Doubling'!L6 | F505: ='6f Sultai ETB Doubling'!M6
A506: Sultai ETB Doubling | B506: 6f | C506: 2 | D506: ='6f Sultai ETB Doubling'!K7 | E506: ='6f Sultai ETB Doubling'!L7 | F506: ='6f Sultai ETB Doubling'!M7
A507: Sultai ETB Doubling | B507: 6f | C507: 3 | D507: ='6f Sultai ETB Doubling'!K8 | E507: ='6f Sultai ETB Doubling'!L8 | F507: ='6f Sultai ETB Doubling'!M8
A508: Sultai ETB Doubling | B508: 6f | C508: 4 | D508: ='6f Sultai ETB Doubling'!K9 | E508: ='6f Sultai ETB Doubling'!L9 | F508: ='6f Sultai ETB Doubling'!M9
A509: Sultai ETB Doubling | B509: 6f | C509: 5 | D509: ='6f Sultai ETB Doubling'!K10 | E509: ='6f Sultai ETB Doubling'!L10 | F509: ='6f Sultai ETB Doubling'!M10
A510: Sultai ETB Doubling | B510: 6f | C510: 6 | D510: ='6f Sultai ETB Doubling'!K11 | E510: ='6f Sultai ETB Doubling'!L11 | F510: ='6f Sultai ETB Doubling'!M11
A511: Sultai ETB Doubling | B511: 6f | C511: 7 | D511: ='6f Sultai ETB Doubling'!K12 | E511: ='6f Sultai ETB Doubling'!L12 | F511: ='6f Sultai ETB Doubling'!M12
A512: Sultai ETB Doubling | B512: 6f | C512: 8 | D512: ='6f Sultai ETB Doubling'!K13 | E512: ='6f Sultai ETB Doubling'!L13 | F512: ='6f Sultai ETB Doubling'!M13
A513: Sultai ETB Doubling | B513: 6f | C513: 9 | D513: ='6f Sultai ETB Doubling'!K14 | E513: ='6f Sultai ETB Doubling'!L14 | F513: ='6f Sultai ETB Doubling'!M14
A514: Sultai ETB Doubling | B514: 6f | C514: 10 | D514: ='6f Sultai ETB Doubling'!K15 | E514: ='6f Sultai ETB Doubling'!L15 | F514: ='6f Sultai ETB Doubling'!M15
A515: Sultai ETB Doubling | B515: 6f | C515: 11 | D515: ='6f Sultai ETB Doubling'!K16 | E515: ='6f Sultai ETB Doubling'!L16 | F515: ='6f Sultai ETB Doubling'!M16
A516: Sultai ETB Doubling | B516: 6f | C516: 12 | D516: ='6f Sultai ETB Doubling'!K17 | E516: ='6f Sultai ETB Doubling'!L17 | F516: ='6f Sultai ETB Doubling'!M17
... A604: Sultai ETB Doubling | B604: 6f | C604: 100 | D604: ='6f Sultai ETB Doubling'!K105 | E604: ='6f Sultai ETB Doubling'!L105 | F604: ='6f Sultai ETB Doubling'!M105
E606: TOTAL | F606: =SUM(F5:F604)

Sheet Notes
A1: Methodology, and what the model cannot see
A3: How a simulated column was produced
A4: The runner builds the list, fetches a candidate pool in the commander's colours, measures a baseline over thousands of games, ranks where the deck actually loses, proposes swaps, re-measures, and repeats until three rounds in a row gain less than 0.75 points. It then replays the original and the optimized list on 5,000 seeds the optimizer never saw. Only that holdout comparison sets the verdict, so a gain that existed only on the tuned seeds is reported as not-confirmed and discarded.
A6: Verdicts
A7: confirmed = the improvement held up on unseen seeds by more than the sampling error. within-noise = ahead, but by less than the error bar. not-confirmed = it only looked better on the seeds it was tuned against. no-change = nothing in the pool beat the list.
A9: Why Enhance-2 and Max-2 were re-verified separately
A10: Those lists were assembled from evidence gathered in separate runs. Assembling a list is not the same as measuring it, so all twelve assembled lists were re-simulated end to end. That check earned its keep: it caught a real bug where a card correctly placed by one stage could be silently evicted by a same-named candidate targeting a different slot, because Commander is singleton. Fixed at the source and re-verified from scratch.
A12: What changed in the v2.1 fun-weighted engine
A13: Three corrections and one scoring change. Corrections: creatures that assign combat damage by toughness (Arcades-style) are now modelled — before, the Bant Walls deck's entire game plan was invisible; planeswalker commanders no longer enter combat as 0-power creatures; and lands reading 'Add {R} or {W}' now produce both colours instead of only the first, which had been overstating mana screw for every multicolour deck (36 real lands affected). Scoring: win rate cut from 0.40 to 0.30 of the composite, with 0.10 given to a fun/participation signal built from how often the deck got to play at all, how much board it developed, and whether the game ran a reasonable length.
A15: The Iroas number is not what it looks like
A16: Iroas measures +13.2 over Quintorius, and that entire margin is a blind spot. The engine does not model devotion, so it treats Iroas as a permanent 7/4 indestructible body. Held to the enchantment it usually is, it scores 59.6 — the same as Quintorius to one decimal. Deck 5's 50 nonland permanents carry 1.22 red/white pips on average, so a normal board of four or five reaches about 5.5 devotion against the 7 Iroas requires. Adopt it for the menace and the damage prevention if you want them; do not adopt it for the measured score.
A18: The Hazel swap is a rebuild, not a tweak
... A28: Scryfall USD at fetch time. A column's total is the full retail value of all 100 cards in it, not the amount still to spend — you already own most of the Base shell.
